{
  "type": "Feature",
  "properties": {
    "gn:admin1_code":"02",
    "gn:asciiname":"Sharshar",
    "gn:country_code":"TJ",
    "gn:dem":725,
    "gn:feature_class":"P",
    "gn:feature_code":"PPL",
    "gn:name":"Sharshar",
    "gn:population":0,
    "gn:timezone":"Asia/Dushanbe",
    "iso:country":"TJ",
    "name:und_x_variant":[
        "\u0428\u0430\u0440\u0448\u0430\u0440"
    ],
    "wof:name":"Sharshar",
    "wof:placetype":"locality"
},
  "geometry": {"coordinates":[68.69539,38.18603],"type":"Point"}
}