{
  "type": "Feature",
  "properties": {
    "gn:admin1_code":"01",
    "gn:asciiname":"Jorf",
    "gn:country_code":"TJ",
    "gn:dem":1348,
    "gn:feature_class":"P",
    "gn:feature_code":"PPL",
    "gn:name":"Jorf",
    "gn:population":0,
    "gn:timezone":"Asia/Dushanbe",
    "iso:country":"TJ",
    "name:und_x_variant":[
        "Javr",
        "Wishkbarv",
        "Dzharf",
        "Dzhorf",
        "Dzhavr",
        "Jorf",
        "\u04b6\u043e\u0440\u0444"
    ],
    "wof:name":"Jorf",
    "wof:placetype":"locality"
},
  "geometry": {"coordinates":[70.96174000000001,38.47848],"type":"Point"}
}