{
  "type": "Feature",
  "properties": {
    "gn:admin1_code":"04",
    "gn:asciiname":"Gurakha",
    "gn:country_code":"TJ",
    "gn:dem":890,
    "gn:feature_class":"P",
    "gn:feature_code":"PPL",
    "gn:name":"Gurakha",
    "gn:population":0,
    "gn:timezone":"Asia/Dushanbe",
    "iso:country":"TJ",
    "wof:name":"Gurakha",
    "wof:placetype":"locality"
},
  "geometry": {"coordinates":[68.76245,38.65033],"type":"Point"}
}