{
  "type": "Feature",
  "properties": {
    "gn:admin1_code":"RR",
    "gn:asciiname":"Panjhok",
    "gn:country_code":"TJ",
    "gn:dem":2303,
    "gn:feature_class":"P",
    "gn:feature_code":"PPL",
    "gn:name":"Panjhok",
    "gn:population":0,
    "gn:timezone":"Asia/Dushanbe",
    "iso:country":"TJ",
    "name:und_x_variant":[
        "Pyandzh-Khok",
        "Pandzhkho",
        "Panjhok",
        "\u041f\u0430\u043d\u04b7\u04b3\u043e\u043a"
    ],
    "wof:name":"Panjhok",
    "wof:placetype":"locality"
},
  "geometry": {"coordinates":[68.77046,39.05289000000001],"type":"Point"}
}