{
  "type": "Feature",
  "properties": {
    "gn:admin1_code":"01",
    "gn:asciiname":"Uist-Dakht",
    "gn:country_code":"TJ",
    "gn:dem":4335,
    "gn:feature_class":"P",
    "gn:feature_code":"PPL",
    "gn:name":"Uist-Dakht",
    "gn:population":0,
    "gn:timezone":"Asia/Dushanbe",
    "iso:country":"TJ",
    "wof:name":"Uist-Dakht",
    "wof:placetype":"locality"
},
  "geometry": {"coordinates":[71.84999999999999,38.45],"type":"Point"}
}