{
  "type": "Feature",
  "properties": {
    "gn:admin1_code":"02",
    "gn:asciiname":"Jida",
    "gn:country_code":"TJ",
    "gn:dem":444,
    "gn:feature_class":"P",
    "gn:feature_code":"PPL",
    "gn:name":"Jida",
    "gn:population":0,
    "gn:timezone":"Asia/Dushanbe",
    "iso:country":"TJ",
    "name:tgk_x_preferred":[
        "Jida"
    ],
    "name:und_x_variant":[
        "Dzhida",
        "Dzhida-Kishlak",
        "\u04b6\u0438\u0434\u0430"
    ],
    "wof:name":"Jida",
    "wof:placetype":"locality"
},
  "geometry": {"coordinates":[69.35244,37.57117],"type":"Point"}
}