{
  "type": "Feature",
  "properties": {
    "gn:admin1_code":"02",
    "gn:asciiname":"Yakkatut",
    "gn:country_code":"TJ",
    "gn:dem":405,
    "gn:feature_class":"P",
    "gn:feature_code":"PPL",
    "gn:name":"Yakkatut",
    "gn:population":0,
    "gn:timezone":"Asia/Dushanbe",
    "iso:country":"TJ",
    "name:und_x_variant":[
        "\u042f\u043a\u043a\u0430\u0442\u0443\u0442",
        "Yakka-Tut"
    ],
    "wof:name":"Yakkatut",
    "wof:placetype":"locality"
},
  "geometry": {"coordinates":[68.74335000000001,37.76324],"type":"Point"}
}