{
  "type": "Feature",
  "properties": {
    "gn:admin1_code":"03",
    "gn:asciiname":"Shing",
    "gn:country_code":"TJ",
    "gn:dem":1446,
    "gn:feature_class":"P",
    "gn:feature_code":"PPL",
    "gn:name":"Shing",
    "gn:population":0,
    "gn:timezone":"Asia/Dushanbe",
    "iso:country":"TJ",
    "name:und_x_variant":[
        "Shink",
        "Shing-Dar\u2019ya",
        "Shing",
        "\u0428\u0438\u043d\u0433"
    ],
    "wof:name":"Shing",
    "wof:placetype":"locality"
},
  "geometry": {"coordinates":[67.80663,39.2817],"type":"Point"}
}