{
  "type": "Feature",
  "properties": {
    "gn:admin1_code":"03",
    "gn:asciiname":"Tavoqbuloq",
    "gn:country_code":"TJ",
    "gn:dem":1166,
    "gn:feature_class":"P",
    "gn:feature_code":"PPL",
    "gn:name":"Tavoqbuloq",
    "gn:population":0,
    "gn:timezone":"Asia/Dushanbe",
    "iso:country":"TJ",
    "name:und_x_variant":[
        "\u0422\u0430\u0432\u043e\u049b\u0431\u0443\u043b\u043e\u049b",
        "Tabokbulok"
    ],
    "wof:name":"Tavoqbuloq",
    "wof:placetype":"locality"
},
  "geometry": {"coordinates":[68.6617,39.8295],"type":"Point"}
}