{
  "type": "Feature",
  "properties": {
    "gn:admin1_code":"02",
    "gn:asciiname":"Kakhramon",
    "gn:country_code":"TJ",
    "gn:dem":369,
    "gn:feature_class":"P",
    "gn:feature_code":"PPL",
    "gn:name":"Kakhramon",
    "gn:population":0,
    "gn:timezone":"Asia/Dushanbe",
    "iso:country":"TJ",
    "wof:name":"Kakhramon",
    "wof:placetype":"locality"
},
  "geometry": {"coordinates":[68.13123,37.27791],"type":"Point"}
}