{
  "type": "Feature",
  "properties": {
    "gn:admin1_code":"02",
    "gn:asciiname":"Toirsu",
    "gn:country_code":"TJ",
    "gn:dem":463,
    "gn:feature_class":"P",
    "gn:feature_code":"PPL",
    "gn:name":"Toirsu",
    "gn:population":0,
    "gn:timezone":"Asia/Dushanbe",
    "iso:country":"TJ",
    "name:tgk_x_preferred":[
        "Tairsu"
    ],
    "name:und_x_variant":[
        "\u0422\u043e\u0438\u0440\u0441\u0443"
    ],
    "wof:name":"Toirsu",
    "wof:placetype":"locality"
},
  "geometry": {"coordinates":[69.33919,37.66162],"type":"Point"}
}