{
  "type": "Feature",
  "properties": {
    "gn:admin1_code":"02",
    "gn:asciiname":"Zarkamar",
    "gn:country_code":"TJ",
    "gn:dem":423,
    "gn:feature_class":"P",
    "gn:feature_code":"PPL",
    "gn:name":"Zarkamar",
    "gn:population":0,
    "gn:timezone":"Asia/Dushanbe",
    "iso:country":"TJ",
    "name:und_x_variant":[
        "\u0417\u0430\u0440\u043a\u0430\u043c\u0430\u0440"
    ],
    "wof:name":"Zarkamar",
    "wof:placetype":"locality"
},
  "geometry": {"coordinates":[68.1478,37.51886],"type":"Point"}
}