{
  "type": "Feature",
  "properties": {
    "gn:admin1_code":"02",
    "gn:asciiname":"Sultonobod",
    "gn:country_code":"TJ",
    "gn:dem":447,
    "gn:feature_class":"P",
    "gn:feature_code":"PPL",
    "gn:name":"Sultonobod",
    "gn:population":0,
    "gn:timezone":"Asia/Dushanbe",
    "iso:country":"TJ",
    "name:ckb_x_preferred":[
        "\u0633\u0648\u06b5\u062a\u0627\u0646\u0627\u0628\u0627\u062f"
    ],
    "name:fas_x_preferred":[
        "\u0633\u0644\u0637\u0627\u0646\u200c\u0622\u0628\u0627\u062f"
    ],
    "name:uzb_x_preferred":[
        "Sultonobod"
    ],
    "wof:name":"Sultonobod",
    "wof:placetype":"locality"
},
  "geometry": {"coordinates":[68.12555,37.61791],"type":"Point"}
}