{
  "type": "Feature",
  "properties": {
    "gn:admin1_code":"02",
    "gn:asciiname":"Sultonobod",
    "gn:country_code":"TJ",
    "gn:dem":447,
    "gn:feature_class":"P",
    "gn:feature_code":"PPL",
    "gn:name":"Sultonobod",
    "gn:population":0,
    "gn:timezone":"Asia/Dushanbe",
    "iso:country":"TJ",
    "name:uzb_x_preferred":[
        "Sultonobod"
    ],
    "wof:name":"Sultonobod",
    "wof:placetype":"locality"
},
  "geometry": {"coordinates":[68.12555,37.61791],"type":"Point"}
}