{
  "type": "Feature",
  "properties": {
    "gn:admin1_code":"RR",
    "gn:asciiname":"Oqmachit",
    "gn:country_code":"TJ",
    "gn:dem":654,
    "gn:feature_class":"P",
    "gn:feature_code":"PPL",
    "gn:name":"Oqmachit",
    "gn:population":0,
    "gn:timezone":"Asia/Dushanbe",
    "iso:country":"TJ",
    "name:und_x_variant":[
        "Ak-Mechet\u2019",
        "Oqmachit"
    ],
    "wof:name":"Oqmachit",
    "wof:placetype":"locality"
},
  "geometry": {"coordinates":[68.17749999999999,38.47528],"type":"Point"}
}