{
  "type": "Feature",
  "properties": {
    "gn:admin1_code":"02",
    "gn:asciiname":"Hayotinav",
    "gn:country_code":"TJ",
    "gn:dem":490,
    "gn:feature_class":"P",
    "gn:feature_code":"PPL",
    "gn:name":"Hayotinav",
    "gn:population":0,
    "gn:timezone":"Asia/Dushanbe",
    "iso:country":"TJ",
    "name:und_x_variant":[
        "\u04b2\u0430\u0451\u0442\u0438\u043d\u0430\u0432"
    ],
    "wof:name":"Hayotinav",
    "wof:placetype":"locality"
},
  "geometry": {"coordinates":[68.63229,37.92292],"type":"Point"}
}