{
  "type": "Feature",
  "properties": {
    "gn:admin1_code":"RR",
    "gn:asciiname":"Nimichi-Poyen",
    "gn:country_code":"TJ",
    "gn:dem":1534,
    "gn:feature_class":"P",
    "gn:feature_code":"PPL",
    "gn:name":"Nimichi-Poy\u00ebn",
    "gn:population":0,
    "gn:timezone":"Asia/Dushanbe",
    "iso:country":"TJ",
    "name:und_x_variant":[
        "Mimichi",
        "Nimicha",
        "Nimichi",
        "Nimichi-Poy\u00ebn"
    ],
    "wof:name":"Nimichi-Poyen",
    "wof:placetype":"locality"
},
  "geometry": {"coordinates":[70.67358,39.10055],"type":"Point"}
}