{
  "type": "Feature",
  "properties": {
    "gn:admin1_code":"03",
    "gn:asciiname":"Langar",
    "gn:country_code":"TJ",
    "gn:dem":604,
    "gn:feature_class":"P",
    "gn:feature_code":"PPL",
    "gn:name":"Langar",
    "gn:population":0,
    "gn:timezone":"Asia/Dushanbe",
    "iso:country":"TJ",
    "name:und_x_variant":[
        "Lyangar",
        "Langar",
        "\u041b\u0430\u043d\u0433\u0430\u0440"
    ],
    "wof:name":"Langar",
    "wof:placetype":"locality"
},
  "geometry": {"coordinates":[69.32134000000001,40.05946],"type":"Point"}
}