{
  "type": "Feature",
  "properties": {
    "gn:admin1_code":"02",
    "gn:asciiname":"Tigavun",
    "gn:country_code":"TJ",
    "gn:dem":1695,
    "gn:feature_class":"P",
    "gn:feature_code":"PPL",
    "gn:name":"Tigavun",
    "gn:population":0,
    "gn:timezone":"Asia/Dushanbe",
    "iso:country":"TJ",
    "wof:name":"Tigavun",
    "wof:placetype":"locality"
},
  "geometry": {"coordinates":[70.24375000000001,38.50254],"type":"Point"}
}