{
  "type": "Feature",
  "properties": {
    "gn:admin1_code":"02",
    "gn:asciiname":"Chinortugay",
    "gn:country_code":"TJ",
    "gn:dem":431,
    "gn:feature_class":"P",
    "gn:feature_code":"PPL",
    "gn:name":"Chinort\u016dgay",
    "gn:population":0,
    "gn:timezone":"Asia/Dushanbe",
    "iso:country":"TJ",
    "name:und_x_variant":[
        "Chinort\u016dgay",
        "\u0427\u0438\u043d\u043e\u043f\u0442\u04ef\u0433\u0430\u0439"
    ],
    "wof:name":"Chinortugay",
    "wof:placetype":"locality"
},
  "geometry": {"coordinates":[68.13599000000001,37.55113],"type":"Point"}
}