{
  "type": "Feature",
  "properties": {
    "gn:admin1_code":"RR",
    "gn:asciiname":"Zachau",
    "gn:country_code":"TJ",
    "gn:dem":1885,
    "gn:feature_class":"P",
    "gn:feature_code":"PPL",
    "gn:name":"Zachau",
    "gn:population":0,
    "gn:timezone":"Asia/Dushanbe",
    "iso:country":"TJ",
    "wof:name":"Zachau",
    "wof:placetype":"locality"
},
  "geometry": {"coordinates":[68.53384,38.76255],"type":"Point"}
}