{
  "type": "Feature",
  "properties": {
    "gn:admin1_code":"RR",
    "gn:asciiname":"Churk-Kishlak",
    "gn:country_code":"TJ",
    "gn:dem":1107,
    "gn:feature_class":"P",
    "gn:feature_code":"PPL",
    "gn:name":"Churk-Kishlak",
    "gn:population":0,
    "gn:timezone":"Asia/Dushanbe",
    "iso:country":"TJ",
    "name:und_x_variant":[
        "Chur-Kishlak",
        "Churk-Kishlak"
    ],
    "wof:name":"Churk-Kishlak",
    "wof:placetype":"locality"
},
  "geometry": {"coordinates":[68.44789,38.40589],"type":"Point"}
}