{
  "type": "Feature",
  "properties": {
    "gn:admin1_code":"RR",
    "gn:asciiname":"Akuyli",
    "gn:country_code":"TJ",
    "gn:dem":706,
    "gn:feature_class":"P",
    "gn:feature_code":"PPL",
    "gn:name":"Akuyli",
    "gn:population":0,
    "gn:timezone":"Asia/Dushanbe",
    "iso:country":"TJ",
    "wof:name":"Akuyli",
    "wof:placetype":"locality"
},
  "geometry": {"coordinates":[68.59999999999999,38.46667],"type":"Point"}
}