{
  "type": "Feature",
  "properties": {
    "gn:admin1_code":"RR",
    "gn:asciiname":"Duchinora",
    "gn:country_code":"TJ",
    "gn:dem":919,
    "gn:feature_class":"P",
    "gn:feature_code":"PPL",
    "gn:name":"Duchinora",
    "gn:population":0,
    "gn:timezone":"Asia/Dushanbe",
    "iso:country":"TJ",
    "name:und_x_variant":[
        "Duchinor",
        "Duchinora"
    ],
    "wof:name":"Duchinora",
    "wof:placetype":"locality"
},
  "geometry": {"coordinates":[68.56249,38.57654],"type":"Point"}
}