{
  "type": "Feature",
  "properties": {
    "gn:admin1_code":"02",
    "gn:asciiname":"Eligovora",
    "gn:country_code":"TJ",
    "gn:dem":2059,
    "gn:feature_class":"P",
    "gn:feature_code":"PPL",
    "gn:name":"\u0116ligovora",
    "gn:population":0,
    "gn:timezone":"Asia/Dushanbe",
    "iso:country":"TJ",
    "name:rus_x_preferred":[
        "\u0116ligovora"
    ],
    "name:rus_x_variant":[
        "Il\u2019govar"
    ],
    "wof:name":"Eligovora",
    "wof:placetype":"locality"
},
  "geometry": {"coordinates":[70.31119,38.30128],"type":"Point"}
}