{
  "type": "Feature",
  "properties": {
    "gn:admin1_code":"03",
    "gn:asciiname":"Gumbazi",
    "gn:country_code":"TJ",
    "gn:dem":804,
    "gn:feature_class":"P",
    "gn:feature_code":"PPL",
    "gn:name":"Gumbazi",
    "gn:population":0,
    "gn:timezone":"Asia/Dushanbe",
    "iso:country":"TJ",
    "name:uzb_x_preferred":[
        "Gumbazi"
    ],
    "wof:name":"Gumbazi",
    "wof:placetype":"locality"
},
  "geometry": {"coordinates":[70.62283000000002,40.14159],"type":"Point"}
}