{
  "type": "Feature",
  "properties": {
    "gn:admin1_code":"03",
    "gn:asciiname":"Tiogli",
    "gn:country_code":"TJ",
    "gn:dem":2702,
    "gn:feature_class":"P",
    "gn:feature_code":"PPL",
    "gn:name":"Tiogli",
    "gn:population":0,
    "gn:timezone":"Asia/Dushanbe",
    "iso:country":"TJ",
    "name:und_x_variant":[
        "\u0422\u0438\u043e\u0433\u043b\u0438"
    ],
    "wof:name":"Tiogli",
    "wof:placetype":"locality"
},
  "geometry": {"coordinates":[67.88032,39.14226],"type":"Point"}
}