{
  "type": "Feature",
  "properties": {
    "gn:admin1_code":"01",
    "gn:asciiname":"Kamchak",
    "gn:country_code":"TJ",
    "gn:dem":2551,
    "gn:feature_class":"P",
    "gn:feature_code":"PPL",
    "gn:name":"Kamchak",
    "gn:population":0,
    "gn:timezone":"Asia/Dushanbe",
    "iso:country":"TJ",
    "name:und_x_variant":[
        "\u041a\u0430\u043c\u0447\u0430\u043a"
    ],
    "wof:name":"Kamchak",
    "wof:placetype":"locality"
},
  "geometry": {"coordinates":[70.67746,38.65426],"type":"Point"}
}