{
  "type": "Feature",
  "properties": {
    "gn:admin1_code":"01",
    "gn:asciiname":"Shanbede",
    "gn:country_code":"TJ",
    "gn:dem":2412,
    "gn:feature_class":"P",
    "gn:feature_code":"PPL",
    "gn:name":"Shanbede",
    "gn:population":0,
    "gn:timezone":"Asia/Dushanbe",
    "iso:country":"TJ",
    "name:und_x_variant":[
        "Shambede",
        "Shambidy",
        "Shanbede",
        "\u0428\u0430\u043d\u0431\u0435\u0434\u0435"
    ],
    "wof:name":"Shanbede",
    "wof:placetype":"locality"
},
  "geometry": {"coordinates":[71.44703,37.09607000000001],"type":"Point"}
}