{
  "type": "Feature",
  "properties": {
    "gn:admin1_code":"03",
    "gn:asciiname":"Nafaroch",
    "gn:country_code":"TJ",
    "gn:dem":1191,
    "gn:feature_class":"P",
    "gn:feature_code":"PPL",
    "gn:name":"Nafaroch",
    "gn:population":0,
    "gn:timezone":"Asia/Dushanbe",
    "iso:country":"TJ",
    "name:und_x_variant":[
        "Nau-Farach",
        "Nafarodzh",
        "Nafaroch"
    ],
    "wof:name":"Nafaroch",
    "wof:placetype":"locality"
},
  "geometry": {"coordinates":[68.99061,39.8304],"type":"Point"}
}