{
  "type": "Feature",
  "properties": {
    "gn:admin1_code":"03",
    "gn:asciiname":"Gazantarak",
    "gn:country_code":"TJ",
    "gn:dem":899,
    "gn:feature_class":"P",
    "gn:feature_code":"PPL",
    "gn:name":"Gazantarak",
    "gn:population":0,
    "gn:timezone":"Asia/Dushanbe",
    "iso:country":"TJ",
    "name:ceb_x_preferred":[
        "Gazantarak"
    ],
    "name:fas_x_preferred":[
        "\u06af\u0632\u0646\u062a\u0631\u06a9"
    ],
    "name:msa_x_preferred":[
        "Gazantarak"
    ],
    "name:tgk_x_preferred":[
        "\u0414\u0435\u04b3\u043e\u0442\u0438 \u0492\u0430\u0437\u0430\u043d\u0442\u0430\u0440\u0430\u043a"
    ],
    "name:und_x_variant":[
        "\u0413\u0430\u0437\u0430\u043d\u0442\u0430\u0440\u0430\u043a"
    ],
    "name:urd_x_preferred":[
        "\u06af\u0632\u0627\u0646\u062a\u0631\u06a9"
    ],
    "wof:name":"Gazantarak",
    "wof:placetype":"locality"
},
  "geometry": {"coordinates":[69.13704,39.9701],"type":"Point"}
}