{
  "type": "Feature",
  "properties": {
    "gn:admin1_code":"03",
    "gn:asciiname":"Gazantarak",
    "gn:country_code":"TJ",
    "gn:dem":899,
    "gn:feature_class":"P",
    "gn:feature_code":"PPL",
    "gn:name":"Gazantarak",
    "gn:population":0,
    "gn:timezone":"Asia/Dushanbe",
    "iso:country":"TJ",
    "name:und_x_variant":[
        "\u0413\u0430\u0437\u0430\u043d\u0442\u0430\u0440\u0430\u043a"
    ],
    "wof:name":"Gazantarak",
    "wof:placetype":"locality"
},
  "geometry": {"coordinates":[69.13704,39.9701],"type":"Point"}
}