{
  "type": "Feature",
  "properties": {
    "gn:admin1_code":"03",
    "gn:asciiname":"Moykatta",
    "gn:country_code":"TJ",
    "gn:dem":1058,
    "gn:feature_class":"P",
    "gn:feature_code":"PPL",
    "gn:name":"Moykatta",
    "gn:population":0,
    "gn:timezone":"Asia/Dushanbe",
    "iso:country":"TJ",
    "name:und_x_variant":[
        "Maykota",
        "Maykata",
        "Maikota",
        "Maykatta",
        "Moykatta",
        "\u041c\u043e\u04e3\u043a\u0430\u0442\u0442\u0430"
    ],
    "wof:name":"Moykatta",
    "wof:placetype":"locality"
},
  "geometry": {"coordinates":[67.76772,39.52027],"type":"Point"}
}