{
  "type": "Feature",
  "properties": {
    "gn:admin1_code":"02",
    "gn:asciiname":"Imeni Voroshilova",
    "gn:country_code":"TJ",
    "gn:dem":363,
    "gn:feature_class":"P",
    "gn:feature_code":"PPL",
    "gn:name":"Imeni Voroshilova",
    "gn:population":0,
    "gn:timezone":"Asia/Dushanbe",
    "iso:country":"TJ",
    "wof:name":"Imeni Voroshilova",
    "wof:placetype":"locality"
},
  "geometry": {"coordinates":[68.23333000000001,37.11667],"type":"Point"}
}