{
  "type": "Feature",
  "properties": {
    "gn:country":"TJ",
    "gn:fcode":"PPLA2",
    "gn:pop":8700,
    "iso:country":"TJ",
    "name:bul_x_preferred":[
        "\u0414\u0443\u0441\u0442\u0438"
    ],
    "name:ceb_x_preferred":[
        "D\u016dst\u00ed"
    ],
    "name:eng_x_preferred":[
        "Dusti"
    ],
    "name:fas_x_preferred":[
        "\u062f\u0648\u0633\u062a\u06cc"
    ],
    "name:nld_x_preferred":[
        "Dusti"
    ],
    "name:pol_x_preferred":[
        "Dusti"
    ],
    "name:pus_x_preferred":[
        "\u062f\u0633\u062a\u064a"
    ],
    "name:rus_x_preferred":[
        "\u0414\u0443\u0441\u0442\u0438"
    ],
    "name:tgk_x_preferred":[
        "D\u016dsty"
    ],
    "name:tgk_x_variant":[
        "\u0414\u04ef\u0441\u0442\u04e3"
    ],
    "name:unk_x_variant":[
        "Molotovabad"
    ],
    "qs:name":"D\u016dst\u00ed",
    "qs:photos_9r":0,
    "qs:photos_sr":0,
    "qs:pop_sr":"5",
    "wof:name":"D\u016dst\u00ed",
    "wof:placetype":"locality",
    "wof:population":8700
},
  "geometry": {"coordinates":[68.66398,37.34812],"type":"Point"}
}