{
  "type": "Feature",
  "properties": {
    "gn:admin1_code":"RR",
    "gn:asciiname":"Durmonbuloq",
    "gn:country_code":"TJ",
    "gn:dem":983,
    "gn:feature_class":"P",
    "gn:feature_code":"PPL",
    "gn:name":"Durmonbuloq",
    "gn:population":0,
    "gn:timezone":"Asia/Dushanbe",
    "iso:country":"TJ",
    "name:und_x_variant":[
        "Durmanbulok",
        "Durmonbuloq"
    ],
    "wof:name":"Durmonbuloq",
    "wof:placetype":"locality"
},
  "geometry": {"coordinates":[68.40694000000001,38.43867],"type":"Point"}
}