{
  "type": "Feature",
  "properties": {
    "gn:admin1_code":"02",
    "gn:asciiname":"Toshguzar",
    "gn:country_code":"TJ",
    "gn:dem":567,
    "gn:feature_class":"P",
    "gn:feature_code":"PPL",
    "gn:name":"Toshguzar",
    "gn:population":0,
    "gn:timezone":"Asia/Dushanbe",
    "iso:country":"TJ",
    "name:tgk_x_preferred":[
        "Toshguzar"
    ],
    "name:und_x_variant":[
        "Tash-Guzar",
        "Tash-Guzan",
        "\u0422\u043e\u0448\u0433\u0443\u0437\u0430\u0440"
    ],
    "wof:name":"Toshguzar",
    "wof:placetype":"locality"
},
  "geometry": {"coordinates":[69.27494,37.90129],"type":"Point"}
}