{
  "type": "Feature",
  "properties": {
    "gn:admin1_code":"03",
    "gn:asciiname":"Kichikayri",
    "gn:country_code":"TJ",
    "gn:dem":578,
    "gn:feature_class":"P",
    "gn:feature_code":"PPL",
    "gn:name":"Kichikayr\u00ed",
    "gn:population":0,
    "gn:timezone":"Asia/Dushanbe",
    "iso:country":"TJ",
    "name:und_x_variant":[
        "Kichikayr\u00ed",
        "\u041a\u0438\u0447\u0438\u043a\u0430\u0439\u0440\u04e3"
    ],
    "wof:name":"Kichikayri",
    "wof:placetype":"locality"
},
  "geometry": {"coordinates":[69.45638000000001,40.36457],"type":"Point"}
}