{
  "type": "Feature",
  "properties": {
    "gn:admin1_code":"RR",
    "gn:asciiname":"Bongura",
    "gn:country_code":"TJ",
    "gn:dem":996,
    "gn:feature_class":"P",
    "gn:feature_code":"PPL",
    "gn:name":"Bongura",
    "gn:population":0,
    "gn:timezone":"Asia/Dushanbe",
    "iso:country":"TJ",
    "wof:name":"Bongura",
    "wof:placetype":"locality"
},
  "geometry": {"coordinates":[69.09473,38.61491],"type":"Point"}
}