{
  "type": "Feature",
  "properties": {
    "gn:admin1_code":"02",
    "gn:asciiname":"Pyandzhsola",
    "gn:country_code":"TJ",
    "gn:dem":529,
    "gn:feature_class":"P",
    "gn:feature_code":"PPL",
    "gn:name":"Pyandzhsola",
    "gn:population":0,
    "gn:timezone":"Asia/Dushanbe",
    "iso:country":"TJ",
    "wof:name":"Pyandzhsola",
    "wof:placetype":"locality"
},
  "geometry": {"coordinates":[69.73921,37.88366],"type":"Point"}
}