{
  "type": "Feature",
  "properties": {
    "gn:admin1_code":"RR",
    "gn:asciiname":"Buyrabov",
    "gn:country_code":"TJ",
    "gn:dem":726,
    "gn:feature_class":"P",
    "gn:feature_code":"PPL",
    "gn:name":"Buyrabov",
    "gn:population":0,
    "gn:timezone":"Asia/Dushanbe",
    "iso:country":"TJ",
    "wof:name":"Buyrabov",
    "wof:placetype":"locality"
},
  "geometry": {"coordinates":[68.68413000000001,38.49501],"type":"Point"}
}