{
  "type": "Feature",
  "properties": {
    "gn:admin1_code":"00",
    "gn:asciiname":"Muk",
    "gn:country_code":"TJ",
    "gn:dem":2206,
    "gn:feature_class":"P",
    "gn:feature_code":"PPL",
    "gn:name":"Muk",
    "gn:population":0,
    "gn:timezone":"Asia/Dushanbe",
    "iso:country":"TJ",
    "wof:name":"Muk",
    "wof:placetype":"locality"
},
  "geometry": {"coordinates":[71.56546,39.1501],"type":"Point"}
}