{
  "type": "Feature",
  "properties": {
    "gn:admin1_code":"03",
    "gn:asciiname":"Mehtar",
    "gn:country_code":"TJ",
    "gn:dem":581,
    "gn:feature_class":"P",
    "gn:feature_code":"PPL",
    "gn:name":"Mehtar",
    "gn:population":0,
    "gn:timezone":"Asia/Dushanbe",
    "iso:country":"TJ",
    "name:und_x_variant":[
        "\u041c\u0435\u04b3\u0442\u0430\u0440"
    ],
    "wof:name":"Mehtar",
    "wof:placetype":"locality"
},
  "geometry": {"coordinates":[69.30696999999999,40.05849],"type":"Point"}
}