{
  "type": "Feature",
  "properties": {
    "gn:admin1_code":"RR",
    "gn:asciiname":"Shulum",
    "gn:country_code":"TJ",
    "gn:dem":856,
    "gn:feature_class":"P",
    "gn:feature_code":"PPL",
    "gn:name":"Shulum",
    "gn:population":0,
    "gn:timezone":"Asia/Dushanbe",
    "iso:country":"TJ",
    "name:und_x_variant":[
        "Shulyum",
        "Shulum"
    ],
    "wof:name":"Shulum",
    "wof:placetype":"locality"
},
  "geometry": {"coordinates":[68.27807,38.34515],"type":"Point"}
}