{
  "type": "Feature",
  "properties": {
    "gn:admin1_code":"01",
    "gn:asciiname":"Roharv",
    "gn:country_code":"TJ",
    "gn:dem":2317,
    "gn:feature_class":"P",
    "gn:feature_code":"PPL",
    "gn:name":"Roharv",
    "gn:population":0,
    "gn:timezone":"Asia/Dushanbe",
    "iso:country":"TJ",
    "name:tgk_x_preferred":[
        "Roshorv"
    ],
    "name:tgk_x_variant":[
        "\u0420\u043e\u0448\u043e\u0440\u0432"
    ],
    "name:und_x_variant":[
        "Rousharv",
        "Rokharv",
        "Roharv",
        "\u0420\u043e\u04b3\u0430\u0440\u0432"
    ],
    "wof:name":"Roharv",
    "wof:placetype":"locality"
},
  "geometry": {"coordinates":[71.3323,38.02517],"type":"Point"}
}