{
  "type": "Feature",
  "properties": {
    "gn:admin1_code":"01",
    "gn:asciiname":"Farkingi",
    "gn:country_code":"TJ",
    "gn:dem":2262,
    "gn:feature_class":"P",
    "gn:feature_code":"PPL",
    "gn:name":"Farkingi",
    "gn:population":0,
    "gn:timezone":"Asia/Dushanbe",
    "iso:country":"TJ",
    "name:und_x_variant":[
        "Farkingy",
        "\u0444\u0430\u0440\u043a\u0438\u043d\u0433\u0438"
    ],
    "wof:name":"Farkingi",
    "wof:placetype":"locality"
},
  "geometry": {"coordinates":[70.72371,38.69611],"type":"Point"}
}