{
  "type": "Feature",
  "properties": {
    "gn:admin1_code":"02",
    "gn:asciiname":"Frunze",
    "gn:country_code":"TJ",
    "gn:dem":402,
    "gn:feature_class":"P",
    "gn:feature_code":"PPL",
    "gn:name":"Frunze",
    "gn:population":0,
    "gn:timezone":"Asia/Dushanbe",
    "iso:country":"TJ",
    "name:und_x_variant":[
        "\u0424\u0440\u0443\u043d\u0437\u0435"
    ],
    "wof:name":"Frunze",
    "wof:placetype":"locality"
},
  "geometry": {"coordinates":[68.66231999999999,37.82015],"type":"Point"}
}