{
  "type": "Feature",
  "properties": {
    "gn:country":"TJ",
    "gn:fcode":"PPL",
    "gn:population":10771,
    "iso:country":"TJ",
    "name:ara_x_preferred":[
        "\u063a\u0631\u0645"
    ],
    "name:ceb_x_preferred":[
        "Rasht"
    ],
    "name:deu_x_preferred":[
        "Garm"
    ],
    "name:diq_x_preferred":[
        "\u011eerm"
    ],
    "name:eng_x_preferred":[
        "Gharm"
    ],
    "name:fas_x_preferred":[
        "\u063a\u0631\u0645"
    ],
    "name:fra_x_preferred":[
        "Garm"
    ],
    "name:ita_x_preferred":[
        "Garm"
    ],
    "name:jpn_x_preferred":[
        "\u30ac\u30eb\u30e0"
    ],
    "name:kor_x_preferred":[
        "\uac00\ub984"
    ],
    "name:lit_x_preferred":[
        "Garmas"
    ],
    "name:msa_x_preferred":[
        "Gharm"
    ],
    "name:nld_x_preferred":[
        "Gharm"
    ],
    "name:pol_x_preferred":[
        "Garm"
    ],
    "name:ron_x_preferred":[
        "Garm"
    ],
    "name:rus_x_preferred":[
        "\u0413\u0430\u0440\u043c"
    ],
    "name:spa_x_preferred":[
        "Jarm"
    ],
    "name:tgk_x_preferred":[
        "\u0492\u0430\u0440\u043c"
    ],
    "name:urd_x_preferred":[
        "\u063a\u0631\u0645"
    ],
    "qs:name":"Rasht",
    "qs:photos_9r":0,
    "qs:photos_sr":0,
    "qs:pop_sr":"6",
    "wd:wordcount":2108,
    "wof:name":"Rasht",
    "wof:placetype":"locality",
    "wof:population":10771
},
  "geometry": {"coordinates":[70.37446,39.02872],"type":"Point"}
}