{
  "type": "Feature",
  "properties": {
    "gn:admin1_code":"01",
    "gn:asciiname":"Manem",
    "gn:country_code":"TJ",
    "gn:dem":2313,
    "gn:feature_class":"P",
    "gn:feature_code":"PPL",
    "gn:name":"Manem",
    "gn:population":0,
    "gn:timezone":"Asia/Dushanbe",
    "iso:country":"TJ",
    "name:und_x_variant":[
        "\u041c\u0430\u043d\u0435\u043c"
    ],
    "wof:name":"Manem",
    "wof:placetype":"locality"
},
  "geometry": {"coordinates":[71.6883,37.54261],"type":"Point"}
}