{
  "type": "Feature",
  "properties": {
    "gn:admin1_code":"02",
    "gn:asciiname":"Pakhtakor",
    "gn:country_code":"TJ",
    "gn:dem":393,
    "gn:feature_class":"P",
    "gn:feature_code":"PPL",
    "gn:name":"Pakhtakor",
    "gn:population":0,
    "gn:timezone":"Asia/Dushanbe",
    "iso:country":"TJ",
    "name:tgk_x_preferred":[
        "Pakhtakor"
    ],
    "name:und_x_variant":[
        "\u041f\u0430\u0445\u0442\u0430\u043a\u043e\u0440"
    ],
    "wof:name":"Pakhtakor",
    "wof:placetype":"locality"
},
  "geometry": {"coordinates":[68.6563,37.37949],"type":"Point"}
}