{
  "type": "Feature",
  "properties": {
    "gn:admin1_code":"02",
    "gn:asciiname":"Qushachinor",
    "gn:country_code":"TJ",
    "gn:dem":387,
    "gn:feature_class":"P",
    "gn:feature_code":"PPL",
    "gn:name":"Q\u016dshachinor",
    "gn:population":0,
    "gn:timezone":"Asia/Dushanbe",
    "iso:country":"TJ",
    "name:tgk_x_preferred":[
        "Kushachinor"
    ],
    "name:und_x_variant":[
        "Koshachinor",
        "Kushaginor",
        "Koshachinar",
        "Q\u016dshachinor",
        "\u049a\u04ef\u0448\u0430\u0447\u0438\u043d\u043e\u0440"
    ],
    "name:uzb_x_preferred":[
        "Qo\u2018shachinor"
    ],
    "wof:name":"Qushachinor",
    "wof:placetype":"locality"
},
  "geometry": {"coordinates":[68.18755,37.34781],"type":"Point"}
}