{
  "type": "Feature",
  "properties": {
    "gn:admin1_code":"RR",
    "gn:asciiname":"Shurobiagon",
    "gn:country_code":"TJ",
    "gn:dem":823,
    "gn:feature_class":"P",
    "gn:feature_code":"PPL",
    "gn:name":"Shurobiagon",
    "gn:population":0,
    "gn:timezone":"Asia/Dushanbe",
    "iso:country":"TJ",
    "name:und_x_variant":[
        "Shurob",
        "Shurobiagon"
    ],
    "wof:name":"Shurobiagon",
    "wof:placetype":"locality"
},
  "geometry": {"coordinates":[68.61796,38.54596],"type":"Point"}
}