{
  "type": "Feature",
  "properties": {
    "gn:admin1_code":"01",
    "gn:asciiname":"Tem",
    "gn:country_code":"TJ",
    "gn:dem":2083,
    "gn:feature_class":"P",
    "gn:feature_code":"PPL",
    "gn:name":"Tem",
    "gn:population":0,
    "gn:timezone":"Asia/Dushanbe",
    "iso:country":"TJ",
    "name:ceb_x_preferred":[
        "Tem"
    ],
    "name:fin_x_preferred":[
        "Tem"
    ],
    "name:fra_x_preferred":[
        "Tem"
    ],
    "name:pol_x_preferred":[
        "Tem"
    ],
    "name:por_x_preferred":[
        "Tem"
    ],
    "name:spa_x_preferred":[
        "Tem"
    ],
    "name:swe_x_preferred":[
        "Tem"
    ],
    "name:und_x_variant":[
        "\u0422\u0435\u043c"
    ],
    "name:vie_x_preferred":[
        "Tem"
    ],
    "wof:name":"Tem",
    "wof:placetype":"locality"
},
  "geometry": {"coordinates":[71.5078,37.52415],"type":"Point"}
}