{
  "type": "Feature",
  "properties": {
    "gn:admin1_code":"02",
    "gn:asciiname":"Pushiyon",
    "gn:country_code":"TJ",
    "gn:dem":750,
    "gn:feature_class":"P",
    "gn:feature_code":"PPL",
    "gn:name":"Pushiyon",
    "gn:population":0,
    "gn:timezone":"Asia/Dushanbe",
    "iso:country":"TJ",
    "name:und_x_variant":[
        "Pushion Miona",
        "Pushiy\u00ebn-Miy\u00ebna",
        "Pushiy\u00ebn",
        "Pushiyon",
        "\u041f\u0443\u0448\u0438\u0451\u043d"
    ],
    "wof:name":"Pushiyon",
    "wof:placetype":"locality"
},
  "geometry": {"coordinates":[69.79361,38.03854000000001],"type":"Point"}
}