{
  "type": "Feature",
  "properties": {
    "gn:admin1_code":"RR",
    "gn:asciiname":"Kofarnihon",
    "gn:country_code":"TJ",
    "gn:dem":950,
    "gn:feature_class":"P",
    "gn:feature_code":"PPL",
    "gn:name":"Kofarnihon",
    "gn:population":0,
    "gn:timezone":"Asia/Dushanbe",
    "iso:country":"TJ",
    "name:und_x_variant":[
        "Kafiringan",
        "Kofarniqon",
        "Kafirnigan",
        "Kafirnihan",
        "Kofarnikhon",
        "Kofarnihon"
    ],
    "wof:name":"Kofarnihon",
    "wof:placetype":"locality"
},
  "geometry": {"coordinates":[69.10863000000001,38.5996],"type":"Point"}
}