{
  "type": "Feature",
  "properties": {
    "gn:admin1_code":"RR",
    "gn:asciiname":"Alisurkhon",
    "gn:country_code":"TJ",
    "gn:dem":2090,
    "gn:feature_class":"P",
    "gn:feature_code":"PPL",
    "gn:name":"Alisurkhon",
    "gn:population":0,
    "gn:timezone":"Asia/Dushanbe",
    "iso:country":"TJ",
    "name:und_x_variant":[
        "Yali-Surkhon",
        "Alisurkhon"
    ],
    "wof:name":"Alisurkhon",
    "wof:placetype":"locality"
},
  "geometry": {"coordinates":[71.01132,38.90877],"type":"Point"}
}