{
  "type": "Feature",
  "properties": {
    "gn:admin1_code":"02",
    "gn:asciiname":"Pobeda",
    "gn:country_code":"TJ",
    "gn:dem":432,
    "gn:feature_class":"P",
    "gn:feature_code":"PPL",
    "gn:name":"Pobeda",
    "gn:population":0,
    "gn:timezone":"Asia/Dushanbe",
    "iso:country":"TJ",
    "name:und_x_variant":[
        "\u041f\u043e\u0431\u0435\u0434\u0430"
    ],
    "wof:name":"Pobeda",
    "wof:placetype":"locality"
},
  "geometry": {"coordinates":[69.35209,37.4203],"type":"Point"}
}