{
  "type": "Feature",
  "properties": {
    "gn:admin1_code":"02",
    "gn:asciiname":"Beshkappa",
    "gn:country_code":"TJ",
    "gn:dem":485,
    "gn:feature_class":"P",
    "gn:feature_code":"PPL",
    "gn:name":"Beshkappa",
    "gn:population":0,
    "gn:timezone":"Asia/Dushanbe",
    "iso:country":"TJ",
    "wof:name":"Beshkappa",
    "wof:placetype":"locality"
},
  "geometry": {"coordinates":[69.60028,37.61972],"type":"Point"}
}