{
  "type": "Feature",
  "properties": {
    "gn:admin1_code":"01",
    "gn:asciiname":"Bidizi Bolo",
    "gn:country_code":"TJ",
    "gn:dem":2803,
    "gn:feature_class":"P",
    "gn:feature_code":"PPL",
    "gn:name":"Bidizi Bolo",
    "gn:population":0,
    "gn:timezone":"Asia/Dushanbe",
    "iso:country":"TJ",
    "name:und_x_variant":[
        "\u0411\u0438\u0434\u0438\u0437\u0438 \u0411\u043e\u043b\u043e"
    ],
    "wof:name":"Bidizi Bolo",
    "wof:placetype":"locality"
},
  "geometry": {"coordinates":[71.85328,37.19524000000001],"type":"Point"}
}