{
  "type": "Feature",
  "properties": {
    "gn:admin1_code":"03",
    "gn:asciiname":"Veshab",
    "gn:country_code":"TJ",
    "gn:dem":1838,
    "gn:feature_class":"P",
    "gn:feature_code":"PPL",
    "gn:name":"Veshab",
    "gn:population":0,
    "gn:timezone":"Asia/Dushanbe",
    "iso:country":"TJ",
    "name:fas_x_preferred":[
        "\u0648\u0634\u0627\u0628"
    ],
    "name:msa_x_preferred":[
        "Veshab"
    ],
    "name:und_x_variant":[
        "\u0412\u0435\u0448\u0430\u0431"
    ],
    "wof:name":"Veshab",
    "wof:placetype":"locality"
},
  "geometry": {"coordinates":[68.93729,39.41349],"type":"Point"}
}