{
  "type": "Feature",
  "properties": {
    "gn:admin1_code":"00",
    "gn:asciiname":"Imeni Kalinina",
    "gn:country_code":"TJ",
    "gn:dem":2069,
    "gn:feature_class":"P",
    "gn:feature_code":"PPL",
    "gn:name":"Imeni Kalinina",
    "gn:population":0,
    "gn:timezone":"Asia/Dushanbe",
    "iso:country":"TJ",
    "wof:name":"Imeni Kalinina",
    "wof:placetype":"locality"
},
  "geometry": {"coordinates":[68.76666999999999,39.66667],"type":"Point"}
}