{
  "type": "Feature",
  "properties": {
    "gn:admin1_code":"03",
    "gn:asciiname":"Pagna",
    "gn:country_code":"TJ",
    "gn:dem":1587,
    "gn:feature_class":"P",
    "gn:feature_code":"PPL",
    "gn:name":"Pagna",
    "gn:population":0,
    "gn:timezone":"Asia/Dushanbe",
    "iso:country":"TJ",
    "name:und_x_variant":[
        "Patna",
        "Pagna"
    ],
    "wof:name":"Pagna",
    "wof:placetype":"locality"
},
  "geometry": {"coordinates":[68.02337,39.32553],"type":"Point"}
}