{
  "type": "Feature",
  "properties": {
    "gn:admin1_code":"RR",
    "gn:asciiname":"Ziyara-Tut",
    "gn:country_code":"TJ",
    "gn:dem":772,
    "gn:feature_class":"P",
    "gn:feature_code":"PPL",
    "gn:name":"Ziyara-Tut",
    "gn:population":0,
    "gn:timezone":"Asia/Dushanbe",
    "iso:country":"TJ",
    "wof:name":"Ziyara-Tut",
    "wof:placetype":"locality"
},
  "geometry": {"coordinates":[68.19750999999999,38.55213],"type":"Point"}
}