{
  "type": "Feature",
  "properties": {
    "gn:admin1_code":"02",
    "gn:asciiname":"Childukhtaron",
    "gn:country_code":"TJ",
    "gn:dem":1736,
    "gn:feature_class":"P",
    "gn:feature_code":"PPL",
    "gn:name":"Childukhtaron",
    "gn:population":0,
    "gn:timezone":"Asia/Dushanbe",
    "iso:country":"TJ",
    "name:und_x_variant":[
        "\u0427\u0438\u043b\u0434\u0443\u0445\u0442\u0430\u0440\u043e\u043d"
    ],
    "wof:name":"Childukhtaron",
    "wof:placetype":"locality"
},
  "geometry": {"coordinates":[70.13460000000001,38.28995],"type":"Point"}
}