{
  "type": "Feature",
  "properties": {
    "gn:asciiname":"Roshtkala",
    "gn:country_code":"TJ",
    "gn:dem":2818,
    "gn:feature_class":"P",
    "gn:feature_code":"PPL",
    "gn:name":"Roshtkala",
    "gn:population":0,
    "gn:timezone":"Asia/Dushanbe",
    "iso:country":"TJ",
    "wof:name":"Roshtkala",
    "wof:placetype":"locality"
},
  "geometry": {"coordinates":[71.81999999999999,37.267],"type":"Point"}
}