{
  "type": "Feature",
  "properties": {
    "gn:admin1_code":"02",
    "gn:asciiname":"Parvar",
    "gn:country_code":"TJ",
    "gn:dem":1567,
    "gn:feature_class":"P",
    "gn:feature_code":"PPL",
    "gn:name":"Parvar",
    "gn:population":0,
    "gn:timezone":"Asia/Dushanbe",
    "iso:country":"TJ",
    "name:tgk_x_preferred":[
        "Parvar"
    ],
    "name:und_x_variant":[
        "\u041f\u0430\u0440\u0432\u0430\u0440"
    ],
    "wof:name":"Parvar",
    "wof:placetype":"locality"
},
  "geometry": {"coordinates":[70.21754,37.73741],"type":"Point"}
}