{
  "type": "Feature",
  "properties": {
    "gn:admin1_code":"04",
    "gn:asciiname":"Sary-Assiya",
    "gn:country_code":"TJ",
    "gn:dem":907,
    "gn:feature_class":"P",
    "gn:feature_code":"PPL",
    "gn:name":"Sary-Assiya",
    "gn:population":0,
    "gn:timezone":"Asia/Dushanbe",
    "iso:country":"TJ",
    "wof:name":"Sary-Assiya",
    "wof:placetype":"locality"
},
  "geometry": {"coordinates":[68.78333000000001,38.61667],"type":"Point"}
}