{
  "type": "Feature",
  "properties": {
    "gn:admin1_code":"03",
    "gn:asciiname":"Pokhut",
    "gn:country_code":"TJ",
    "gn:dem":1675,
    "gn:feature_class":"P",
    "gn:feature_code":"PPL",
    "gn:name":"Pokhut",
    "gn:population":0,
    "gn:timezone":"Asia/Dushanbe",
    "iso:country":"TJ",
    "name:und_x_variant":[
        "\u041f\u043e\u0445\u0443\u0442",
        "Pakhurd"
    ],
    "wof:name":"Pokhut",
    "wof:placetype":"locality"
},
  "geometry": {"coordinates":[68.80558000000001,39.37789],"type":"Point"}
}