{
  "type": "Feature",
  "properties": {
    "gn:admin1_code":"02",
    "gn:asciiname":"Cholon",
    "gn:country_code":"TJ",
    "gn:dem":1305,
    "gn:feature_class":"P",
    "gn:feature_code":"PPL",
    "gn:name":"Cholon",
    "gn:population":0,
    "gn:timezone":"Asia/Dushanbe",
    "iso:country":"TJ",
    "wof:name":"Cholon",
    "wof:placetype":"locality"
},
  "geometry": {"coordinates":[69.78001,38.23644],"type":"Point"}
}