{
  "type": "Feature",
  "properties": {
    "gn:admin1_code":"02",
    "gn:asciiname":"Uchqul",
    "gn:country_code":"TJ",
    "gn:dem":741,
    "gn:feature_class":"P",
    "gn:feature_code":"PPL",
    "gn:name":"Uchqul",
    "gn:population":0,
    "gn:timezone":"Asia/Dushanbe",
    "iso:country":"TJ",
    "name:tgk_x_preferred":[
        "Uchkol"
    ],
    "name:und_x_variant":[
        "\u0423\u0447\u049b\u0443\u043b"
    ],
    "wof:name":"Uchqul",
    "wof:placetype":"locality"
},
  "geometry": {"coordinates":[69.45823,37.91022],"type":"Point"}
}