{
  "type": "Feature",
  "properties": {
    "gn:admin1_code":"02",
    "gn:asciiname":"Larkhobi",
    "gn:country_code":"TJ",
    "gn:dem":482,
    "gn:feature_class":"P",
    "gn:feature_code":"PPL",
    "gn:name":"Larkhobi",
    "gn:population":0,
    "gn:timezone":"Asia/Dushanbe",
    "iso:country":"TJ",
    "name:und_x_variant":[
        "Lyarkhobi",
        "Larkhobi"
    ],
    "wof:name":"Larkhobi",
    "wof:placetype":"locality"
},
  "geometry": {"coordinates":[69.67971,37.81936],"type":"Point"}
}