{
  "type": "Feature",
  "properties": {
    "gn:admin1_code":"02",
    "gn:asciiname":"Andizhan",
    "gn:country_code":"TJ",
    "gn:dem":354,
    "gn:feature_class":"P",
    "gn:feature_code":"PPL",
    "gn:name":"Andizhan",
    "gn:population":0,
    "gn:timezone":"Asia/Dushanbe",
    "iso:country":"TJ",
    "wof:name":"Andizhan",
    "wof:placetype":"locality"
},
  "geometry": {"coordinates":[69.05960999999999,37.28858],"type":"Point"}
}