{
  "type": "Feature",
  "properties": {
    "gn:admin1_code":"03",
    "gn:asciiname":"Fotehobod",
    "gn:country_code":"TJ",
    "gn:dem":315,
    "gn:feature_class":"P",
    "gn:feature_code":"PPL",
    "gn:name":"Fotehobod",
    "gn:population":0,
    "gn:timezone":"Asia/Dushanbe",
    "iso:country":"TJ",
    "name:und_x_variant":[
        "\u0424\u043e\u0442\u0435\u04b3\u043e\u0431\u043e\u0434"
    ],
    "wof:name":"Fotehobod",
    "wof:placetype":"locality"
},
  "geometry": {"coordinates":[69.27599000000001,40.53548],"type":"Point"}
}