{
  "type": "Feature",
  "properties": {
    "gn:admin1_code":"02",
    "gn:asciiname":"Khalkaer",
    "gn:country_code":"TJ",
    "gn:dem":1221,
    "gn:feature_class":"P",
    "gn:feature_code":"PPL",
    "gn:name":"Khalka\u00ebr",
    "gn:population":0,
    "gn:timezone":"Asia/Dushanbe",
    "iso:country":"TJ",
    "name:rus_x_preferred":[
        "Khalka\u00ebr"
    ],
    "wof:name":"Khalkaer",
    "wof:placetype":"locality"
},
  "geometry": {"coordinates":[69.89649,38.18628],"type":"Point"}
}