{
  "type": "Feature",
  "properties": {
    "gn:admin1_code":"01",
    "gn:asciiname":"Voznavd",
    "gn:country_code":"TJ",
    "gn:dem":1875,
    "gn:feature_class":"P",
    "gn:feature_code":"PPL",
    "gn:name":"Voznavd",
    "gn:population":0,
    "gn:timezone":"Asia/Dushanbe",
    "iso:country":"TJ",
    "name:tgk_x_preferred":[
        "Voznavd"
    ],
    "name:tgk_x_variant":[
        "\u0412\u043e\u0437\u043d\u0430\u0432\u0434"
    ],
    "name:und_x_variant":[
        "Waznud",
        "Voznaut",
        "Voznaud"
    ],
    "wof:name":"Voznavd",
    "wof:placetype":"locality"
},
  "geometry": {"coordinates":[71.27500999999999,37.96117],"type":"Point"}
}