{
  "type": "Feature",
  "properties": {
    "gn:admin1_code":"RR",
    "gn:asciiname":"Shirkent",
    "gn:country_code":"TJ",
    "gn:dem":968,
    "gn:feature_class":"P",
    "gn:feature_code":"PPL",
    "gn:name":"Shirkent",
    "gn:population":0,
    "gn:timezone":"Asia/Dushanbe",
    "iso:country":"TJ",
    "name:und_x_variant":[
        "Chirkent",
        "Sharkent",
        "Sherkent",
        "Sherkend",
        "Shirkent"
    ],
    "wof:name":"Shirkent",
    "wof:placetype":"locality"
},
  "geometry": {"coordinates":[68.22214,38.63532],"type":"Point"}
}