{
  "type": "Feature",
  "properties": {
    "gn:admin1_code":"03",
    "gn:asciiname":"Qayroqqum",
    "gn:country_code":"TJ",
    "gn:dem":362,
    "gn:feature_class":"P",
    "gn:feature_code":"PPL",
    "gn:name":"Qayroqqum",
    "gn:population":0,
    "gn:timezone":"Asia/Dushanbe",
    "iso:country":"TJ",
    "name:und_x_variant":[
        "Kayrakkum",
        "Kaikak Kum",
        "Kayrakum",
        "Khodzhent",
        "Qayraqqum",
        "Qayroqqum",
        "\u049a\u0430\u0439\u0440\u043e\u049b\u049b\u0443\u043c"
    ],
    "wof:name":"Qayroqqum",
    "wof:placetype":"locality"
},
  "geometry": {"coordinates":[69.79585,40.26598],"type":"Point"}
}