{
  "type": "Feature",
  "properties": {
    "gn:admin1_code":"00",
    "gn:asciiname":"Besh-Khabib",
    "gn:country_code":"TJ",
    "gn:dem":821,
    "gn:feature_class":"P",
    "gn:feature_code":"PPL",
    "gn:name":"Besh-Khabib",
    "gn:population":0,
    "gn:timezone":"Asia/Dushanbe",
    "iso:country":"TJ",
    "wof:name":"Besh-Khabib",
    "wof:placetype":"locality"
},
  "geometry": {"coordinates":[69.83333,37.88333],"type":"Point"}
}