{
  "type": "Feature",
  "properties": {
    "gn:admin1_code":"RR",
    "gn:asciiname":"Degi-Mulla",
    "gn:country_code":"TJ",
    "gn:dem":2528,
    "gn:feature_class":"P",
    "gn:feature_code":"PPL",
    "gn:name":"Degi-Mulla",
    "gn:population":0,
    "gn:timezone":"Asia/Dushanbe",
    "iso:country":"TJ",
    "wof:name":"Degi-Mulla",
    "wof:placetype":"locality"
},
  "geometry": {"coordinates":[70.45,38.88333],"type":"Point"}
}