{
  "type": "Feature",
  "properties": {
    "gn:admin1_code":"RR",
    "gn:asciiname":"Qarabolchik",
    "gn:country_code":"TJ",
    "gn:dem":596,
    "gn:feature_class":"P",
    "gn:feature_code":"PPL",
    "gn:name":"Qarabolchik",
    "gn:population":0,
    "gn:timezone":"Asia/Dushanbe",
    "iso:country":"TJ",
    "name:und_x_variant":[
        "Karabolchik",
        "Kara-Bal\u2019yank",
        "Kara-Bal\u2019chik",
        "Qarabolchik"
    ],
    "wof:name":"Qarabolchik",
    "wof:placetype":"locality"
},
  "geometry": {"coordinates":[68.38305,38.09442],"type":"Point"}
}