{
  "type": "Feature",
  "properties": {
    "gn:admin1_code":"02",
    "gn:asciiname":"Jam'iyati Dehqon",
    "gn:country_code":"TJ",
    "gn:dem":339,
    "gn:feature_class":"P",
    "gn:feature_code":"PPL",
    "gn:name":"Jam\u2019iyati Dehqon",
    "gn:population":0,
    "gn:timezone":"Asia/Dushanbe",
    "iso:country":"TJ",
    "name:tgk_x_preferred":[
        "Jam\u2019iyatdehqon"
    ],
    "name:und_x_variant":[
        "Dzhamiyat-Dekhan",
        "Jam\u2019iyati Dehqon",
        "\u04b6\u0430\u043c\u0438\u044f\u0442\u0438 \u0414\u0435\u04b3\u049b\u043e\u043d"
    ],
    "wof:name":"Jam'iyati Dehqon",
    "wof:placetype":"locality"
},
  "geometry": {"coordinates":[68.10297,37.11924000000001],"type":"Point"}
}