{
  "type": "Feature",
  "properties": {
    "gn:admin1_code":"03",
    "gn:asciiname":"Tutikavola",
    "gn:country_code":"TJ",
    "gn:dem":360,
    "gn:feature_class":"P",
    "gn:feature_code":"PPL",
    "gn:name":"Tutikavola",
    "gn:population":0,
    "gn:timezone":"Asia/Dushanbe",
    "iso:country":"TJ",
    "name:uzb_x_preferred":[
        "Tutikavola"
    ],
    "wof:name":"Tutikavola",
    "wof:placetype":"locality"
},
  "geometry": {"coordinates":[70.38584,40.28192],"type":"Point"}
}