{
  "type": "Feature",
  "properties": {
    "gn:admin1_code":"03",
    "gn:asciiname":"Zarxoq",
    "gn:country_code":"TJ",
    "gn:dem":609,
    "gn:feature_class":"P",
    "gn:feature_code":"PPL",
    "gn:name":"Zarxoq",
    "gn:population":0,
    "gn:timezone":"Asia/Dushanbe",
    "iso:country":"TJ",
    "name:und_x_variant":[
        "Zartkhak"
    ],
    "name:uzb_x_preferred":[
        "Zarxoq"
    ],
    "wof:name":"Zarxoq",
    "wof:placetype":"locality"
},
  "geometry": {"coordinates":[70.56596,40.26665],"type":"Point"}
}