{
  "type": "Feature",
  "properties": {
    "gn:admin1_code":"01",
    "gn:asciiname":"Nagodak",
    "gn:country_code":"TJ",
    "gn:dem":2105,
    "gn:feature_class":"P",
    "gn:feature_code":"PPL",
    "gn:name":"Nagodak",
    "gn:population":0,
    "gn:timezone":"Asia/Dushanbe",
    "iso:country":"TJ",
    "name:und_x_variant":[
        "Navodak",
        "Nagodak"
    ],
    "wof:name":"Nagodak",
    "wof:placetype":"locality"
},
  "geometry": {"coordinates":[71.52559000000002,37.47118],"type":"Point"}
}