{
  "type": "Feature",
  "properties": {
    "gn:admin1_code":"RR",
    "gn:asciiname":"Yangi-Kishlak",
    "gn:country_code":"TJ",
    "gn:dem":860,
    "gn:feature_class":"P",
    "gn:feature_code":"PPL",
    "gn:name":"Yangi-Kishlak",
    "gn:population":0,
    "gn:timezone":"Asia/Dushanbe",
    "iso:country":"TJ",
    "wof:name":"Yangi-Kishlak",
    "wof:placetype":"locality"
},
  "geometry": {"coordinates":[68.3049,38.35868],"type":"Point"}
}