{
  "type": "Feature",
  "properties": {
    "gn:admin1_code":"02",
    "gn:asciiname":"Dzharbulok",
    "gn:country_code":"TJ",
    "gn:dem":644,
    "gn:feature_class":"P",
    "gn:feature_code":"PPL",
    "gn:name":"Dzharbulok",
    "gn:population":0,
    "gn:timezone":"Asia/Dushanbe",
    "iso:country":"TJ",
    "wof:name":"Dzharbulok",
    "wof:placetype":"locality"
},
  "geometry": {"coordinates":[69.35921999999999,37.87077],"type":"Point"}
}