{
  "type": "Feature",
  "properties": {
    "gn:admin1_code":"RR",
    "gn:asciiname":"Bogak",
    "gn:country_code":"TJ",
    "gn:dem":1196,
    "gn:feature_class":"P",
    "gn:feature_code":"PPL",
    "gn:name":"Bogak",
    "gn:population":0,
    "gn:timezone":"Asia/Dushanbe",
    "iso:country":"TJ",
    "wof:name":"Bogak",
    "wof:placetype":"locality"
},
  "geometry": {"coordinates":[68.54096,38.18011],"type":"Point"}
}