{
  "type": "Feature",
  "properties": {
    "gn:admin1_code":"RR",
    "gn:asciiname":"Dushakhokogak",
    "gn:country_code":"TJ",
    "gn:dem":2285,
    "gn:feature_class":"P",
    "gn:feature_code":"PPL",
    "gn:name":"Dushakhokogak",
    "gn:population":0,
    "gn:timezone":"Asia/Dushanbe",
    "iso:country":"TJ",
    "wof:name":"Dushakhokogak",
    "wof:placetype":"locality"
},
  "geometry": {"coordinates":[70.43333,38.88333],"type":"Point"}
}