{
  "type": "Feature",
  "properties": {
    "gn:admin1_code":"01",
    "gn:asciiname":"Parinishian",
    "gn:country_code":"TJ",
    "gn:dem":2932,
    "gn:feature_class":"P",
    "gn:feature_code":"PPL",
    "gn:name":"Parinishian",
    "gn:population":0,
    "gn:timezone":"Asia/Dushanbe",
    "iso:country":"TJ",
    "wof:name":"Parinishian",
    "wof:placetype":"locality"
},
  "geometry": {"coordinates":[72.15137,37.74702],"type":"Point"}
}