{
  "type": "Feature",
  "properties": {
    "gn:admin1_code":"02",
    "gn:asciiname":"Garavchak",
    "gn:country_code":"TJ",
    "gn:dem":481,
    "gn:feature_class":"P",
    "gn:feature_code":"PPL",
    "gn:name":"Garavchak",
    "gn:population":0,
    "gn:timezone":"Asia/Dushanbe",
    "iso:country":"TJ",
    "wof:name":"Garavchak",
    "wof:placetype":"locality"
},
  "geometry": {"coordinates":[69.63249999999999,37.82278],"type":"Point"}
}