{
  "type": "Feature",
  "properties": {
    "gn:admin1_code":"02",
    "gn:asciiname":"Oqbuloq",
    "gn:country_code":"TJ",
    "gn:dem":1117,
    "gn:feature_class":"P",
    "gn:feature_code":"PPL",
    "gn:name":"Oqbuloq",
    "gn:population":0,
    "gn:timezone":"Asia/Dushanbe",
    "iso:country":"TJ",
    "name:und_x_variant":[
        "Okbulok",
        "Oqbuloq",
        "\u041e\u049b\u0431\u0443\u043b\u043e\u049b"
    ],
    "wof:name":"Oqbuloq",
    "wof:placetype":"locality"
},
  "geometry": {"coordinates":[69.70779,38.28122000000001],"type":"Point"}
}