{
  "type": "Feature",
  "properties": {
    "gn:admin1_code":"03",
    "gn:asciiname":"Qal'achai Gulizard",
    "gn:country_code":"TJ",
    "gn:dem":1059,
    "gn:feature_class":"P",
    "gn:feature_code":"PPL",
    "gn:name":"Qal\u2019achai Gulizard",
    "gn:population":0,
    "gn:timezone":"Asia/Dushanbe",
    "iso:country":"TJ",
    "name:und_x_variant":[
        "Qal\u2019achai Gulizard",
        "\u049a\u0430\u043b\u044a\u0430\u0441\u0430\u0438 \u0413\u0443\u043b\u0438\u0437\u0430\u0440\u0434"
    ],
    "wof:name":"Qal'achai Gulizard",
    "wof:placetype":"locality"
},
  "geometry": {"coordinates":[69.0415,39.89741],"type":"Point"}
}