{
  "type": "Feature",
  "properties": {
    "iso:country":"TJ",
    "name:ckb_x_preferred":[
        "\u0695\u06c6\u0634\u0627\u0646"
    ],
    "name:eng_x_preferred":[
        "Rushon"
    ],
    "name:fas_x_preferred":[
        "\u0631\u0648\u0634\u0627\u0646"
    ],
    "name:fra_x_preferred":[
        "Rushan"
    ],
    "name:nld_x_preferred":[
        "Rushon"
    ],
    "name:rus_x_preferred":[
        "\u0420\u0443\u0448\u0430\u043d"
    ],
    "name:tgk_x_preferred":[
        "\u0420\u04ef\u0448\u043e\u043d"
    ],
    "name:tgk_x_variant":[
        "R\u016dshon",
        "\u04b6\u0430\u043c\u043e\u0430\u0442\u0438 \u0420\u04ef\u0448\u043e\u043d"
    ],
    "name:und_x_variant":[
        "Kala-i-Warma"
    ],
    "name:urd_x_preferred":[
        "\u0631\u0648\u0634\u0627\u0646"
    ],
    "qs:gn_country":"TJ",
    "qs:gn_fcode":"PPLA2",
    "qs:gn_pop":0,
    "qs:name":"Rushan",
    "qs:name_adm0":"Tajikistan",
    "qs:name_adm1":"Kuhistoni Badakhshon",
    "qs:photos":37,
    "qs:photos_1k":7,
    "qs:photos_9k":1,
    "qs:photos_9r":2,
    "qs:photos_all":37,
    "qs:photos_sr":2,
    "qs:placetype":"Town",
    "qs:pop_sr":"0",
    "qs:woe_adm0":23424961,
    "wd:wordcount":85,
    "wof:name":"Rushan",
    "wof:placetype":"locality"
},
  "geometry": {"coordinates":[71.55744,37.94487],"type":"Point"}
}