{
  "type": "Feature",
  "properties": {
    "gn:admin1_code":"01",
    "gn:asciiname":"Chatyr-Tash",
    "gn:country_code":"TJ",
    "gn:dem":3991,
    "gn:feature_class":"P",
    "gn:feature_code":"PPL",
    "gn:name":"Chatyr-Tash",
    "gn:population":0,
    "gn:timezone":"Asia/Dushanbe",
    "iso:country":"TJ",
    "name:und_x_variant":[
        "Murzabek",
        "Rabat Chatyr-Tash",
        "Chatyr-Tash"
    ],
    "wof:name":"Chatyr-Tash",
    "wof:placetype":"locality"
},
  "geometry": {"coordinates":[73.65000000000001,37.85],"type":"Point"}
}