{
  "type": "Feature",
  "properties": {
    "gn:admin1_code":"03",
    "gn:asciiname":"Baland",
    "gn:country_code":"TJ",
    "gn:dem":736,
    "gn:feature_class":"P",
    "gn:feature_code":"PPL",
    "gn:name":"Baland",
    "gn:population":0,
    "gn:timezone":"Asia/Dushanbe",
    "iso:country":"TJ",
    "name:und_x_variant":[
        "\u0411\u0430\u043b\u0430\u043d\u0434",
        "Arab"
    ],
    "wof:name":"Baland",
    "wof:placetype":"locality"
},
  "geometry": {"coordinates":[70.58443,40.18811],"type":"Point"}
}