{
  "type": "Feature",
  "properties": {
    "gn:admin1_code":"02",
    "gn:asciiname":"Taginomak",
    "gn:cc2":"TJ",
    "gn:country_code":"TJ",
    "gn:dem":473,
    "gn:feature_class":"P",
    "gn:feature_code":"PPL",
    "gn:name":"Taginomak",
    "gn:population":0,
    "gn:timezone":"Asia/Dushanbe",
    "iso:country":"TJ",
    "name:tgk_x_preferred":[
        "Taginomak"
    ],
    "name:und_x_variant":[
        "Taginimak"
    ],
    "wof:name":"Taginomak",
    "wof:placetype":"locality"
},
  "geometry": {"coordinates":[69.60194,37.69278],"type":"Point"}
}