{
  "type": "Feature",
  "properties": {
    "gn:admin1_code":"03",
    "gn:asciiname":"Hushyor",
    "gn:country_code":"TJ",
    "gn:dem":2110,
    "gn:feature_class":"P",
    "gn:feature_code":"PPL",
    "gn:name":"Hushyor",
    "gn:population":0,
    "gn:timezone":"Asia/Dushanbe",
    "iso:country":"TJ",
    "name:und_x_variant":[
        "\u04b2\u0443\u0448\u0451\u0440"
    ],
    "wof:name":"Hushyor",
    "wof:placetype":"locality"
},
  "geometry": {"coordinates":[67.79054000000001,39.19906],"type":"Point"}
}