{
  "type": "Feature",
  "properties": {
    "gn:admin1_code":"02",
    "gn:asciiname":"Mishkoron",
    "gn:country_code":"TJ",
    "gn:dem":854,
    "gn:feature_class":"P",
    "gn:feature_code":"PPL",
    "gn:name":"Mishkoron",
    "gn:population":0,
    "gn:timezone":"Asia/Dushanbe",
    "iso:country":"TJ",
    "name:tgk_x_preferred":[
        "Mishkoron"
    ],
    "name:und_x_variant":[
        "Marish-Karon",
        "\u041c\u0438\u0448\u043a\u043e\u0440\u043e\u043d"
    ],
    "wof:name":"Mishkoron",
    "wof:placetype":"locality"
},
  "geometry": {"coordinates":[69.85120000000001,37.69211],"type":"Point"}
}