{
  "type": "Feature",
  "properties": {
    "gn:admin1_code":"02",
    "gn:asciiname":"Kurot",
    "gn:country_code":"TJ",
    "gn:dem":360,
    "gn:feature_class":"P",
    "gn:feature_code":"PPL",
    "gn:name":"Kurot",
    "gn:population":0,
    "gn:timezone":"Asia/Dushanbe",
    "iso:country":"TJ",
    "name:und_x_variant":[
        "\u041a\u0443\u0440\u043e\u0442"
    ],
    "wof:name":"Kurot",
    "wof:placetype":"locality"
},
  "geometry": {"coordinates":[68.16557,37.24987],"type":"Point"}
}