{
  "type": "Feature",
  "properties": {
    "gn:admin1_code":"01",
    "gn:asciiname":"Andarbog",
    "gn:country_code":"TJ",
    "gn:dem":1897,
    "gn:feature_class":"P",
    "gn:feature_code":"PPL",
    "gn:name":"Andarbog",
    "gn:population":0,
    "gn:timezone":"Asia/Dushanbe",
    "iso:country":"TJ",
    "name:tgk_x_preferred":[
        "\u0410\u043d\u0434\u0430\u0440\u0431\u0430\u043a"
    ],
    "name:tgk_x_variant":[
        "Andarbak"
    ],
    "name:und_x_variant":[
        "Andarbag",
        "Anderbak",
        "Anderbag",
        "Andarbog",
        "Amdarbog",
        "\u0410\u043d\u0434\u0430\u0440\u0431\u043e\u0433"
    ],
    "wof:name":"Andarbog",
    "wof:placetype":"locality"
},
  "geometry": {"coordinates":[71.5442,38.23232],"type":"Point"}
}