{
  "type": "Feature",
  "properties": {
    "gn:admin1_code":"03",
    "gn:asciiname":"Jangal",
    "gn:country_code":"TJ",
    "gn:dem":921,
    "gn:feature_class":"P",
    "gn:feature_code":"PPL",
    "gn:name":"Jangal",
    "gn:population":0,
    "gn:timezone":"Asia/Dushanbe",
    "iso:country":"TJ",
    "name:deu_x_preferred":[
        "Changal"
    ],
    "name:und_x_variant":[
        "Changa",
        "Jangal",
        "\u04b6\u0432\u043d\u0433\u0430\u043b"
    ],
    "wof:name":"Jangal",
    "wof:placetype":"locality"
},
  "geometry": {"coordinates":[67.51485,39.52119],"type":"Point"}
}