{
  "type": "Feature",
  "properties": {
    "gn:admin1_code":"01",
    "gn:asciiname":"Jund",
    "gn:country_code":"TJ",
    "gn:dem":2877,
    "gn:feature_class":"P",
    "gn:feature_code":"PPL",
    "gn:name":"Jund",
    "gn:population":0,
    "gn:timezone":"Asia/Dushanbe",
    "iso:country":"TJ",
    "name:cat_x_preferred":[
        "Jund"
    ],
    "name:deu_x_preferred":[
        "Dschund"
    ],
    "name:fra_x_preferred":[
        "Jund"
    ],
    "name:ind_x_preferred":[
        "Jund"
    ],
    "name:ita_x_preferred":[
        "Jund"
    ],
    "name:por_x_preferred":[
        "Junde"
    ],
    "name:spa_x_preferred":[
        "Yund"
    ],
    "name:tgk_x_preferred":[
        "Jund"
    ],
    "name:tgk_x_variant":[
        "\u04b6\u0443\u043d\u0434"
    ],
    "name:und_x_variant":[
        "Dzhunt"
    ],
    "name:urd_x_preferred":[
        "\u062c\u0646\u062f"
    ],
    "wof:name":"Jund",
    "wof:placetype":"locality"
},
  "geometry": {"coordinates":[71.53333000000001,37.21667],"type":"Point"}
}