{
  "type": "Feature",
  "properties": {
    "gn:admin1_code":"01",
    "gn:asciiname":"Vishkharv",
    "gn:country_code":"TJ",
    "gn:dem":1869,
    "gn:feature_class":"P",
    "gn:feature_code":"PPL",
    "gn:name":"Vishkharv",
    "gn:population":0,
    "gn:timezone":"Asia/Dushanbe",
    "iso:country":"TJ",
    "name:tgk_x_preferred":[
        "Vishkharv"
    ],
    "name:und_x_variant":[
        "Vishikharv",
        "Vyshkharv",
        "\u0412\u0438\u0448\u0445\u0430\u0440\u0432"
    ],
    "wof:name":"Vishkharv",
    "wof:placetype":"locality"
},
  "geometry": {"coordinates":[71.52369,38.22668],"type":"Point"}
}