{
  "type": "Feature",
  "properties": {
    "iso:country":"TJ",
    "name:ces_x_preferred":[
        "I\u0161ka\u0161im"
    ],
    "name:deu_x_preferred":[
        "Ischkoschim"
    ],
    "name:ell_x_preferred":[
        "\u0399\u03c3\u03ba\u03bf\u03c3\u03af\u03bc"
    ],
    "name:eng_x_preferred":[
        "Ishkoshim"
    ],
    "name:est_x_preferred":[
        "I\u0161ko\u0161im"
    ],
    "name:fra_x_preferred":[
        "Ishkashim"
    ],
    "name:hun_x_preferred":[
        "Iskosim"
    ],
    "name:jpn_x_preferred":[
        "\u30a4\u30b7\u30e5\u30b3\u30b7\u30e0"
    ],
    "name:nld_x_preferred":[
        "Ishkoshim"
    ],
    "name:rus_x_preferred":[
        "\u0418\u0448\u043a\u0430\u0448\u0438\u043c"
    ],
    "name:tgk_x_preferred":[
        "\u04b6\u0430\u043c\u043e\u0430\u0442\u0438 \u0418\u0448\u043a\u043e\u0448\u0438\u043c"
    ],
    "name:ukr_x_preferred":[
        "\u0406\u0448\u043a\u0430\u0448\u0438\u043c"
    ],
    "name:und_x_variant":[
        "Ishk\u0101sh\u012bm Post"
    ],
    "name:urd_x_preferred":[
        "\u067e\u0646\u062c"
    ],
    "name:urd_x_variant":[
        "\u0627\u0634\u06a9\u0627\u0634\u0645"
    ],
    "name:uzb_x_preferred":[
        "Ishkashim"
    ],
    "qs:gn_country":"TJ",
    "qs:gn_fcode":"PPLA2",
    "qs:gn_pop":26000,
    "qs:name":"Ishkashim",
    "qs:name_adm0":"Tajikistan",
    "qs:name_adm1":"Kuhistoni Badakhshon",
    "qs:photos":64,
    "qs:photos_1k":13,
    "qs:photos_9k":1,
    "qs:photos_9r":2,
    "qs:photos_all":64,
    "qs:photos_sr":2,
    "qs:placetype":"Town",
    "qs:pop_sr":"7",
    "qs:woe_adm0":23424961,
    "wd:wordcount":171,
    "wof:name":"Ishkashim",
    "wof:placetype":"locality",
    "wof:population":26000
},
  "geometry": {"coordinates":[71.61331,36.72484],"type":"Point"}
}