{
  "type": "Feature",
  "properties": {
    "gn:admin1_code":"02",
    "gn:asciiname":"Zarbdor",
    "gn:country_code":"TJ",
    "gn:dem":363,
    "gn:feature_class":"P",
    "gn:feature_code":"PPL",
    "gn:name":"Zarbdor",
    "gn:population":0,
    "gn:timezone":"Asia/Dushanbe",
    "iso:country":"TJ",
    "wof:name":"Zarbdor",
    "wof:placetype":"locality"
},
  "geometry": {"coordinates":[69.0806,37.32205],"type":"Point"}
}