{
  "type": "Feature",
  "properties": {
    "gn:admin1_code":"02",
    "gn:asciiname":"Yangiobod",
    "gn:country_code":"TJ",
    "gn:dem":392,
    "gn:feature_class":"P",
    "gn:feature_code":"PPL",
    "gn:name":"Yangiobod",
    "gn:population":0,
    "gn:timezone":"Asia/Dushanbe",
    "iso:country":"TJ",
    "name:und_x_variant":[
        "\u042f\u043d\u0433\u0438\u043e\u0431\u043e\u0434"
    ],
    "wof:name":"Yangiobod",
    "wof:placetype":"locality"
},
  "geometry": {"coordinates":[68.74694000000001,37.66461],"type":"Point"}
}