{
  "type": "Feature",
  "properties": {
    "gn:admin1_code":"02",
    "gn:asciiname":"Qurbonshahid",
    "gn:country_code":"TJ",
    "gn:dem":476,
    "gn:feature_class":"P",
    "gn:feature_code":"PPL",
    "gn:name":"Qurbonshahid",
    "gn:population":0,
    "gn:timezone":"Asia/Dushanbe",
    "iso:country":"TJ",
    "name:tgk_x_preferred":[
        "Qurbonshahid"
    ],
    "name:und_x_variant":[
        "Kurbanshaid",
        "Kurbansheit",
        "Kurbanshait",
        "\u049a\u0443\u0440\u0431\u043e\u043d\u0448\u0430\u04b3\u0438\u0434"
    ],
    "wof:name":"Qurbonshahid",
    "wof:placetype":"locality"
},
  "geometry": {"coordinates":[69.55488000000001,37.7788],"type":"Point"}
}