{
  "type": "Feature",
  "properties": {
    "gn:admin1_code":"02",
    "gn:asciiname":"Gurdara",
    "gn:country_code":"TJ",
    "gn:dem":587,
    "gn:feature_class":"P",
    "gn:feature_code":"PPL",
    "gn:name":"Gurdara",
    "gn:population":0,
    "gn:timezone":"Asia/Dushanbe",
    "iso:country":"TJ",
    "wof:name":"Gurdara",
    "wof:placetype":"locality"
},
  "geometry": {"coordinates":[69.57083,37.95396],"type":"Point"}
}