{
  "type": "Feature",
  "properties": {
    "gn:admin1_code":"02",
    "gn:asciiname":"Davlatobod",
    "gn:country_code":"TJ",
    "gn:dem":482,
    "gn:feature_class":"P",
    "gn:feature_code":"PPL",
    "gn:name":"Davlatobod",
    "gn:population":0,
    "gn:timezone":"Asia/Dushanbe",
    "iso:country":"TJ",
    "name:tgk_x_preferred":[
        "Davlatobod"
    ],
    "name:und_x_variant":[
        "Davlatabad",
        "\u0414\u0430\u0432\u043f\u0430\u0442\u043e\u0431\u043e\u0434"
    ],
    "wof:name":"Davlatobod",
    "wof:placetype":"locality"
},
  "geometry": {"coordinates":[69.59425,37.64171],"type":"Point"}
}