{
  "type": "Feature",
  "properties": {
    "gn:admin1_code":"03",
    "gn:asciiname":"Khuzya",
    "gn:country_code":"TJ",
    "gn:dem":880,
    "gn:feature_class":"P",
    "gn:feature_code":"PPL",
    "gn:name":"Khuzya",
    "gn:population":0,
    "gn:timezone":"Asia/Dushanbe",
    "iso:country":"TJ",
    "wof:name":"Khuzya",
    "wof:placetype":"locality"
},
  "geometry": {"coordinates":[68.98333000000001,39.96667],"type":"Point"}
}