{
  "type": "Feature",
  "properties": {
    "gn:admin1_code":"RR",
    "gn:asciiname":"Kurpay",
    "gn:country_code":"TJ",
    "gn:dem":1411,
    "gn:feature_class":"P",
    "gn:feature_code":"PPL",
    "gn:name":"Kurpay",
    "gn:population":0,
    "gn:timezone":"Asia/Dushanbe",
    "iso:country":"TJ",
    "name:und_x_variant":[
        "Kurpai",
        "Kurpay"
    ],
    "wof:name":"Kurpay",
    "wof:placetype":"locality"
},
  "geometry": {"coordinates":[68.86248000000001,38.64223],"type":"Point"}
}