{
  "type": "Feature",
  "properties": {
    "gn:admin1_code":"RR",
    "gn:asciiname":"Ming-Tut",
    "gn:country_code":"TJ",
    "gn:dem":665,
    "gn:feature_class":"P",
    "gn:feature_code":"PPL",
    "gn:name":"Ming-Tut",
    "gn:population":0,
    "gn:timezone":"Asia/Dushanbe",
    "iso:country":"TJ",
    "wof:name":"Ming-Tut",
    "wof:placetype":"locality"
},
  "geometry": {"coordinates":[68.23038000000001,38.46894],"type":"Point"}
}