{
  "type": "Feature",
  "properties": {
    "gn:admin1_code":"RR",
    "gn:asciiname":"Foru",
    "gn:country_code":"TJ",
    "gn:dem":1986,
    "gn:feature_class":"P",
    "gn:feature_code":"PPL",
    "gn:name":"Foru",
    "gn:population":0,
    "gn:timezone":"Asia/Dushanbe",
    "iso:country":"TJ",
    "name:und_x_variant":[
        "Poru",
        "Foru"
    ],
    "wof:name":"Foru",
    "wof:placetype":"locality"
},
  "geometry": {"coordinates":[69.66181999999999,38.684],"type":"Point"}
}