{
  "type": "Feature",
  "properties": {
    "gn:admin1_code":"RR",
    "gn:asciiname":"Laqaybegi",
    "gn:country_code":"TJ",
    "gn:dem":908,
    "gn:feature_class":"P",
    "gn:feature_code":"PPL",
    "gn:name":"Laqaybeg\u00ed",
    "gn:population":0,
    "gn:timezone":"Asia/Dushanbe",
    "iso:country":"TJ",
    "name:und_x_variant":[
        "Lakaybegi",
        "Lakai-Bezi",
        "Lakai-Begi",
        "Laqaybeg\u00ed"
    ],
    "wof:name":"Laqaybegi",
    "wof:placetype":"locality"
},
  "geometry": {"coordinates":[69.07536,38.51164],"type":"Point"}
}