{
  "type": "Feature",
  "properties": {
    "gn:admin1_code":"02",
    "gn:asciiname":"Turkoni",
    "gn:country_code":"TJ",
    "gn:dem":1362,
    "gn:feature_class":"P",
    "gn:feature_code":"PPL",
    "gn:name":"Turkoni",
    "gn:population":0,
    "gn:timezone":"Asia/Dushanbe",
    "iso:country":"TJ",
    "name:rus_x_preferred":[
        "\u0425\u0430\u0440\u043e\u0431\u0430 \u0422\u0443\u0440\u043a\u043e\u043d\u0438"
    ],
    "name:tgk_x_preferred":[
        "Kharoba Turkoni"
    ],
    "name:und_x_variant":[
        "\u0425\u0430\u0440\u043e\u0431\u0430 \u0422\u0443\u0440\u043a\u043e\u043d\u0438",
        "Razvaliny Turkoni"
    ],
    "wof:name":"Turkoni",
    "wof:placetype":"locality"
},
  "geometry": {"coordinates":[69.9439,37.88561],"type":"Point"}
}