{
  "type": "Feature",
  "properties": {
    "gn:admin1_code":"02",
    "gn:asciiname":"Davlatshoyon",
    "gn:country_code":"TJ",
    "gn:dem":911,
    "gn:feature_class":"P",
    "gn:feature_code":"PPL",
    "gn:name":"Davlatshoyon",
    "gn:population":0,
    "gn:timezone":"Asia/Dushanbe",
    "iso:country":"TJ",
    "name:und_x_variant":[
        "Davlatshoy\u00ebn",
        "Davlatshoyon",
        "\u0414\u0430\u0432\u043b\u0430\u0442\u0448\u043e\u0451\u043d"
    ],
    "wof:name":"Davlatshoyon",
    "wof:placetype":"locality"
},
  "geometry": {"coordinates":[69.51716999999999,38.26009000000001],"type":"Point"}
}