{
  "type": "Feature",
  "properties": {
    "gn:admin1_code":"01",
    "gn:asciiname":"Buniga",
    "gn:country_code":"TJ",
    "gn:dem":1597,
    "gn:feature_class":"P",
    "gn:feature_code":"PPL",
    "gn:name":"Buniga",
    "gn:population":0,
    "gn:timezone":"Asia/Dushanbe",
    "iso:country":"TJ",
    "name:tgk_x_preferred":[
        "Buniga"
    ],
    "name:tgk_x_variant":[
        "\u0411\u0443\u043d\u0438\u0433\u0430"
    ],
    "wof:name":"Buniga",
    "wof:placetype":"locality"
},
  "geometry": {"coordinates":[71.27583,38.31544],"type":"Point"}
}