{
  "type": "Feature",
  "properties": {
    "gn:admin1_code":"01",
    "gn:asciiname":"Umarak",
    "gn:country_code":"TJ",
    "gn:dem":1263,
    "gn:feature_class":"P",
    "gn:feature_code":"PPL",
    "gn:name":"Umarak",
    "gn:population":0,
    "gn:timezone":"Asia/Dushanbe",
    "iso:country":"TJ",
    "name:und_x_variant":[
        "\u0423\u043c\u0430\u0440\u0430\u043a"
    ],
    "wof:name":"Umarak",
    "wof:placetype":"locality"
},
  "geometry": {"coordinates":[70.76413000000002,38.44673],"type":"Point"}
}