{
  "type": "Feature",
  "properties": {
    "gn:admin1_code":"02",
    "gn:asciiname":"Chruch",
    "gn:country_code":"TJ",
    "gn:dem":977,
    "gn:feature_class":"P",
    "gn:feature_code":"PPL",
    "gn:name":"Chruch",
    "gn:population":0,
    "gn:timezone":"Asia/Dushanbe",
    "iso:country":"TJ",
    "name:und_x_variant":[
        "\u0427\u0443\u0440\u0443\u0447"
    ],
    "wof:name":"Chruch",
    "wof:placetype":"locality"
},
  "geometry": {"coordinates":[69.38646,38.36152],"type":"Point"}
}