{
  "type": "Feature",
  "properties": {
    "gn:admin1_code":"02",
    "gn:asciiname":"Imamtarifi",
    "gn:country_code":"TJ",
    "gn:dem":564,
    "gn:feature_class":"P",
    "gn:feature_code":"PPL",
    "gn:name":"Imamtarifi",
    "gn:population":0,
    "gn:timezone":"Asia/Dushanbe",
    "iso:country":"TJ",
    "wof:name":"Imamtarifi",
    "wof:placetype":"locality"
},
  "geometry": {"coordinates":[69.72075,37.93134000000001],"type":"Point"}
}