{
  "type": "Feature",
  "properties": {
    "gn:admin1_code":"03",
    "gn:asciiname":"Khabutak",
    "gn:country_code":"TJ",
    "gn:dem":1036,
    "gn:feature_class":"P",
    "gn:feature_code":"PPL",
    "gn:name":"Khabutak",
    "gn:population":0,
    "gn:timezone":"Asia/Dushanbe",
    "iso:country":"TJ",
    "name:und_x_variant":[
        "\u0425\u0430\u0431\u0443\u0442\u0430\u043a"
    ],
    "wof:name":"Khabutak",
    "wof:placetype":"locality"
},
  "geometry": {"coordinates":[69.27422,39.93406],"type":"Point"}
}