{
  "type": "Feature",
  "properties": {
    "gn:admin1_code":"03",
    "gn:asciiname":"Pishanza",
    "gn:country_code":"TJ",
    "gn:dem":2372,
    "gn:feature_class":"P",
    "gn:feature_code":"PPL",
    "gn:name":"Pishanza",
    "gn:population":0,
    "gn:timezone":"Asia/Dushanbe",
    "iso:country":"TJ",
    "name:und_x_variant":[
        "\u041f\u0438\u0448\u0430\u043d\u0437\u0430"
    ],
    "wof:name":"Pishanza",
    "wof:placetype":"locality"
},
  "geometry": {"coordinates":[68.63736,39.23754],"type":"Point"}
}