{
  "type": "Feature",
  "properties": {
    "gn:admin1_code":"02",
    "gn:asciiname":"Zafarabad",
    "gn:country_code":"TJ",
    "gn:dem":564,
    "gn:feature_class":"P",
    "gn:feature_code":"PPL",
    "gn:name":"Zafarabad",
    "gn:population":0,
    "gn:timezone":"Asia/Dushanbe",
    "iso:country":"TJ",
    "wof:name":"Zafarabad",
    "wof:placetype":"locality"
},
  "geometry": {"coordinates":[69.51586999999999,37.79356],"type":"Point"}
}