{
  "type": "Feature",
  "properties": {
    "gn:admin1_code":"01",
    "gn:asciiname":"Bopasor",
    "gn:country_code":"TJ",
    "gn:dem":3005,
    "gn:feature_class":"P",
    "gn:feature_code":"PPL",
    "gn:name":"Bopasor",
    "gn:population":0,
    "gn:timezone":"Asia/Dushanbe",
    "iso:country":"TJ",
    "name:und_x_variant":[
        "\u0411\u043e\u043f\u0430\u0441\u043e\u0440"
    ],
    "wof:name":"Bopasor",
    "wof:placetype":"locality"
},
  "geometry": {"coordinates":[72.62424,38.39929],"type":"Point"}
}