{
  "type": "Feature",
  "properties": {
    "gn:admin1_code":"03",
    "gn:asciiname":"Dehmoi",
    "gn:country_code":"TJ",
    "gn:dem":348,
    "gn:feature_class":"P",
    "gn:feature_code":"PPL",
    "gn:name":"Dehmo\u00ed",
    "gn:population":0,
    "gn:timezone":"Asia/Dushanbe",
    "iso:country":"TJ",
    "name:und_x_variant":[
        "Dehmo\u00ed",
        "\u0414\u0435\u04b3\u043c\u043e\u04e3"
    ],
    "wof:name":"Dehmoi",
    "wof:placetype":"locality"
},
  "geometry": {"coordinates":[69.51860000000001,40.21438],"type":"Point"}
}