{
  "type": "Feature",
  "properties": {
    "gn:admin1_code":"02",
    "gn:asciiname":"Gulisoy Vtoroy",
    "gn:country_code":"TJ",
    "gn:dem":1055,
    "gn:feature_class":"P",
    "gn:feature_code":"PPL",
    "gn:name":"Gulisoy Vtoroy",
    "gn:population":0,
    "gn:timezone":"Asia/Dushanbe",
    "iso:country":"TJ",
    "name:und_x_variant":[
        "Gulisoy 2 (Vtoroy)",
        "Gulisoy 2",
        "Gulisoy Vtoroy"
    ],
    "wof:name":"Gulisoy Vtoroy",
    "wof:placetype":"locality"
},
  "geometry": {"coordinates":[69.75603000000001,38.11658],"type":"Point"}
}