{
  "type": "Feature",
  "properties": {
    "gn:admin1_code":"01",
    "gn:asciiname":"Bodaud",
    "gn:country_code":"TJ",
    "gn:dem":1861,
    "gn:feature_class":"P",
    "gn:feature_code":"PPL",
    "gn:name":"Bodaud",
    "gn:population":0,
    "gn:timezone":"Asia/Dushanbe",
    "iso:country":"TJ",
    "name:und_x_variant":[
        "Bodau",
        "Bodaud"
    ],
    "wof:name":"Bodaud",
    "wof:placetype":"locality"
},
  "geometry": {"coordinates":[71.42035,38.35386],"type":"Point"}
}