{
  "type": "Feature",
  "properties": {
    "gn:admin1_code":"02",
    "gn:asciiname":"Shaydon",
    "gn:country_code":"TJ",
    "gn:dem":1596,
    "gn:feature_class":"P",
    "gn:feature_code":"PPL",
    "gn:name":"Shaydon",
    "gn:population":0,
    "gn:timezone":"Asia/Dushanbe",
    "iso:country":"TJ",
    "name:und_x_variant":[
        "\u0428\u0430\u0439\u0434\u043e\u043d"
    ],
    "wof:name":"Shaydon",
    "wof:placetype":"locality"
},
  "geometry": {"coordinates":[69.87998,38.41482],"type":"Point"}
}