{
  "type": "Feature",
  "properties": {
    "gn:admin1_code":"02",
    "gn:asciiname":"Tugarak",
    "gn:country_code":"TJ",
    "gn:dem":479,
    "gn:feature_class":"P",
    "gn:feature_code":"PPL",
    "gn:name":"T\u016dgarak",
    "gn:population":0,
    "gn:timezone":"Asia/Dushanbe",
    "iso:country":"TJ",
    "name:tgk_x_preferred":[
        "Tugarak"
    ],
    "name:und_x_variant":[
        "T\u016dgarak",
        "\u0422\u04ef\u0433\u0430\u0440\u0430\u043a"
    ],
    "wof:name":"Tugarak",
    "wof:placetype":"locality"
},
  "geometry": {"coordinates":[69.67161999999999,37.80007],"type":"Point"}
}