{
  "type": "Feature",
  "properties": {
    "gn:admin1_code":"00",
    "gn:asciiname":"Khodzha-Isan",
    "gn:country_code":"TJ",
    "gn:dem":1186,
    "gn:feature_class":"P",
    "gn:feature_code":"PPL",
    "gn:name":"Khodzha-Isan",
    "gn:population":0,
    "gn:timezone":"Asia/Dushanbe",
    "iso:country":"TJ",
    "wof:name":"Khodzha-Isan",
    "wof:placetype":"locality"
},
  "geometry": {"coordinates":[69.81667,37.66667],"type":"Point"}
}