{
  "type": "Feature",
  "properties": {
    "gn:admin1_code":"02",
    "gn:asciiname":"Bachamazor",
    "gn:country_code":"TJ",
    "gn:dem":649,
    "gn:feature_class":"P",
    "gn:feature_code":"PPL",
    "gn:name":"Bachamazor",
    "gn:population":0,
    "gn:timezone":"Asia/Dushanbe",
    "iso:country":"TJ",
    "name:tgk_x_preferred":[
        "Bachamazor"
    ],
    "name:und_x_variant":[
        "Bacha-Mazar",
        "\u0411\u0430\u0447\u0430\u043c\u0430\u0437\u043e\u0440"
    ],
    "wof:name":"Bachamazor",
    "wof:placetype":"locality"
},
  "geometry": {"coordinates":[69.63404,37.98047],"type":"Point"}
}