{
  "type": "Feature",
  "properties": {
    "gn:admin1_code":"01",
    "gn:asciiname":"Shidz",
    "gn:country_code":"TJ",
    "gn:dem":2015,
    "gn:feature_class":"P",
    "gn:feature_code":"PPL",
    "gn:name":"Shidz",
    "gn:population":0,
    "gn:timezone":"Asia/Dushanbe",
    "iso:country":"TJ",
    "name:und_x_variant":[
        "\u0428\u0438\u0434\u044d"
    ],
    "wof:name":"Shidz",
    "wof:placetype":"locality"
},
  "geometry": {"coordinates":[71.31078000000002,37.924],"type":"Point"}
}