{
  "type": "Feature",
  "properties": {
    "gn:admin1_code":"RR",
    "gn:asciiname":"Arshi",
    "gn:country_code":"TJ",
    "gn:dem":1314,
    "gn:feature_class":"P",
    "gn:feature_code":"PPL",
    "gn:name":"Arshi",
    "gn:population":0,
    "gn:timezone":"Asia/Dushanbe",
    "iso:country":"TJ",
    "wof:name":"Arshi",
    "wof:placetype":"locality"
},
  "geometry": {"coordinates":[68.36962,38.65956],"type":"Point"}
}