{
  "type": "Feature",
  "properties": {
    "gn:admin1_code":"02",
    "gn:asciiname":"Kochkiya",
    "gn:country_code":"TJ",
    "gn:dem":366,
    "gn:feature_class":"P",
    "gn:feature_code":"PPL",
    "gn:name":"Kochkiya",
    "gn:population":0,
    "gn:timezone":"Asia/Dushanbe",
    "iso:country":"TJ",
    "wof:name":"Kochkiya",
    "wof:placetype":"locality"
},
  "geometry": {"coordinates":[69.12352,37.30542],"type":"Point"}
}