{
  "type": "Feature",
  "properties": {
    "gn:admin1_code":"RR",
    "gn:asciiname":"Omada",
    "gn:country_code":"TJ",
    "gn:dem":795,
    "gn:feature_class":"P",
    "gn:feature_code":"PPL",
    "gn:name":"Omada",
    "gn:population":0,
    "gn:timezone":"Asia/Dushanbe",
    "iso:country":"TJ",
    "wof:name":"Omada",
    "wof:placetype":"locality"
},
  "geometry": {"coordinates":[68.36254,38.54633],"type":"Point"}
}