{
  "type": "Feature",
  "properties": {
    "gn:admin1_code":"02",
    "gn:asciiname":"Sarym-Sagli",
    "gn:country_code":"TJ",
    "gn:dem":1090,
    "gn:feature_class":"P",
    "gn:feature_code":"PPL",
    "gn:name":"Sarym-Sagli",
    "gn:population":0,
    "gn:timezone":"Asia/Dushanbe",
    "iso:country":"TJ",
    "wof:name":"Sarym-Sagli",
    "wof:placetype":"locality"
},
  "geometry": {"coordinates":[69.76982,38.12073],"type":"Point"}
}