{
  "type": "Feature",
  "properties": {
    "gn:admin1_code":"02",
    "gn:asciiname":"Juzak",
    "gn:country_code":"TJ",
    "gn:dem":851,
    "gn:feature_class":"P",
    "gn:feature_code":"PPL",
    "gn:name":"Juzak",
    "gn:population":0,
    "gn:timezone":"Asia/Dushanbe",
    "iso:country":"TJ",
    "name:tgk_x_preferred":[
        "Juzak"
    ],
    "name:und_x_variant":[
        "Dzhyuzak"
    ],
    "wof:name":"Juzak",
    "wof:placetype":"locality"
},
  "geometry": {"coordinates":[69.15706999999999,37.73213],"type":"Point"}
}