{
  "type": "Feature",
  "properties": {
    "gn:admin1_code":"RR",
    "gn:asciiname":"Zarkamar",
    "gn:country_code":"TJ",
    "gn:dem":695,
    "gn:feature_class":"P",
    "gn:feature_code":"PPL",
    "gn:name":"Zarkamar",
    "gn:population":0,
    "gn:timezone":"Asia/Dushanbe",
    "iso:country":"TJ",
    "name:und_x_variant":[
        "Zarkomar",
        "Zarkamar"
    ],
    "wof:name":"Zarkamar",
    "wof:placetype":"locality"
},
  "geometry": {"coordinates":[68.2676,38.47827],"type":"Point"}
}