{
  "type": "Feature",
  "properties": {
    "gn:admin1_code":"02",
    "gn:asciiname":"Kartaypak",
    "gn:country_code":"TJ",
    "gn:dem":1070,
    "gn:feature_class":"P",
    "gn:feature_code":"PPL",
    "gn:name":"Kartaypak",
    "gn:population":0,
    "gn:timezone":"Asia/Dushanbe",
    "iso:country":"TJ",
    "wof:name":"Kartaypak",
    "wof:placetype":"locality"
},
  "geometry": {"coordinates":[69.69759999999999,38.0588],"type":"Point"}
}