{
  "type": "Feature",
  "properties": {
    "gn:admin1_code":"03",
    "gn:asciiname":"Quruqsoi",
    "gn:country_code":"TJ",
    "gn:dem":540,
    "gn:feature_class":"P",
    "gn:feature_code":"PPL",
    "gn:name":"Quruqso\u00ed",
    "gn:population":0,
    "gn:timezone":"Asia/Dushanbe",
    "iso:country":"TJ",
    "name:und_x_variant":[
        "Quruqso\u00ed",
        "\u049a\u0443\u0440\u0443\u049b\u0441\u043e\u04e3"
    ],
    "wof:name":"Quruqsoi",
    "wof:placetype":"locality"
},
  "geometry": {"coordinates":[69.407,40.72261],"type":"Point"}
}