{
  "type": "Feature",
  "properties": {
    "gn:admin1_code":"RR",
    "gn:asciiname":"Chashmaikulo",
    "gn:country_code":"TJ",
    "gn:dem":1766,
    "gn:feature_class":"P",
    "gn:feature_code":"PPL",
    "gn:name":"Chashmaikulo",
    "gn:population":0,
    "gn:timezone":"Asia/Dushanbe",
    "iso:country":"TJ",
    "wof:name":"Chashmaikulo",
    "wof:placetype":"locality"
},
  "geometry": {"coordinates":[69.6289,38.71029],"type":"Point"}
}