{
  "type": "Feature",
  "properties": {
    "gn:admin1_code":"01",
    "gn:asciiname":"Lukhch",
    "gn:country_code":"TJ",
    "gn:dem":2503,
    "gn:feature_class":"P",
    "gn:feature_code":"PPL",
    "gn:name":"Lukhch",
    "gn:population":0,
    "gn:timezone":"Asia/Dushanbe",
    "iso:country":"TJ",
    "name:und_x_variant":[
        "\u041b\u0443\u0445\u0447"
    ],
    "wof:name":"Lukhch",
    "wof:placetype":"locality"
},
  "geometry": {"coordinates":[70.68913000000001,38.67028],"type":"Point"}
}