{
  "type": "Feature",
  "properties": {
    "gn:admin1_code":"RR",
    "gn:asciiname":"Mekhtari Novyy",
    "gn:country_code":"TJ",
    "gn:dem":1044,
    "gn:feature_class":"P",
    "gn:feature_code":"PPL",
    "gn:name":"Mekhtari Novyy",
    "gn:population":0,
    "gn:timezone":"Asia/Dushanbe",
    "iso:country":"TJ",
    "wof:name":"Mekhtari Novyy",
    "wof:placetype":"locality"
},
  "geometry": {"coordinates":[68.90817,38.6051],"type":"Point"}
}