{
  "type": "Feature",
  "properties": {
    "gn:admin1_code":"RR",
    "gn:asciiname":"Tomchi",
    "gn:country_code":"TJ",
    "gn:dem":807,
    "gn:feature_class":"P",
    "gn:feature_code":"PPL",
    "gn:name":"Tomchi",
    "gn:population":0,
    "gn:timezone":"Asia/Dushanbe",
    "iso:country":"TJ",
    "name:und_x_variant":[
        "Tamchi",
        "Tomchi"
    ],
    "wof:name":"Tomchi",
    "wof:placetype":"locality"
},
  "geometry": {"coordinates":[68.93284,38.49781],"type":"Point"}
}