{
  "type": "Feature",
  "properties": {
    "gn:admin1_code":"02",
    "gn:asciiname":"Pakhtakor-Surkh",
    "gn:country_code":"TJ",
    "gn:dem":359,
    "gn:feature_class":"P",
    "gn:feature_code":"PPL",
    "gn:name":"Pakhtakor-Surkh",
    "gn:population":0,
    "gn:timezone":"Asia/Dushanbe",
    "iso:country":"TJ",
    "name:und_x_variant":[
        "Surkh",
        "Partizani Surkh",
        "Pakhtakor-Surkh"
    ],
    "wof:name":"Pakhtakor-Surkh",
    "wof:placetype":"locality"
},
  "geometry": {"coordinates":[68.54951,37.53611],"type":"Point"}
}