{
  "type": "Feature",
  "properties": {
    "gn:admin1_code":"02",
    "gn:asciiname":"Khuseynshug",
    "gn:country_code":"TJ",
    "gn:dem":719,
    "gn:feature_class":"P",
    "gn:feature_code":"PPL",
    "gn:name":"Khuseynshug",
    "gn:population":0,
    "gn:timezone":"Asia/Dushanbe",
    "iso:country":"TJ",
    "name:und_x_variant":[
        "Khusenshug",
        "Khuseynshug",
        "Huseynshaykh",
        "\u04b2\u0443\u0441\u0435\u0439\u043d\u0448\u0430\u0439\u0445"
    ],
    "wof:name":"Khuseynshug",
    "wof:placetype":"locality"
},
  "geometry": {"coordinates":[69.45893000000001,38.13224],"type":"Point"}
}