{
  "type": "Feature",
  "properties": {
    "gn:admin1_code":"RR",
    "gn:asciiname":"Frunze",
    "gn:country_code":"TJ",
    "gn:dem":685,
    "gn:feature_class":"P",
    "gn:feature_code":"PPL",
    "gn:name":"Frunze",
    "gn:population":0,
    "gn:timezone":"Asia/Dushanbe",
    "iso:country":"TJ",
    "name:bel_x_preferred":[
        "\u0424\u0440\u0443\u043d\u0437\u0435"
    ],
    "name:bul_x_preferred":[
        "\u0424\u0440\u0443\u043d\u0437\u0435"
    ],
    "name:ceb_x_preferred":[
        "Frunze"
    ],
    "name:ces_x_preferred":[
        "Frunze"
    ],
    "name:deu_x_preferred":[
        "Frunse"
    ],
    "name:est_x_preferred":[
        "Frunze"
    ],
    "name:fas_x_preferred":[
        "\u0641\u0631\u0648\u0646\u0632\u0647"
    ],
    "name:fin_x_preferred":[
        "Frunze"
    ],
    "name:fra_x_preferred":[
        "Frounze"
    ],
    "name:hun_x_preferred":[
        "Frunze"
    ],
    "name:hye_x_preferred":[
        "\u0556\u0580\u0578\u0582\u0576\u0566\u0565"
    ],
    "name:ita_x_preferred":[
        "Frunze"
    ],
    "name:jpn_x_preferred":[
        "\u30d5\u30eb\u30f3\u30bc"
    ],
    "name:kaz_x_preferred":[
        "\u0424\u0440\u0443\u043d\u0437\u0435"
    ],
    "name:kor_x_preferred":[
        "\ud504\ub8ec\uc81c"
    ],
    "name:lav_x_preferred":[
        "Frunze"
    ],
    "name:nld_x_preferred":[
        "Froenze"
    ],
    "name:pol_x_preferred":[
        "Frunze"
    ],
    "name:ron_x_preferred":[
        "Frunze"
    ],
    "name:rus_x_preferred":[
        "\u0424\u0440\u0443\u043d\u0437\u0435"
    ],
    "name:sah_x_preferred":[
        "\u0424\u0440\u0443\u043d\u0437\u0435"
    ],
    "name:slk_x_preferred":[
        "Frunze"
    ],
    "name:slv_x_preferred":[
        "Frunze"
    ],
    "name:spa_x_preferred":[
        "Frunze"
    ],
    "name:swe_x_preferred":[
        "Frunze"
    ],
    "name:tur_x_preferred":[
        "Frunze"
    ],
    "name:ukr_x_preferred":[
        "\u0424\u0440\u0443\u043d\u0437\u0435"
    ],
    "name:uzb_x_preferred":[
        "Frunze"
    ],
    "wof:name":"Frunze",
    "wof:placetype":"locality"
},
  "geometry": {"coordinates":[68.24311,38.49126],"type":"Point"}
}