{
  "type": "Feature",
  "properties": {
    "gn:admin1_code":"RR",
    "gn:asciiname":"Frunze",
    "gn:country_code":"TJ",
    "gn:dem":685,
    "gn:feature_class":"P",
    "gn:feature_code":"PPL",
    "gn:name":"Frunze",
    "gn:population":0,
    "gn:timezone":"Asia/Dushanbe",
    "iso:country":"TJ",
    "name:uzb_x_preferred":[
        "Frunze"
    ],
    "wof:name":"Frunze",
    "wof:placetype":"locality"
},
  "geometry": {"coordinates":[68.24311,38.49126],"type":"Point"}
}