{
  "type": "Feature",
  "properties": {
    "gn:admin1_code":"03",
    "gn:asciiname":"Ghaznich",
    "gn:country_code":"TJ",
    "gn:dem":2050,
    "gn:feature_class":"P",
    "gn:feature_code":"PPL",
    "gn:name":"Ghaznich",
    "gn:population":0,
    "gn:timezone":"Asia/Dushanbe",
    "iso:country":"TJ",
    "name:fas_x_preferred":[
        "\u06af\u0627\u0632\u0646\u06cc\u0686"
    ],
    "name:msa_x_preferred":[
        "Gaznich"
    ],
    "name:und_x_variant":[
        "Gaznych",
        "Ghaznich",
        "\u0492\u0430\u0437\u043d\u0438\u0447"
    ],
    "wof:name":"Ghaznich",
    "wof:placetype":"locality"
},
  "geometry": {"coordinates":[68.04382,39.22635],"type":"Point"}
}