{
  "type": "Feature",
  "properties": {
    "gn:admin1_code":"02",
    "gn:asciiname":"Arab",
    "gn:country_code":"TJ",
    "gn:dem":353,
    "gn:feature_class":"P",
    "gn:feature_code":"PPL",
    "gn:name":"Arab",
    "gn:population":0,
    "gn:timezone":"Asia/Dushanbe",
    "iso:country":"TJ",
    "name:und_x_variant":[
        "\u0410\u0440\u0430\u0431"
    ],
    "wof:name":"Arab",
    "wof:placetype":"locality"
},
  "geometry": {"coordinates":[69.04618000000001,37.2921],"type":"Point"}
}