{
  "type": "Feature",
  "properties": {
    "gn:admin1_code":"02",
    "gn:asciiname":"Qahramon",
    "gn:country_code":"TJ",
    "gn:dem":386,
    "gn:feature_class":"P",
    "gn:feature_code":"PPL",
    "gn:name":"Qahramon",
    "gn:population":0,
    "gn:timezone":"Asia/Dushanbe",
    "iso:country":"TJ",
    "name:ceb_x_preferred":[
        "Qahramon"
    ],
    "name:ckb_x_preferred":[
        "\u0642\u06d5\u06be\u0631\u06d5\u0645\u0627\u0646"
    ],
    "name:fas_x_preferred":[
        "\u0642\u0647\u0631\u0645\u0627\u0646"
    ],
    "name:kik_x_preferred":[
        "Qahramon"
    ],
    "name:tgk_x_preferred":[
        "\u0414\u0435\u04b3\u043e\u0442\u0438 \u049a\u0430\u04b3\u0440\u0430\u043c\u043e\u043d"
    ],
    "name:ukr_x_preferred":[
        "\u041a\u0430\u0445\u0440\u0430\u043c\u043e\u043d\u0441\u044c\u043a\u0438\u0439 \u0434\u0436\u0430\u043c\u043e\u0430\u0442"
    ],
    "name:und_x_variant":[
        "\u049a\u0430\u04b3\u0440\u0430\u043c\u043e\u043d"
    ],
    "wof:name":"Qahramon",
    "wof:placetype":"locality"
},
  "geometry": {"coordinates":[68.62789000000001,37.52092],"type":"Point"}
}