{
  "type": "Feature",
  "properties": {
    "gn:admin1_code":"02",
    "gn:asciiname":"Qahramon",
    "gn:country_code":"TJ",
    "gn:dem":386,
    "gn:feature_class":"P",
    "gn:feature_code":"PPL",
    "gn:name":"Qahramon",
    "gn:population":0,
    "gn:timezone":"Asia/Dushanbe",
    "iso:country":"TJ",
    "name:und_x_variant":[
        "\u049a\u0430\u04b3\u0440\u0430\u043c\u043e\u043d"
    ],
    "wof:name":"Qahramon",
    "wof:placetype":"locality"
},
  "geometry": {"coordinates":[68.62789000000001,37.52092],"type":"Point"}
}