{
  "type": "Feature",
  "properties": {
    "gn:admin1_code":"RR",
    "gn:asciiname":"Kurbonkusa",
    "gn:country_code":"TJ",
    "gn:dem":615,
    "gn:feature_class":"P",
    "gn:feature_code":"PPL",
    "gn:name":"K\u016drbonk\u016dsa",
    "gn:population":0,
    "gn:timezone":"Asia/Dushanbe",
    "iso:country":"TJ",
    "name:und_x_variant":[
        "Kurban-Kusa",
        "K\u016drbonk\u016dsa"
    ],
    "name:uzb_x_preferred":[
        "Qurbonko\u2018sa"
    ],
    "wof:name":"Kurbonkusa",
    "wof:placetype":"locality"
},
  "geometry": {"coordinates":[68.1584,38.44224000000001],"type":"Point"}
}