{
  "type": "Feature",
  "properties": {
    "gn:admin1_code":"01",
    "gn:asciiname":"Garnavat",
    "gn:country_code":"TJ",
    "gn:dem":3011,
    "gn:feature_class":"P",
    "gn:feature_code":"PPL",
    "gn:name":"Garnavat",
    "gn:population":0,
    "gn:timezone":"Asia/Dushanbe",
    "iso:country":"TJ",
    "wof:name":"Garnavat",
    "wof:placetype":"locality"
},
  "geometry": {"coordinates":[71.59999999999999,38.48333],"type":"Point"}
}