{
  "type": "Feature",
  "properties": {
    "gn:admin1_code":"RR",
    "gn:asciiname":"Beshbulok",
    "gn:country_code":"TJ",
    "gn:dem":1140,
    "gn:feature_class":"P",
    "gn:feature_code":"PPL",
    "gn:name":"Beshbulok",
    "gn:population":0,
    "gn:timezone":"Asia/Dushanbe",
    "iso:country":"TJ",
    "wof:name":"Beshbulok",
    "wof:placetype":"locality"
},
  "geometry": {"coordinates":[68.59749000000001,38.59032],"type":"Point"}
}