{
  "type": "Feature",
  "properties": {
    "gn:admin1_code":"02",
    "gn:asciiname":"Alijon",
    "gn:country_code":"TJ",
    "gn:dem":947,
    "gn:feature_class":"P",
    "gn:feature_code":"PPL",
    "gn:name":"Alijon",
    "gn:population":0,
    "gn:timezone":"Asia/Dushanbe",
    "iso:country":"TJ",
    "name:und_x_variant":[
        "Alidzhan",
        "Alijon",
        "\u0410\u043b\u0438\u04b7\u043e\u043d"
    ],
    "wof:name":"Alijon",
    "wof:placetype":"locality"
},
  "geometry": {"coordinates":[69.39418000000001,38.17018],"type":"Point"}
}