{
  "type": "Feature",
  "properties": {
    "gn:admin1_code":"00",
    "gn:asciiname":"Kul'-Ayud-Bek",
    "gn:country_code":"TJ",
    "gn:dem":1754,
    "gn:feature_class":"P",
    "gn:feature_code":"PPL",
    "gn:name":"Kul'-Ayud-Bek",
    "gn:population":0,
    "gn:timezone":"Asia/Dushanbe",
    "iso:country":"TJ",
    "wof:name":"Kul'-Ayud-Bek",
    "wof:placetype":"locality"
},
  "geometry": {"coordinates":[69.98333000000001,37.96667],"type":"Point"}
}