{
  "type": "Feature",
  "properties": {
    "gn:admin1_code":"02",
    "gn:asciiname":"Namozbuloq",
    "gn:country_code":"TJ",
    "gn:dem":779,
    "gn:feature_class":"P",
    "gn:feature_code":"PPL",
    "gn:name":"Namozbuloq",
    "gn:population":0,
    "gn:timezone":"Asia/Dushanbe",
    "iso:country":"TJ",
    "name:tgk_x_preferred":[
        "Namozbuloq"
    ],
    "name:und_x_variant":[
        "\u041d\u0430\u043c\u043e\u0437\u0431\u0443\u043b\u043e\u049b"
    ],
    "wof:name":"Namozbuloq",
    "wof:placetype":"locality"
},
  "geometry": {"coordinates":[68.00805,37.6142],"type":"Point"}
}