{
  "type": "Feature",
  "properties": {
    "gn:admin1_code":"03",
    "gn:asciiname":"Ariqi Yakum",
    "gn:country_code":"TJ",
    "gn:dem":430,
    "gn:feature_class":"P",
    "gn:feature_code":"PPL",
    "gn:name":"Ariqi Yak\u016dm",
    "gn:population":0,
    "gn:timezone":"Asia/Dushanbe",
    "iso:country":"TJ",
    "name:und_x_variant":[
        "Ariqi Yak\u016dm",
        "\u0410\u0440\u0438\u049b\u0438 \u042f\u043a\u04ef\u043c"
    ],
    "wof:name":"Ariqi Yakum",
    "wof:placetype":"locality"
},
  "geometry": {"coordinates":[69.82999000000001,40.1879],"type":"Point"}
}