{
  "type": "Feature",
  "properties": {
    "gn:admin1_code":"RR",
    "gn:asciiname":"Gou-Gavdi-Pao",
    "gn:country_code":"TJ",
    "gn:dem":2403,
    "gn:feature_class":"P",
    "gn:feature_code":"PPL",
    "gn:name":"Gou-Gavdi-Pao",
    "gn:population":0,
    "gn:timezone":"Asia/Dushanbe",
    "iso:country":"TJ",
    "name:und_x_variant":[
        "Gou-Gavdi-Nau",
        "Gou",
        "Gou-Gavdi-Pao"
    ],
    "wof:name":"Gou-Gavdi-Pao",
    "wof:placetype":"locality"
},
  "geometry": {"coordinates":[70.95,38.88333],"type":"Point"}
}