{
  "type": "Feature",
  "properties": {
    "gn:admin1_code":"02",
    "gn:asciiname":"Shurkul",
    "gn:country_code":"TJ",
    "gn:dem":469,
    "gn:feature_class":"P",
    "gn:feature_code":"PPL",
    "gn:name":"Shurk\u016dl",
    "gn:population":0,
    "gn:timezone":"Asia/Dushanbe",
    "iso:country":"TJ",
    "name:tgk_x_preferred":[
        "Shurk\u016dl"
    ],
    "wof:name":"Shurkul",
    "wof:placetype":"locality"
},
  "geometry": {"coordinates":[69.48966999999999,37.62706],"type":"Point"}
}