{
  "type": "Feature",
  "properties": {
    "gn:admin1_code":"RR",
    "gn:asciiname":"Rangok",
    "gn:country_code":"TJ",
    "gn:dem":1520,
    "gn:feature_class":"P",
    "gn:feature_code":"PPL",
    "gn:name":"Rangok",
    "gn:population":0,
    "gn:timezone":"Asia/Dushanbe",
    "iso:country":"TJ",
    "name:und_x_variant":[
        "Rangon",
        "Rangok"
    ],
    "wof:name":"Rangok",
    "wof:placetype":"locality"
},
  "geometry": {"coordinates":[68.82885999999999,38.3704],"type":"Point"}
}