{
  "type": "Feature",
  "properties": {
    "gn:admin1_code":"RR",
    "gn:asciiname":"Soni",
    "gn:country_code":"TJ",
    "gn:dem":1617,
    "gn:feature_class":"P",
    "gn:feature_code":"PPL",
    "gn:name":"Soni",
    "gn:population":0,
    "gn:timezone":"Asia/Dushanbe",
    "iso:country":"TJ",
    "name:ceb_x_preferred":[
        "Soni"
    ],
    "name:deu_x_preferred":[
        "Soni"
    ],
    "name:ita_x_preferred":[
        "Soni"
    ],
    "name:nld_x_preferred":[
        "Soni"
    ],
    "name:rus_x_preferred":[
        "\u0421\u043e\u043d\u0438"
    ],
    "name:swe_x_preferred":[
        "Soni"
    ],
    "name:ukr_x_preferred":[
        "\u0421\u043e\u043d\u0456"
    ],
    "wof:name":"Soni",
    "wof:placetype":"locality"
},
  "geometry": {"coordinates":[69.44244,38.82574],"type":"Point"}
}