{
  "type": "Feature",
  "properties": {
    "gn:admin1_code":"RR",
    "gn:asciiname":"Ak-Tak",
    "gn:country_code":"TJ",
    "gn:dem":1202,
    "gn:feature_class":"P",
    "gn:feature_code":"PPL",
    "gn:name":"Ak-Tak",
    "gn:population":0,
    "gn:timezone":"Asia/Dushanbe",
    "iso:country":"TJ",
    "wof:name":"Ak-Tak",
    "wof:placetype":"locality"
},
  "geometry": {"coordinates":[68.86667,38.61667],"type":"Point"}
}