{
  "type": "Feature",
  "properties": {
    "gn:admin1_code":"02",
    "gn:asciiname":"Bogdayen",
    "gn:country_code":"TJ",
    "gn:dem":1094,
    "gn:feature_class":"P",
    "gn:feature_code":"PPL",
    "gn:name":"Bogday\u00ebn",
    "gn:population":0,
    "gn:timezone":"Asia/Dushanbe",
    "iso:country":"TJ",
    "wof:name":"Bogdayen",
    "wof:placetype":"locality"
},
  "geometry": {"coordinates":[69.86263000000001,38.18275],"type":"Point"}
}