{
  "type": "Feature",
  "properties": {
    "gn:admin1_code":"RR",
    "gn:asciiname":"Gulbog",
    "gn:country_code":"TJ",
    "gn:dem":1271,
    "gn:feature_class":"P",
    "gn:feature_code":"PPL",
    "gn:name":"Gulbog",
    "gn:population":0,
    "gn:timezone":"Asia/Dushanbe",
    "iso:country":"TJ",
    "wof:name":"Gulbog",
    "wof:placetype":"locality"
},
  "geometry": {"coordinates":[68.95805,38.62613],"type":"Point"}
}