{
  "type": "Feature",
  "properties": {
    "gn:admin1_code":"RR",
    "gn:asciiname":"Khushon",
    "gn:country_code":"TJ",
    "gn:dem":1308,
    "gn:feature_class":"P",
    "gn:feature_code":"PPL",
    "gn:name":"Khushon",
    "gn:population":0,
    "gn:timezone":"Asia/Dushanbe",
    "iso:country":"TJ",
    "wof:name":"Khushon",
    "wof:placetype":"locality"
},
  "geometry": {"coordinates":[69.28098,38.77127],"type":"Point"}
}