{
  "type": "Feature",
  "properties": {
    "gn:admin1_code":"03",
    "gn:asciiname":"Narge-Say",
    "gn:country_code":"TJ",
    "gn:dem":1758,
    "gn:feature_class":"P",
    "gn:feature_code":"PPL",
    "gn:name":"Narge-Say",
    "gn:population":0,
    "gn:timezone":"Asia/Dushanbe",
    "iso:country":"TJ",
    "wof:name":"Narge-Say",
    "wof:placetype":"locality"
},
  "geometry": {"coordinates":[68.36667,39.46667],"type":"Point"}
}