{
  "type": "Feature",
  "properties": {
    "gn:admin1_code":"03",
    "gn:asciiname":"Voru",
    "gn:country_code":"TJ",
    "gn:dem":2295,
    "gn:feature_class":"P",
    "gn:feature_code":"PPL",
    "gn:name":"Voru",
    "gn:population":0,
    "gn:timezone":"Asia/Dushanbe",
    "iso:country":"TJ",
    "name:und_x_variant":[
        "\u0412\u043e\u0440\u0443"
    ],
    "wof:name":"Voru",
    "wof:placetype":"locality"
},
  "geometry": {"coordinates":[67.98862,39.23432],"type":"Point"}
}