{
  "type": "Feature",
  "properties": {
    "gn:admin1_code":"00",
    "gn:asciiname":"Kishtibolo",
    "gn:country_code":"TJ",
    "gn:dem":1585,
    "gn:feature_class":"P",
    "gn:feature_code":"PPL",
    "gn:name":"Kishtibolo",
    "gn:population":0,
    "gn:timezone":"Asia/Dushanbe",
    "iso:country":"TJ",
    "wof:name":"Kishtibolo",
    "wof:placetype":"locality"
},
  "geometry": {"coordinates":[70.13333,37.93333],"type":"Point"}
}