{
  "type": "Feature",
  "properties": {
    "gn:admin1_code":"02",
    "gn:asciiname":"Sangtuda",
    "gn:country_code":"TJ",
    "gn:dem":565,
    "gn:feature_class":"P",
    "gn:feature_code":"PPL",
    "gn:name":"Sangt\u016dda",
    "gn:population":0,
    "gn:timezone":"Asia/Dushanbe",
    "iso:country":"TJ",
    "name:ckb_x_preferred":[
        "\u0633\u06d5\u0646\u06af\u062a\u0648\u062f\u06d5"
    ],
    "name:fas_x_preferred":[
        "\u0633\u0646\u06af\u200c\u062a\u0648\u062f\u0647"
    ],
    "name:tgk_x_preferred":[
        "\u0414\u0435\u04b3\u043e\u0442\u0438 \u0421\u0430\u043d\u0433\u0442\u04ef\u0434\u0430"
    ],
    "name:und_x_variant":[
        "Sangt\u016dda",
        "\u0421\u0430\u043d\u0433\u0442\u04ef\u0434\u0430"
    ],
    "wof:name":"Sangtuda",
    "wof:placetype":"locality"
},
  "geometry": {"coordinates":[69.07411,38.04258],"type":"Point"}
}