{
  "type": "Feature",
  "properties": {
    "gn:admin1_code":"01",
    "gn:asciiname":"Zhovid",
    "gn:country_code":"TJ",
    "gn:dem":1993,
    "gn:feature_class":"P",
    "gn:feature_code":"PPL",
    "gn:name":"Zhovid",
    "gn:population":0,
    "gn:timezone":"Asia/Dushanbe",
    "iso:country":"TJ",
    "name:und_x_variant":[
        "Dzhauvid",
        "Dzhivid",
        "Dzhouvid",
        "Dzhovud",
        "Zhovid"
    ],
    "wof:name":"Zhovid",
    "wof:placetype":"locality"
},
  "geometry": {"coordinates":[71.62770999999999,38.47008],"type":"Point"}
}