{
  "type": "Feature",
  "properties": {
    "gn:admin1_code":"02",
    "gn:asciiname":"Obikiik",
    "gn:country_code":"TJ",
    "gn:dem":662,
    "gn:feature_class":"P",
    "gn:feature_code":"PPLA2",
    "gn:name":"Obikiik",
    "gn:population":0,
    "gn:timezone":"Asia/Dushanbe",
    "iso:country":"TJ",
    "name:und_x_variant":[
        "\u041e\u0431\u0438\u043a\u0438\u0438\u043a"
    ],
    "wof:name":"Obikiik",
    "wof:placetype":"locality"
},
  "geometry": {"coordinates":[68.66605,38.16033],"type":"Point"}
}