{
  "type": "Feature",
  "properties": {
    "gn:admin1_code":"00",
    "gn:asciiname":"Ghorbuloq",
    "gn:country_code":"TJ",
    "gn:dem":1013,
    "gn:feature_class":"P",
    "gn:feature_code":"PPL",
    "gn:name":"Ghorbuloq",
    "gn:population":0,
    "gn:timezone":"Asia/Dushanbe",
    "iso:country":"TJ",
    "name:und_x_variant":[
        "Gar-Bulak",
        "Garbulok",
        "Garbuloq",
        "Ghorbuloq",
        "\u0492\u043e\u0440\u0431\u0443\u043b\u043e\u049b",
        "Tut-Bulak"
    ],
    "wof:name":"Ghorbuloq",
    "wof:placetype":"locality"
},
  "geometry": {"coordinates":[68.94579,38.38741],"type":"Point"}
}