{
  "type": "Feature",
  "properties": {
    "gn:admin1_code":"02",
    "gn:asciiname":"Gulobod",
    "gn:country_code":"TJ",
    "gn:dem":485,
    "gn:feature_class":"P",
    "gn:feature_code":"PPL",
    "gn:name":"Gulobod",
    "gn:population":0,
    "gn:timezone":"Asia/Dushanbe",
    "iso:country":"TJ",
    "name:rus_x_preferred":[
        "Gul\u2019abad"
    ],
    "name:tgk_x_preferred":[
        "Gulobod"
    ],
    "name:und_x_variant":[
        "Marazteppa",
        "\u0413\u0443\u043b\u043e\u0431\u043e\u0434"
    ],
    "wof:name":"Gulobod",
    "wof:placetype":"locality"
},
  "geometry": {"coordinates":[69.59817,37.82197],"type":"Point"}
}