{
  "type": "Feature",
  "properties": {
    "gn:admin1_code":"02",
    "gn:asciiname":"Shahob",
    "gn:country_code":"TJ",
    "gn:dem":388,
    "gn:feature_class":"P",
    "gn:feature_code":"PPL",
    "gn:name":"Shahob",
    "gn:population":0,
    "gn:timezone":"Asia/Dushanbe",
    "iso:country":"TJ",
    "name:tgk_x_preferred":[
        "Shakhob"
    ],
    "name:und_x_variant":[
        "\u0428\u0430\u04b3\u043e\u0431"
    ],
    "wof:name":"Shahob",
    "wof:placetype":"locality"
},
  "geometry": {"coordinates":[68.18499,37.36105],"type":"Point"}
}