{
  "type": "Feature",
  "properties": {
    "gn:admin1_code":"02",
    "gn:asciiname":"Gulisurkh",
    "gn:country_code":"TJ",
    "gn:dem":1258,
    "gn:feature_class":"P",
    "gn:feature_code":"PPL",
    "gn:name":"Gulisurkh",
    "gn:population":0,
    "gn:timezone":"Asia/Dushanbe",
    "iso:country":"TJ",
    "wof:name":"Gulisurkh",
    "wof:placetype":"locality"
},
  "geometry": {"coordinates":[69.22306999999999,38.44342],"type":"Point"}
}