{
  "type": "Feature",
  "properties": {
    "gn:admin1_code":"RR",
    "gn:asciiname":"Shpilion",
    "gn:country_code":"TJ",
    "gn:dem":1825,
    "gn:feature_class":"P",
    "gn:feature_code":"PPL",
    "gn:name":"Shpilion",
    "gn:population":0,
    "gn:timezone":"Asia/Dushanbe",
    "iso:country":"TJ",
    "wof:name":"Shpilion",
    "wof:placetype":"locality"
},
  "geometry": {"coordinates":[70.77983,38.84034000000001],"type":"Point"}
}