{
  "type": "Feature",
  "properties": {
    "gn:admin1_code":"RR",
    "gn:asciiname":"Farrukh",
    "gn:country_code":"TJ",
    "gn:dem":2111,
    "gn:feature_class":"P",
    "gn:feature_code":"PPL",
    "gn:name":"Farrukh",
    "gn:population":0,
    "gn:timezone":"Asia/Dushanbe",
    "iso:country":"TJ",
    "wof:name":"Farrukh",
    "wof:placetype":"locality"
},
  "geometry": {"coordinates":[69.65713000000001,38.67233],"type":"Point"}
}