{
  "type": "Feature",
  "properties": {
    "gn:admin1_code":"02",
    "gn:asciiname":"Langar",
    "gn:country_code":"TJ",
    "gn:dem":1472,
    "gn:feature_class":"P",
    "gn:feature_code":"PPL",
    "gn:name":"Langar",
    "gn:population":0,
    "gn:timezone":"Asia/Dushanbe",
    "iso:country":"TJ",
    "name:ceb_x_preferred":[
        "Langar"
    ],
    "name:deu_x_preferred":[
        "Langar"
    ],
    "name:swe_x_preferred":[
        "Langar"
    ],
    "name:tgk_x_preferred":[
        "Langar"
    ],
    "name:und_x_variant":[
        "Lyangar-Kolon",
        "Langar-Kalon",
        "\u041b\u0430\u043d\u0433\u0430\u0440"
    ],
    "name:urd_x_preferred":[
        "\u0644\u0646\u06af\u0631"
    ],
    "name:uzb_x_preferred":[
        "Langar"
    ],
    "wof:name":"Langar",
    "wof:placetype":"locality"
},
  "geometry": {"coordinates":[70.00328,37.98442],"type":"Point"}
}