{
  "type": "Feature",
  "properties": {
    "gn:admin1_code":"03",
    "gn:asciiname":"Poshkent",
    "gn:country_code":"TJ",
    "gn:dem":1081,
    "gn:feature_class":"P",
    "gn:feature_code":"PPL",
    "gn:name":"Poshkent",
    "gn:population":0,
    "gn:timezone":"Asia/Dushanbe",
    "iso:country":"TJ",
    "name:ceb_x_preferred":[
        "Poshkent"
    ],
    "name:fas_x_preferred":[
        "\u067e\u0627\u0634\u06a9\u0646\u062f"
    ],
    "name:msa_x_preferred":[
        "Poshkent"
    ],
    "name:tgk_x_preferred":[
        "\u04b6\u0430\u043c\u043e\u0430\u0442\u0438 \u041f\u043e\u0448\u043a\u0435\u043d\u0442"
    ],
    "name:und_x_variant":[
        "\u041f\u043e\u0448\u043a\u0435\u043d\u0442"
    ],
    "name:urd_x_preferred":[
        "\u067e\u0627\u0634\u0642\u0646\u062f"
    ],
    "wof:name":"Poshkent",
    "wof:placetype":"locality"
},
  "geometry": {"coordinates":[69.02705,39.88018],"type":"Point"}
}