{
  "type": "Feature",
  "properties": {
    "gn:admin1_code":"03",
    "gn:asciiname":"Poshkent",
    "gn:country_code":"TJ",
    "gn:dem":1081,
    "gn:feature_class":"P",
    "gn:feature_code":"PPL",
    "gn:name":"Poshkent",
    "gn:population":0,
    "gn:timezone":"Asia/Dushanbe",
    "iso:country":"TJ",
    "name:und_x_variant":[
        "\u041f\u043e\u0448\u043a\u0435\u043d\u0442"
    ],
    "wof:name":"Poshkent",
    "wof:placetype":"locality"
},
  "geometry": {"coordinates":[69.02705,39.88018],"type":"Point"}
}