{
  "type": "Feature",
  "properties": {
    "gn:admin1_code":"RR",
    "gn:asciiname":"Shaikhak",
    "gn:country_code":"TJ",
    "gn:dem":1208,
    "gn:feature_class":"P",
    "gn:feature_code":"PPL",
    "gn:name":"Sha\u00edkhak",
    "gn:population":0,
    "gn:timezone":"Asia/Dushanbe",
    "iso:country":"TJ",
    "name:und_x_variant":[
        "Shaykhon",
        "Sheykhon",
        "Sha\u00edkhak"
    ],
    "wof:name":"Shaikhak",
    "wof:placetype":"locality"
},
  "geometry": {"coordinates":[68.90352,38.62606],"type":"Point"}
}