{
  "type": "Feature",
  "properties": {
    "gn:admin1_code":"03",
    "gn:asciiname":"Chilgazi",
    "gn:country_code":"TJ",
    "gn:dem":829,
    "gn:feature_class":"P",
    "gn:feature_code":"PPL",
    "gn:name":"Chilgaz\u00ed",
    "gn:population":0,
    "gn:timezone":"Asia/Bishkek",
    "iso:country":"TJ",
    "name:tgk_x_preferred":[
        "Chilgaz\u00ed"
    ],
    "name:tgk_x_variant":[
        "\u0427\u0438\u043b\u0433\u0430\u0437\u04e3"
    ],
    "name:und_x_variant":[
        "Chil\u2019gazi",
        "Chil\u2019gazy"
    ],
    "name:uzb_x_preferred":[
        "Chilg\u2018ozi"
    ],
    "wof:name":"Chilgazi",
    "wof:placetype":"locality"
},
  "geometry": {"coordinates":[70.73169,40.15689],"type":"Point"}
}