{
  "type": "Feature",
  "properties": {
    "gn:admin1_code":"RR",
    "gn:asciiname":"Novakipoyen",
    "gn:country_code":"TJ",
    "gn:dem":1626,
    "gn:feature_class":"P",
    "gn:feature_code":"PPL",
    "gn:name":"Novakipoy\u00ebn",
    "gn:population":0,
    "gn:timezone":"Asia/Dushanbe",
    "iso:country":"TJ",
    "name:und_x_variant":[
        "Novak",
        "Novakipoy\u00ebn"
    ],
    "wof:name":"Novakipoyen",
    "wof:placetype":"locality"
},
  "geometry": {"coordinates":[69.26666999999999,38.88333],"type":"Point"}
}