{
  "type": "Feature",
  "properties": {
    "gn:admin1_code":"02",
    "gn:asciiname":"Qazoqmazor",
    "gn:country_code":"TJ",
    "gn:dem":778,
    "gn:feature_class":"P",
    "gn:feature_code":"PPL",
    "gn:name":"Qazoqmazor",
    "gn:population":0,
    "gn:timezone":"Asia/Dushanbe",
    "iso:country":"TJ",
    "name:tgk_x_preferred":[
        "Kazakmazor"
    ],
    "name:und_x_variant":[
        "\u049a\u0430\u0437\u043e\u049b\u043c\u0430\u0437\u043e\u0440"
    ],
    "wof:name":"Qazoqmazor",
    "wof:placetype":"locality"
},
  "geometry": {"coordinates":[69.11425,37.80885],"type":"Point"}
}