{
  "type": "Feature",
  "properties": {
    "gn:admin1_code":"RR",
    "gn:asciiname":"Tuda",
    "gn:country_code":"TJ",
    "gn:dem":924,
    "gn:feature_class":"P",
    "gn:feature_code":"PPL",
    "gn:name":"Tuda",
    "gn:population":0,
    "gn:timezone":"Asia/Dushanbe",
    "iso:country":"TJ",
    "name:uzb_x_preferred":[
        "To\u2018da"
    ],
    "wof:name":"Tuda",
    "wof:placetype":"locality"
},
  "geometry": {"coordinates":[68.47721999999999,38.57893],"type":"Point"}
}