{
  "type": "Feature",
  "properties": {
    "gn:admin1_code":"RR",
    "gn:asciiname":"Qarabuloq",
    "gn:country_code":"TJ",
    "gn:dem":1081,
    "gn:feature_class":"P",
    "gn:feature_code":"PPL",
    "gn:name":"Qarabuloq",
    "gn:population":0,
    "gn:timezone":"Asia/Dushanbe",
    "iso:country":"TJ",
    "name:und_x_variant":[
        "Karabulok",
        "Qarabuloq"
    ],
    "wof:name":"Qarabuloq",
    "wof:placetype":"locality"
},
  "geometry": {"coordinates":[69.16611,38.53818],"type":"Point"}
}