{
  "type": "Feature",
  "properties": {
    "gn:admin1_code":"01",
    "gn:asciiname":"Shoshbuvad",
    "gn:country_code":"TJ",
    "gn:dem":3252,
    "gn:feature_class":"P",
    "gn:feature_code":"PPL",
    "gn:name":"Shoshbuvad",
    "gn:population":0,
    "gn:timezone":"Asia/Dushanbe",
    "iso:country":"TJ",
    "name:und_x_variant":[
        "Shash-Buat",
        "Shashevat",
        "Shoshbulat",
        "Shos-Bulat",
        "Shoshbuvad",
        "\u0428\u043e\u0448\u0431\u0443\u0432\u0430\u0434"
    ],
    "wof:name":"Shoshbuvad",
    "wof:placetype":"locality"
},
  "geometry": {"coordinates":[72.27571999999998,37.34709],"type":"Point"}
}