{
  "type": "Feature",
  "properties": {
    "gn:admin1_code":"02",
    "gn:asciiname":"Mogol",
    "gn:country_code":"TJ",
    "gn:dem":616,
    "gn:feature_class":"P",
    "gn:feature_code":"PPL",
    "gn:name":"Mogol",
    "gn:population":0,
    "gn:timezone":"Asia/Dushanbe",
    "iso:country":"TJ",
    "wof:name":"Mogol",
    "wof:placetype":"locality"
},
  "geometry": {"coordinates":[69.75546999999999,37.96327],"type":"Point"}
}