{
  "type": "Feature",
  "properties": {
    "gn:admin1_code":"RR",
    "gn:asciiname":"Chingirov",
    "gn:country_code":"TJ",
    "gn:dem":903,
    "gn:feature_class":"P",
    "gn:feature_code":"PPL",
    "gn:name":"Chingirov",
    "gn:population":0,
    "gn:timezone":"Asia/Dushanbe",
    "iso:country":"TJ",
    "name:uzb_x_preferred":[
        "Chingirov"
    ],
    "wof:name":"Chingirov",
    "wof:placetype":"locality"
},
  "geometry": {"coordinates":[68.33905,38.36288],"type":"Point"}
}