{
  "type": "Feature",
  "properties": {
    "gn:admin1_code":"01",
    "gn:asciiname":"Rid",
    "gn:country_code":"TJ",
    "gn:dem":2066,
    "gn:feature_class":"P",
    "gn:feature_code":"PPL",
    "gn:name":"Rid",
    "gn:population":0,
    "gn:timezone":"Asia/Dushanbe",
    "iso:country":"TJ",
    "wof:name":"Rid",
    "wof:placetype":"locality"
},
  "geometry": {"coordinates":[71.72955,37.97095],"type":"Point"}
}