{
  "type": "Feature",
  "properties": {
    "iso:country":"TJ",
    "name:bul_x_preferred":[
        "\u0418\u0441\u0442\u0438\u043a\u043b\u043e\u043b"
    ],
    "name:deu_x_preferred":[
        "Istiqlol"
    ],
    "name:eng_x_preferred":[
        "Taboshar"
    ],
    "name:fas_x_preferred":[
        "\u062a\u0628\u0627\u0634\u0631"
    ],
    "name:nld_x_preferred":[
        "Taboshar"
    ],
    "name:pol_x_preferred":[
        "Taboszar"
    ],
    "name:pus_x_preferred":[
        "\u062a\u0648\u0628\u0648\u0634\u0631"
    ],
    "name:rus_x_preferred":[
        "\u0418\u0441\u0442\u0438\u043a\u043b\u043e\u043b"
    ],
    "name:rus_x_variant":[
        "\u0422\u0430\u0431\u043e\u0448\u0430\u0440"
    ],
    "name:tgk_x_preferred":[
        "\u0422\u0430\u0431\u043e\u0448\u0430\u0440"
    ],
    "name:ukr_x_preferred":[
        "\u0406\u0441\u0442\u0456\u043a\u043b\u043e\u043b"
    ],
    "name:unk_x_variant":[
        "Taboshary"
    ],
    "qs:gn_country":"TJ",
    "qs:gn_fcode":"PPL",
    "qs:gn_pop":11578,
    "qs:name":"Taboshar",
    "qs:name_adm0":"Tajikistan",
    "qs:name_adm1":"Leninobod",
    "qs:photos":0,
    "qs:photos_1k":0,
    "qs:photos_9k":0,
    "qs:photos_9r":0,
    "qs:photos_all":0,
    "qs:photos_sr":0,
    "qs:placetype":"Town",
    "qs:pop_sr":"6",
    "qs:woe_adm0":23424961,
    "wd:wordcount":111,
    "wof:name":"Taboshar",
    "wof:placetype":"locality",
    "wof:population":11578
},
  "geometry": {"coordinates":[69.64175,40.57018],"type":"Point"}
}