{
  "type": "Feature",
  "properties": {
    "gn:admin1_code":"03",
    "gn:asciiname":"Tuqquzchalak",
    "gn:country_code":"TJ",
    "gn:dem":678,
    "gn:feature_class":"P",
    "gn:feature_code":"PPL",
    "gn:name":"T\u016dqquzchalak",
    "gn:population":0,
    "gn:timezone":"Asia/Dushanbe",
    "iso:country":"TJ",
    "name:und_x_variant":[
        "T\u016dqquzchalak",
        "\u0422\u04ef\u049b\u049b\u0443\u0437\u0447\u0430\u043b\u0430\u043a"
    ],
    "wof:name":"Tuqquzchalak",
    "wof:placetype":"locality"
},
  "geometry": {"coordinates":[69.04921999999999,40.04698],"type":"Point"}
}