{
  "type": "Feature",
  "properties": {
    "gn:admin1_code":"02",
    "gn:asciiname":"Ruyob-Sandara",
    "gn:country_code":"TJ",
    "gn:dem":1533,
    "gn:feature_class":"P",
    "gn:feature_code":"PPL",
    "gn:name":"R\u016dyob-Sandara",
    "gn:population":0,
    "gn:timezone":"Asia/Dushanbe",
    "iso:country":"TJ",
    "name:und_x_variant":[
        "R\u016dyob-Sandara",
        "\u0420\u04ef\u0439\u043e\u0431-\u0421\u0430\u043d\u0434\u0430\u0440\u0430",
        "R\u016diob-Sandora"
    ],
    "wof:name":"Ruyob-Sandara",
    "wof:placetype":"locality"
},
  "geometry": {"coordinates":[70.13157,38.38065],"type":"Point"}
}