{
  "type": "Feature",
  "properties": {
    "gn:admin1_code":"02",
    "gn:asciiname":"Traktor",
    "gn:country_code":"TJ",
    "gn:dem":359,
    "gn:feature_class":"P",
    "gn:feature_code":"PPL",
    "gn:name":"Traktor",
    "gn:population":0,
    "gn:timezone":"Asia/Dushanbe",
    "iso:country":"TJ",
    "name:fra_x_preferred":[
        "Traktor"
    ],
    "name:por_x_preferred":[
        "Traktor"
    ],
    "name:und_x_variant":[
        "\u0422\u0440\u0430\u043a\u0442\u043e\u0440"
    ],
    "wof:name":"Traktor",
    "wof:placetype":"locality"
},
  "geometry": {"coordinates":[68.13579,37.23288],"type":"Point"}
}