{
  "type": "Feature",
  "properties": {
    "gn:admin1_code":"02",
    "gn:asciiname":"Peteul",
    "gn:country_code":"TJ",
    "gn:dem":384,
    "gn:feature_class":"P",
    "gn:feature_code":"PPL",
    "gn:name":"Peteul",
    "gn:population":0,
    "gn:timezone":"Asia/Dushanbe",
    "iso:country":"TJ",
    "wof:name":"Peteul",
    "wof:placetype":"locality"
},
  "geometry": {"coordinates":[68.63329,37.36677],"type":"Point"}
}