{
  "type": "Feature",
  "properties": {
    "gn:admin1_code":"02",
    "gn:asciiname":"Jailma",
    "gn:country_code":"TJ",
    "gn:dem":496,
    "gn:feature_class":"P",
    "gn:feature_code":"PPL",
    "gn:name":"Jailma",
    "gn:population":0,
    "gn:timezone":"Asia/Dushanbe",
    "iso:country":"TJ",
    "name:rus_x_preferred":[
        "Dzhail\u2019ma"
    ],
    "name:tgk_x_preferred":[
        "Jailma"
    ],
    "name:und_x_variant":[
        "\u04b6\u0430\u0438\u043b\u043c\u0430"
    ],
    "wof:name":"Jailma",
    "wof:placetype":"locality"
},
  "geometry": {"coordinates":[68.18966,37.79005],"type":"Point"}
}