{
  "type": "Feature",
  "properties": {
    "gn:admin1_code":"RR",
    "gn:asciiname":"Farishti",
    "gn:country_code":"TJ",
    "gn:dem":997,
    "gn:feature_class":"P",
    "gn:feature_code":"PPL",
    "gn:name":"Farishti",
    "gn:population":0,
    "gn:timezone":"Asia/Dushanbe",
    "iso:country":"TJ",
    "name:und_x_variant":[
        "Firishti",
        "Farishti"
    ],
    "wof:name":"Farishti",
    "wof:placetype":"locality"
},
  "geometry": {"coordinates":[69.00060999999999,38.59553],"type":"Point"}
}