{
  "type": "Feature",
  "properties": {
    "gn:admin1_code":"01",
    "gn:asciiname":"Miyonshahr",
    "gn:country_code":"TJ",
    "gn:dem":3031,
    "gn:feature_class":"P",
    "gn:feature_code":"PPL",
    "gn:name":"Miyonshahr",
    "gn:population":0,
    "gn:timezone":"Asia/Dushanbe",
    "iso:country":"TJ",
    "name:und_x_variant":[
        "Razak",
        "Miyenshar",
        "Mianshar",
        "Miyonshahr",
        "\u041c\u0438\u0451\u043d\u0448\u0430\u04b7\u0440"
    ],
    "wof:name":"Miyonshahr",
    "wof:placetype":"locality"
},
  "geometry": {"coordinates":[72.25106,37.72254],"type":"Point"}
}