{
  "type": "Feature",
  "properties": {
    "gn:admin1_code":"00",
    "gn:asciiname":"Turghuling",
    "gn:country_code":"TJ",
    "gn:dem":1089,
    "gn:feature_class":"P",
    "gn:feature_code":"PPL",
    "gn:name":"Turghuling",
    "gn:population":0,
    "gn:timezone":"Asia/Dushanbe",
    "iso:country":"TJ",
    "name:und_x_variant":[
        "\u0422\u0443\u0440\u0493\u0443\u043b\u0438\u043d\u0433",
        "Turgoling"
    ],
    "wof:name":"Turghuling",
    "wof:placetype":"locality"
},
  "geometry": {"coordinates":[69.56941999999999,38.4827],"type":"Point"}
}