{
  "type": "Feature",
  "properties": {
    "gn:admin1_code":"RR",
    "gn:asciiname":"Khodzhimard",
    "gn:country_code":"TJ",
    "gn:dem":1278,
    "gn:feature_class":"P",
    "gn:feature_code":"PPL",
    "gn:name":"Khodzhimard",
    "gn:population":0,
    "gn:timezone":"Asia/Dushanbe",
    "iso:country":"TJ",
    "wof:name":"Khodzhimard",
    "wof:placetype":"locality"
},
  "geometry": {"coordinates":[69.31667,38.56667],"type":"Point"}
}