{
  "type": "Feature",
  "properties": {
    "gn:admin1_code":"03",
    "gn:asciiname":"Mayshik",
    "gn:country_code":"TJ",
    "gn:dem":393,
    "gn:feature_class":"P",
    "gn:feature_code":"PPL",
    "gn:name":"Mayshik",
    "gn:population":0,
    "gn:timezone":"Asia/Dushanbe",
    "iso:country":"TJ",
    "name:eng_x_preferred":[
        "Mayshik"
    ],
    "name:uzb_x_preferred":[
        "Mayshiq"
    ],
    "wof:name":"Mayshik",
    "wof:placetype":"locality"
},
  "geometry": {"coordinates":[70.76024,40.71243],"type":"Point"}
}