{
  "type": "Feature",
  "properties": {
    "gn:admin1_code":"02",
    "gn:asciiname":"Bobokhonshaid",
    "gn:country_code":"TJ",
    "gn:dem":857,
    "gn:feature_class":"P",
    "gn:feature_code":"PPL",
    "gn:name":"Bobokhonshaid",
    "gn:population":0,
    "gn:timezone":"Asia/Dushanbe",
    "iso:country":"TJ",
    "wof:name":"Bobokhonshaid",
    "wof:placetype":"locality"
},
  "geometry": {"coordinates":[69.65692,38.2282],"type":"Point"}
}