{
  "type": "Feature",
  "properties": {
    "gn:admin1_code":"03",
    "gn:asciiname":"Dzhumabazar",
    "gn:country_code":"TJ",
    "gn:dem":336,
    "gn:feature_class":"P",
    "gn:feature_code":"PPL",
    "gn:name":"Dzhumabazar",
    "gn:population":0,
    "gn:timezone":"Asia/Dushanbe",
    "iso:country":"TJ",
    "name:fas_x_preferred":[
        "\u062c\u0645\u0639\u0647 \u0628\u0627\u0632\u0627\u0631"
    ],
    "name:msa_x_preferred":[
        "Dzhumabazar"
    ],
    "wof:name":"Dzhumabazar",
    "wof:placetype":"locality"
},
  "geometry": {"coordinates":[69.34999999999999,40.31667],"type":"Point"}
}