{
  "type": "Feature",
  "properties": {
    "gn:admin1_code":"02",
    "gn:asciiname":"Mash'al",
    "gn:country_code":"TJ",
    "gn:dem":478,
    "gn:feature_class":"P",
    "gn:feature_code":"PPL",
    "gn:name":"Mash\u2019al",
    "gn:population":0,
    "gn:timezone":"Asia/Dushanbe",
    "iso:country":"TJ",
    "name:tgk_x_preferred":[
        "Mashal"
    ],
    "name:tgk_x_variant":[
        "Mash\u2019al"
    ],
    "name:und_x_variant":[
        "\u041c\u0430\u0448\u044a\u0430\u043b"
    ],
    "wof:name":"Mash'al",
    "wof:placetype":"locality"
},
  "geometry": {"coordinates":[69.04510999999999,37.73889000000001],"type":"Point"}
}