{
  "type": "Feature",
  "properties": {
    "gn:admin1_code":"03",
    "gn:asciiname":"Oksukon",
    "gn:country_code":"TJ",
    "gn:dem":460,
    "gn:feature_class":"P",
    "gn:feature_code":"PPL",
    "gn:name":"Oksukon",
    "gn:population":0,
    "gn:timezone":"Asia/Dushanbe",
    "iso:country":"TJ",
    "name:und_x_variant":[
        "Kurort Oksukon",
        "Oksukon"
    ],
    "wof:name":"Oksukon",
    "wof:placetype":"locality"
},
  "geometry": {"coordinates":[70.40000000000001,40.53333],"type":"Point"}
}