{
  "type": "Feature",
  "properties": {
    "gn:admin1_code":"RR",
    "gn:asciiname":"Kalacha",
    "gn:country_code":"TJ",
    "gn:dem":3013,
    "gn:feature_class":"P",
    "gn:feature_code":"PPL",
    "gn:name":"Kalacha",
    "gn:population":0,
    "gn:timezone":"Asia/Dushanbe",
    "iso:country":"TJ",
    "wof:name":"Kalacha",
    "wof:placetype":"locality"
},
  "geometry": {"coordinates":[69.93333,39.28333],"type":"Point"}
}