{
  "type": "Feature",
  "properties": {
    "gn:admin1_code":"02",
    "gn:asciiname":"Dashti-Raz",
    "gn:country_code":"TJ",
    "gn:dem":1200,
    "gn:feature_class":"P",
    "gn:feature_code":"PPL",
    "gn:name":"Dashti-Raz",
    "gn:population":0,
    "gn:timezone":"Asia/Dushanbe",
    "iso:country":"TJ",
    "wof:name":"Dashti-Raz",
    "wof:placetype":"locality"
},
  "geometry": {"coordinates":[69.40934,38.30803],"type":"Point"}
}