{
  "type": "Feature",
  "properties": {
    "gn:admin1_code":"01",
    "gn:asciiname":"Buved",
    "gn:country_code":"TJ",
    "gn:dem":2139,
    "gn:feature_class":"P",
    "gn:feature_code":"PPL",
    "gn:name":"Buved",
    "gn:population":0,
    "gn:timezone":"Asia/Dushanbe",
    "iso:country":"TJ",
    "name:tgk_x_preferred":[
        "Buved"
    ],
    "name:tgk_x_variant":[
        "\u0411\u0443\u0432\u0435\u0434"
    ],
    "name:und_x_variant":[
        "Porshnev"
    ],
    "wof:name":"Buved",
    "wof:placetype":"locality"
},
  "geometry": {"coordinates":[71.51560000000001,37.58103],"type":"Point"}
}