{
  "type": "Feature",
  "properties": {
    "gn:admin1_code":"03",
    "gn:asciiname":"Madaniyat",
    "gn:country_code":"TJ",
    "gn:dem":864,
    "gn:feature_class":"P",
    "gn:feature_code":"PPL",
    "gn:name":"Madaniyat",
    "gn:population":0,
    "gn:timezone":"Asia/Dushanbe",
    "iso:country":"TJ",
    "name:und_x_variant":[
        "\u041c\u0430\u0434\u0430\u043d\u0438\u044f\u0442"
    ],
    "wof:name":"Madaniyat",
    "wof:placetype":"locality"
},
  "geometry": {"coordinates":[69.0326,39.96676],"type":"Point"}
}