{
  "type": "Feature",
  "properties": {
    "gn:asciiname":"Lahhuty",
    "gn:country_code":"TJ",
    "gn:dem":1247,
    "gn:feature_class":"P",
    "gn:feature_code":"PPL",
    "gn:name":"Lahhuty",
    "gn:population":0,
    "gn:timezone":"Asia/Dushanbe",
    "iso:country":"TJ",
    "wof:name":"Lahhuty",
    "wof:placetype":"locality"
},
  "geometry": {"coordinates":[69.89842,38.29533],"type":"Point"}
}