{
  "type": "Feature",
  "properties": {
    "gn:admin1_code":"02",
    "gn:asciiname":"Chiriq",
    "gn:country_code":"TJ",
    "gn:dem":374,
    "gn:feature_class":"P",
    "gn:feature_code":"PPL",
    "gn:name":"Chiriq",
    "gn:population":0,
    "gn:timezone":"Asia/Dushanbe",
    "iso:country":"TJ",
    "name:tgk_x_preferred":[
        "Chirik"
    ],
    "name:und_x_variant":[
        "\u0427\u0438\u0440\u0438\u049b"
    ],
    "wof:name":"Chiriq",
    "wof:placetype":"locality"
},
  "geometry": {"coordinates":[68.1994,37.22024],"type":"Point"}
}