{
  "type": "Feature",
  "properties": {
    "iso:country":"TJ",
    "ne:ADM0CAP":0.0,
    "ne:ADM0NAME":"Tajikistan",
    "ne:ADM0_A3":"TJK",
    "ne:ADM1NAME":"Khatlon",
    "ne:ADMIN1_COD":0,
    "ne:CAPALT":0,
    "ne:CHANGED":0,
    "ne:CHECKME":0,
    "ne:COMPARE":0,
    "ne:DIFFASCII":0,
    "ne:ELEVATION":0.0,
    "ne:FEATURECLA":"Populated place",
    "ne:GEONAMEID":-1,
    "ne:GEONAMESNO":"No GeoNames match due to small population, not in GeoNames, or poor NEV placement.",
    "ne:GN_POP":0,
    "ne:GTOPO30":0.0,
    "ne:ISO_A2":"TJ",
    "ne:LABELRANK":8,
    "ne:LATITUDE":37.979399,
    "ne:LONGITUDE":68.688975,
    "ne:LS_MATCH":1,
    "ne:LS_NAME":"Kuybyshevskiy",
    "ne:MAX_AREAKM":11.0,
    "ne:MAX_AREAMI":4.0,
    "ne:MAX_BBXMAX":68.741667,
    "ne:MAX_BBXMIN":68.675,
    "ne:MAX_BBYMAX":38.008333,
    "ne:MAX_BBYMIN":37.966667,
    "ne:MAX_NATSCA":20.0,
    "ne:MAX_PERKM":25.0,
    "ne:MAX_PERMI":16.0,
    "ne:MAX_POP10":8925,
    "ne:MAX_POP20":8925,
    "ne:MAX_POP300":0,
    "ne:MAX_POP310":0,
    "ne:MAX_POP50":0,
    "ne:MEAN_BBXC":68.706771,
    "ne:MEAN_BBYC":37.984896,
    "ne:MEGACITY":0,
    "ne:MIN_AREAKM":11.0,
    "ne:MIN_AREAMI":4.0,
    "ne:MIN_BBXMAX":68.741667,
    "ne:MIN_BBXMIN":68.675,
    "ne:MIN_BBYMAX":38.008333,
    "ne:MIN_BBYMIN":37.966667,
    "ne:MIN_PERKM":25.0,
    "ne:MIN_PERMI":16.0,
    "ne:NAME":"Kuybyshevskiy",
    "ne:NAMEASCII":"Kuybyshevskiy",
    "ne:NAMEDIFF":0,
    "ne:NATSCALE":20,
    "ne:POP1950":0,
    "ne:POP1955":0,
    "ne:POP1960":0,
    "ne:POP1965":0,
    "ne:POP1970":0,
    "ne:POP1975":0,
    "ne:POP1980":0,
    "ne:POP1985":0,
    "ne:POP1990":0,
    "ne:POP1995":0,
    "ne:POP2000":0,
    "ne:POP2005":0,
    "ne:POP2010":0,
    "ne:POP2015":0,
    "ne:POP2020":0,
    "ne:POP2025":0,
    "ne:POP2050":0,
    "ne:POP_MAX":8925,
    "ne:POP_MIN":8925,
    "ne:POP_OTHER":3507,
    "ne:RANK_MAX":5,
    "ne:RANK_MIN":5,
    "ne:SCALERANK":7,
    "ne:SOV0NAME":"Tajikistan",
    "ne:SOV_A3":"TJK",
    "ne:UN_FID":0,
    "ne:UN_LAT":0.0,
    "ne:UN_LONG":0.0,
    "ne:WORLDCITY":0,
    "ne:min_zoom":6.7,
    "wof:name":"Kuybyshevskiy",
    "wof:placetype":"locality"
},
  "geometry": {"coordinates":[68.68897497444601,37.97939882308503],"type":"Point"}
}