{
  "type": "Feature",
  "properties": {
    "gn:admin1_code":"RR",
    "gn:asciiname":"Abdu",
    "gn:country_code":"TJ",
    "gn:dem":1111,
    "gn:feature_class":"P",
    "gn:feature_code":"PPL",
    "gn:name":"Abdu",
    "gn:population":0,
    "gn:timezone":"Asia/Dushanbe",
    "iso:country":"TJ",
    "wof:name":"Abdu",
    "wof:placetype":"locality"
},
  "geometry": {"coordinates":[68.36865,38.71545],"type":"Point"}
}