{
  "type": "Feature",
  "properties": {
    "gn:admin1_code":"02",
    "gn:asciiname":"Gardana",
    "gn:country_code":"TJ",
    "gn:dem":1294,
    "gn:feature_class":"P",
    "gn:feature_code":"PPL",
    "gn:name":"Gardana",
    "gn:population":0,
    "gn:timezone":"Asia/Dushanbe",
    "iso:country":"TJ",
    "wof:name":"Gardana",
    "wof:placetype":"locality"
},
  "geometry": {"coordinates":[69.16667,38.16667],"type":"Point"}
}