{
  "type": "Feature",
  "properties": {
    "gn:admin1_code":"01",
    "gn:asciiname":"Shirgin",
    "gn:country_code":"TJ",
    "gn:dem":2896,
    "gn:feature_class":"P",
    "gn:feature_code":"PPL",
    "gn:name":"Shirgin",
    "gn:population":0,
    "gn:timezone":"Asia/Dushanbe",
    "iso:country":"TJ",
    "name:und_x_variant":[
        "Shargin",
        "Shirgin",
        "\u0428\u0438\u0440\u0433\u0438\u043d"
    ],
    "wof:name":"Shirgin",
    "wof:placetype":"locality"
},
  "geometry": {"coordinates":[72.52119,37.00901],"type":"Point"}
}