{
  "type": "Feature",
  "properties": {
    "gn:admin1_code":"RR",
    "gn:asciiname":"Gulkhori",
    "gn:country_code":"TJ",
    "gn:dem":1903,
    "gn:feature_class":"P",
    "gn:feature_code":"PPL",
    "gn:name":"Gulkhori",
    "gn:population":0,
    "gn:timezone":"Asia/Dushanbe",
    "iso:country":"TJ",
    "name:und_x_variant":[
        "Gul\u2019khari",
        "Gulkhori"
    ],
    "wof:name":"Gulkhori",
    "wof:placetype":"locality"
},
  "geometry": {"coordinates":[69.51916999999999,38.66306],"type":"Point"}
}