{
  "type": "Feature",
  "properties": {
    "gn:admin1_code":"02",
    "gn:asciiname":"Jal Jal",
    "gn:country_code":"TJ",
    "gn:dem":658,
    "gn:feature_class":"P",
    "gn:feature_code":"PPL",
    "gn:name":"Jal Jal",
    "gn:population":0,
    "gn:timezone":"Asia/Dushanbe",
    "iso:country":"TJ",
    "name:und_x_variant":[
        "\u04b6\u0430\u043b \u04b6\u0430\u043b",
        "Chalchal"
    ],
    "wof:name":"Jal Jal",
    "wof:placetype":"locality"
},
  "geometry": {"coordinates":[69.20756999999999,38.37615],"type":"Point"}
}