{
  "type": "Feature",
  "properties": {
    "gn:admin1_code":"02",
    "gn:asciiname":"Ustotoymas",
    "gn:country_code":"TJ",
    "gn:dem":672,
    "gn:feature_class":"P",
    "gn:feature_code":"PPL",
    "gn:name":"Ustotoymas",
    "gn:population":0,
    "gn:timezone":"Asia/Dushanbe",
    "iso:country":"TJ",
    "name:und_x_variant":[
        "\u0423\u0441\u0442\u043e\u0442\u043e\u0439\u043c\u0430\u0441"
    ],
    "wof:name":"Ustotoymas",
    "wof:placetype":"locality"
},
  "geometry": {"coordinates":[68.92918,37.90823],"type":"Point"}
}