{
  "type": "Feature",
  "properties": {
    "gn:admin1_code":"RR",
    "gn:asciiname":"Kulibedak",
    "gn:country_code":"TJ",
    "gn:dem":1160,
    "gn:feature_class":"P",
    "gn:feature_code":"PPL",
    "gn:name":"Kulibedak",
    "gn:population":0,
    "gn:timezone":"Asia/Dushanbe",
    "iso:country":"TJ",
    "wof:name":"Kulibedak",
    "wof:placetype":"locality"
},
  "geometry": {"coordinates":[68.72431999999999,38.65764],"type":"Point"}
}