{
  "type": "Feature",
  "properties": {
    "gn:admin1_code":"01",
    "gn:asciiname":"Lyangar",
    "gn:country_code":"TJ",
    "gn:dem":2152,
    "gn:feature_class":"P",
    "gn:feature_code":"PPL",
    "gn:name":"Lyangar",
    "gn:population":0,
    "gn:timezone":"Asia/Dushanbe",
    "iso:country":"TJ",
    "wof:name":"Lyangar",
    "wof:placetype":"locality"
},
  "geometry": {"coordinates":[71.83246,38.58672],"type":"Point"}
}