{
  "type": "Feature",
  "properties": {
    "gn:admin1_code":"02",
    "gn:asciiname":"Uchastok Imeni Krupskoy",
    "gn:country_code":"TJ",
    "gn:dem":393,
    "gn:feature_class":"P",
    "gn:feature_code":"PPL",
    "gn:name":"Uchastok Imeni Krupskoy",
    "gn:population":0,
    "gn:timezone":"Asia/Dushanbe",
    "iso:country":"TJ",
    "wof:name":"Uchastok Imeni Krupskoy",
    "wof:placetype":"locality"
},
  "geometry": {"coordinates":[68.62815000000001,37.45364],"type":"Point"}
}