{
  "type": "Feature",
  "properties": {
    "gn:admin1_code":"00",
    "gn:asciiname":"Kol-Bulak",
    "gn:country_code":"TJ",
    "gn:dem":1353,
    "gn:feature_class":"P",
    "gn:feature_code":"PPL",
    "gn:name":"Kol-Bulak",
    "gn:population":0,
    "gn:timezone":"Asia/Dushanbe",
    "iso:country":"TJ",
    "wof:name":"Kol-Bulak",
    "wof:placetype":"locality"
},
  "geometry": {"coordinates":[69.15000000000001,37.96667],"type":"Point"}
}