{
  "type": "Feature",
  "properties": {
    "gn:admin1_code":"02",
    "gn:asciiname":"Namuna",
    "gn:country_code":"TJ",
    "gn:dem":345,
    "gn:feature_class":"P",
    "gn:feature_code":"PPL",
    "gn:name":"Namuna",
    "gn:population":0,
    "gn:timezone":"Asia/Dushanbe",
    "iso:country":"TJ",
    "wof:name":"Namuna",
    "wof:placetype":"locality"
},
  "geometry": {"coordinates":[68.51546,37.43133],"type":"Point"}
}