{
  "type": "Feature",
  "properties": {
    "gn:admin1_code":"RR",
    "gn:asciiname":"Torbuloq",
    "gn:country_code":"TJ",
    "gn:dem":862,
    "gn:feature_class":"P",
    "gn:feature_code":"PPL",
    "gn:name":"Torbuloq",
    "gn:population":0,
    "gn:timezone":"Asia/Dushanbe",
    "iso:country":"TJ",
    "name:und_x_variant":[
        "Torbulok",
        "Torbuloq"
    ],
    "wof:name":"Torbuloq",
    "wof:placetype":"locality"
},
  "geometry": {"coordinates":[69.02715999999999,38.52137000000001],"type":"Point"}
}