{
  "type": "Feature",
  "properties": {
    "gn:admin1_code":"02",
    "gn:asciiname":"Rohi Lenin",
    "gn:country_code":"TJ",
    "gn:dem":413,
    "gn:feature_class":"P",
    "gn:feature_code":"PPL",
    "gn:name":"Rohi Lenin",
    "gn:population":0,
    "gn:timezone":"Asia/Dushanbe",
    "iso:country":"TJ",
    "name:tgk_x_preferred":[
        "Rohi Lenin"
    ],
    "name:und_x_variant":[
        "Rokhi-Lenin",
        "\u0420\u043e\u04b3\u0438 \u041b\u0435\u043d\u0438\u043d"
    ],
    "wof:name":"Rohi Lenin",
    "wof:placetype":"locality"
},
  "geometry": {"coordinates":[68.66575,37.50753],"type":"Point"}
}