{
  "type": "Feature",
  "properties": {
    "gn:admin1_code":"01",
    "gn:asciiname":"Patkunob",
    "gn:country_code":"TJ",
    "gn:dem":1208,
    "gn:feature_class":"P",
    "gn:feature_code":"PPL",
    "gn:name":"Patkunob",
    "gn:population":0,
    "gn:timezone":"Asia/Dushanbe",
    "iso:country":"TJ",
    "name:und_x_variant":[
        "Padkinov",
        "Patkunob",
        "\u041f\u0430\u0442\u043a\u0443\u043d\u043e\u0431"
    ],
    "wof:name":"Patkunob",
    "wof:placetype":"locality"
},
  "geometry": {"coordinates":[70.67267,38.39554],"type":"Point"}
}