{
  "type": "Feature",
  "properties": {
    "gn:admin1_code":"02",
    "gn:asciiname":"Khavzako",
    "gn:country_code":"TJ",
    "gn:dem":443,
    "gn:feature_class":"P",
    "gn:feature_code":"PPL",
    "gn:name":"Khavzako",
    "gn:population":0,
    "gn:timezone":"Asia/Dushanbe",
    "iso:country":"TJ",
    "name:tgk_x_preferred":[
        "Khavzak\u00b7ho"
    ],
    "name:tgk_x_variant":[
        "\u0425\u0430\u0432\u0437\u0430\u043a\u04b3\u043e"
    ],
    "wof:name":"Khavzako",
    "wof:placetype":"locality"
},
  "geometry": {"coordinates":[69.35875,37.54313],"type":"Point"}
}