{
  "type": "Feature",
  "properties": {
    "gn:admin1_code":"RR",
    "gn:asciiname":"Kisatorosh",
    "gn:country_code":"TJ",
    "gn:dem":1308,
    "gn:feature_class":"P",
    "gn:feature_code":"PPL",
    "gn:name":"Kisatorosh",
    "gn:population":0,
    "gn:timezone":"Asia/Dushanbe",
    "iso:country":"TJ",
    "wof:name":"Kisatorosh",
    "wof:placetype":"locality"
},
  "geometry": {"coordinates":[68.66774000000001,38.68327],"type":"Point"}
}