{
  "type": "Feature",
  "properties": {
    "gn:admin1_code":"RR",
    "gn:asciiname":"Karatikon",
    "gn:country_code":"TJ",
    "gn:dem":1522,
    "gn:feature_class":"P",
    "gn:feature_code":"PPL",
    "gn:name":"Karatikon",
    "gn:population":0,
    "gn:timezone":"Asia/Dushanbe",
    "iso:country":"TJ",
    "wof:name":"Karatikon",
    "wof:placetype":"locality"
},
  "geometry": {"coordinates":[68.38333,38.73333],"type":"Point"}
}