{
  "type": "Feature",
  "properties": {
    "gn:admin1_code":"02",
    "gn:asciiname":"Somonchi",
    "gn:country_code":"TJ",
    "gn:dem":455,
    "gn:feature_class":"P",
    "gn:feature_code":"PPL",
    "gn:name":"Somonch\u00ed",
    "gn:population":0,
    "gn:timezone":"Asia/Dushanbe",
    "iso:country":"TJ",
    "name:tgk_x_preferred":[
        "Samonch\u00ed"
    ],
    "name:und_x_variant":[
        "Samanchi",
        "Somonch\u00ed",
        "\u0421\u043e\u043c\u043e\u043d\u0447\u04e3"
    ],
    "wof:name":"Somonchi",
    "wof:placetype":"locality"
},
  "geometry": {"coordinates":[69.41455000000001,37.65191],"type":"Point"}
}