{
  "type": "Feature",
  "properties": {
    "gn:admin1_code":"01",
    "gn:asciiname":"Zugvand",
    "gn:country_code":"TJ",
    "gn:dem":2792,
    "gn:feature_class":"P",
    "gn:feature_code":"PPL",
    "gn:name":"Zugvand",
    "gn:population":0,
    "gn:timezone":"Asia/Dushanbe",
    "iso:country":"TJ",
    "name:und_x_variant":[
        "\u042d\u0443\u0433\u0432\u0430\u043d\u0434"
    ],
    "wof:name":"Zugvand",
    "wof:placetype":"locality"
},
  "geometry": {"coordinates":[72.59002,37.01869],"type":"Point"}
}