{
  "type": "Feature",
  "properties": {
    "iso:country":"TJ",
    "name:und_x_variant":[
        "Oltintopkan"
    ],
    "qs:gn_country":"TJ",
    "qs:gn_fcode":"PPL",
    "qs:gn_pop":4823,
    "qs:name":"Altyn-Topkan",
    "qs:name_adm0":"Tajikistan",
    "qs:name_adm1":"Leninobod",
    "qs:photos":0,
    "qs:photos_1k":0,
    "qs:photos_9k":0,
    "qs:photos_9r":0,
    "qs:photos_all":0,
    "qs:photos_sr":0,
    "qs:placetype":"Town",
    "qs:pop_sr":"4",
    "qs:woe_adm0":23424961,
    "wof:name":"Altyn-Topkan",
    "wof:placetype":"locality",
    "wof:population":4823
},
  "geometry": {"coordinates":[69.59811000000001,40.65425],"type":"Point"}
}