{
  "type": "Feature",
  "properties": {
    "gn:admin1_code":"03",
    "gn:asciiname":"Dehavo",
    "gn:country_code":"TJ",
    "gn:dem":2567,
    "gn:feature_class":"P",
    "gn:feature_code":"PPL",
    "gn:name":"Dehavo",
    "gn:population":0,
    "gn:timezone":"Asia/Dushanbe",
    "iso:country":"TJ",
    "name:und_x_variant":[
        "\u0414\u0435\u04b3\u0430\u0432\u043e"
    ],
    "wof:name":"Dehavo",
    "wof:placetype":"locality"
},
  "geometry": {"coordinates":[70.19530999999999,39.44747],"type":"Point"}
}