{
  "type": "Feature",
  "properties": {
    "gn:admin1_code":"02",
    "gn:asciiname":"Dahana",
    "gn:country_code":"TJ",
    "gn:dem":714,
    "gn:feature_class":"P",
    "gn:feature_code":"PPL",
    "gn:name":"Dahana",
    "gn:population":0,
    "gn:timezone":"Asia/Dushanbe",
    "iso:country":"TJ",
    "name:ceb_x_preferred":[
        "Dahana"
    ],
    "name:ind_x_preferred":[
        "Dahana"
    ],
    "name:jav_x_preferred":[
        "Dahana"
    ],
    "name:nld_x_preferred":[
        "Dahana"
    ],
    "name:swe_x_preferred":[
        "Dahana"
    ],
    "name:tgk_x_preferred":[
        "\u0414\u0430\u04b3\u0430\u043d\u0430"
    ],
    "name:und_x_variant":[
        "Dagana",
        "Dakhana"
    ],
    "wof:name":"Dahana",
    "wof:placetype":"locality"
},
  "geometry": {"coordinates":[68.9859,38.33641],"type":"Point"}
}