{
  "type": "Feature",
  "properties": {
    "gn:admin1_code":"03",
    "gn:asciiname":"Sirdaryo",
    "gn:country_code":"TJ",
    "gn:dem":396,
    "gn:feature_class":"P",
    "gn:feature_code":"PPL",
    "gn:name":"Sirdaryo",
    "gn:population":0,
    "gn:timezone":"Asia/Dushanbe",
    "iso:country":"TJ",
    "name:ceb_x_preferred":[
        "Sirdaryo"
    ],
    "name:fas_x_preferred":[
        "\u0633\u06cc\u0631\u062f\u0627\u0631\u06cc\u0648"
    ],
    "name:fra_x_preferred":[
        "Sirdaryo"
    ],
    "name:hsb_x_preferred":[
        "Sirdaryo"
    ],
    "name:ita_x_preferred":[
        "Sirdaryo"
    ],
    "name:jpn_x_preferred":[
        "\u30b7\u30eb\u30c0\u30ea\u30e4"
    ],
    "name:kik_x_preferred":[
        "Sirdaryo"
    ],
    "name:nld_x_preferred":[
        "Sirdarjo"
    ],
    "name:nor_x_preferred":[
        "Sirdaryo"
    ],
    "name:pol_x_preferred":[
        "Syrdaria"
    ],
    "name:rus_x_preferred":[
        "\u0421\u044b\u0440\u0434\u0430\u0440\u044c\u044f"
    ],
    "name:spa_x_preferred":[
        "Sirdaryo"
    ],
    "name:tat_x_preferred":[
        "\u0421\u044b\u0440\u0434\u04d9\u0440\u044c\u044f"
    ],
    "name:tur_x_preferred":[
        "Sirderya"
    ],
    "name:und_x_variant":[
        "Syrdar\u2019inskiy",
        "\u0421\u0438\u0440\u0434\u0430\u0440\u0451"
    ],
    "name:urd_x_preferred":[
        "\u0633\u06cc\u0631\u062f\u0631\u06cc\u0627"
    ],
    "name:uzb_x_preferred":[
        "Sirdaryo"
    ],
    "wof:name":"Sirdaryo",
    "wof:placetype":"locality"
},
  "geometry": {"coordinates":[69.73044,40.25238],"type":"Point"}
}