{
  "type": "Feature",
  "properties": {
    "gn:admin1_code":"03",
    "gn:asciiname":"Sirdaryo",
    "gn:country_code":"TJ",
    "gn:dem":396,
    "gn:feature_class":"P",
    "gn:feature_code":"PPL",
    "gn:name":"Sirdaryo",
    "gn:population":0,
    "gn:timezone":"Asia/Dushanbe",
    "iso:country":"TJ",
    "name:und_x_variant":[
        "Syrdar\u2019inskiy",
        "Sirdaryo",
        "\u0421\u0438\u0440\u0434\u0430\u0440\u0451"
    ],
    "wof:name":"Sirdaryo",
    "wof:placetype":"locality"
},
  "geometry": {"coordinates":[69.73044,40.25238],"type":"Point"}
}