{
  "type": "Feature",
  "properties": {
    "gn:admin1_code":"01",
    "gn:asciiname":"Savsipushdasht",
    "gn:country_code":"TJ",
    "gn:dem":2225,
    "gn:feature_class":"P",
    "gn:feature_code":"PPL",
    "gn:name":"Savsipushdasht",
    "gn:population":0,
    "gn:timezone":"Asia/Dushanbe",
    "iso:country":"TJ",
    "wof:name":"Savsipushdasht",
    "wof:placetype":"locality"
},
  "geometry": {"coordinates":[71.86125,38.03716],"type":"Point"}
}