{
  "type": "Feature",
  "properties": {
    "gn:admin1_code":"01",
    "gn:asciiname":"Ghumayak",
    "gn:country_code":"TJ",
    "gn:dem":1788,
    "gn:feature_class":"P",
    "gn:feature_code":"PPL",
    "gn:name":"Ghumayak",
    "gn:population":0,
    "gn:timezone":"Asia/Dushanbe",
    "iso:country":"TJ",
    "name:und_x_variant":[
        "\u0492\u0443\u043c\u0430\u044f\u043a",
        "Gumayak"
    ],
    "wof:name":"Ghumayak",
    "wof:placetype":"locality"
},
  "geometry": {"coordinates":[71.51485,38.39534],"type":"Point"}
}