{
  "type": "Feature",
  "properties": {
    "gn:admin1_code":"01",
    "gn:asciiname":"Dashtak",
    "gn:country_code":"TJ",
    "gn:dem":2571,
    "gn:feature_class":"P",
    "gn:feature_code":"PPL",
    "gn:name":"Dashtak",
    "gn:population":0,
    "gn:timezone":"Asia/Dushanbe",
    "iso:country":"TJ",
    "name:ceb_x_preferred":[
        "Dashtak"
    ],
    "name:swe_x_preferred":[
        "Dashtak"
    ],
    "name:tgk_x_preferred":[
        "Dashtak"
    ],
    "name:tgk_x_variant":[
        "\u0414\u0430\u0448\u0442\u0430\u043a"
    ],
    "name:und_x_variant":[
        "Dashta"
    ],
    "wof:name":"Dashtak",
    "wof:placetype":"locality"
},
  "geometry": {"coordinates":[71.72317,37.32782],"type":"Point"}
}