{
  "type": "Feature",
  "properties": {
    "gn:admin1_code":"RR",
    "gn:asciiname":"Chuqurak",
    "gn:country_code":"TJ",
    "gn:dem":1424,
    "gn:feature_class":"P",
    "gn:feature_code":"PPL",
    "gn:name":"Chuqurak",
    "gn:population":0,
    "gn:timezone":"Asia/Dushanbe",
    "iso:country":"TJ",
    "name:und_x_variant":[
        "Chukurak",
        "Chuqurak"
    ],
    "wof:name":"Chuqurak",
    "wof:placetype":"locality"
},
  "geometry": {"coordinates":[69.37654999999999,38.53462],"type":"Point"}
}