{
  "type": "Feature",
  "properties": {
    "gn:admin1_code":"03",
    "gn:asciiname":"Qizilqishloq",
    "gn:country_code":"TJ",
    "gn:dem":333,
    "gn:feature_class":"P",
    "gn:feature_code":"PPL",
    "gn:name":"Qizilqishloq",
    "gn:population":0,
    "gn:timezone":"Asia/Dushanbe",
    "iso:country":"TJ",
    "name:und_x_variant":[
        "\u049a\u0438\u0437\u0438\u043b\u049b\u0438\u0448\u043b\u043e\u049b"
    ],
    "wof:name":"Qizilqishloq",
    "wof:placetype":"locality"
},
  "geometry": {"coordinates":[69.65683,40.29605],"type":"Point"}
}