{
  "type": "Feature",
  "properties": {
    "gn:admin1_code":"03",
    "gn:asciiname":"Dehisor",
    "gn:country_code":"TJ",
    "gn:dem":2592,
    "gn:feature_class":"P",
    "gn:feature_code":"PPL",
    "gn:name":"Dehisor",
    "gn:population":0,
    "gn:timezone":"Asia/Dushanbe",
    "iso:country":"TJ",
    "name:fas_x_preferred":[
        "\u062f\u06cc\u062e\u06cc\u0633\u0648\u0631"
    ],
    "name:msa_x_preferred":[
        "Dikhisor"
    ],
    "name:und_x_variant":[
        "Dikhesar",
        "Dikhasar",
        "Dikhisor",
        "Dehisor",
        "\u0414\u0435\u04b3\u0438\u0441\u043e\u0440"
    ],
    "wof:name":"Dehisor",
    "wof:placetype":"locality"
},
  "geometry": {"coordinates":[70.2226,39.44282000000001],"type":"Point"}
}