{
  "type": "Feature",
  "properties": {
    "gn:admin1_code":"02",
    "gn:asciiname":"Devdor",
    "gn:country_code":"TJ",
    "gn:dem":1897,
    "gn:feature_class":"P",
    "gn:feature_code":"PPL",
    "gn:name":"Devdor",
    "gn:population":0,
    "gn:timezone":"Asia/Dushanbe",
    "iso:country":"TJ",
    "name:tgk_x_preferred":[
        "Devdor"
    ],
    "name:und_x_variant":[
        "Dovdorbolo",
        "Divdar-Bole",
        "Divdor-Bolo"
    ],
    "wof:name":"Devdor",
    "wof:placetype":"locality"
},
  "geometry": {"coordinates":[69.97858000000001,37.8026],"type":"Point"}
}