{
  "type": "Feature",
  "properties": {
    "gn:admin1_code":"03",
    "gn:asciiname":"Tegirmonteppa",
    "gn:country_code":"TJ",
    "gn:dem":1202,
    "gn:feature_class":"P",
    "gn:feature_code":"PPL",
    "gn:name":"Tegirmonteppa",
    "gn:population":0,
    "gn:timezone":"Asia/Dushanbe",
    "iso:country":"TJ",
    "name:und_x_variant":[
        "\u041f\u0435\u0433\u0438\u0440\u043c\u043e\u043d\u0442\u0435\u043f\u043f\u0430"
    ],
    "wof:name":"Tegirmonteppa",
    "wof:placetype":"locality"
},
  "geometry": {"coordinates":[67.51308,39.43972],"type":"Point"}
}