{
  "type": "Feature",
  "properties": {
    "gn:admin1_code":"02",
    "gn:asciiname":"Khayrkoron",
    "gn:country_code":"TJ",
    "gn:dem":2119,
    "gn:feature_class":"P",
    "gn:feature_code":"PPLF",
    "gn:name":"Khayrkoron",
    "gn:population":0,
    "gn:timezone":"Asia/Dushanbe",
    "iso:country":"TJ",
    "name:tgk_x_preferred":[
        "Khayrkoron"
    ],
    "name:und_x_variant":[
        "Kharkaron",
        "\u0425\u0430\u0439\u0440\u043a\u043e\u0440\u043e\u043d"
    ],
    "wof:name":"Khayrkoron",
    "wof:placetype":"locality"
},
  "geometry": {"coordinates":[70.05873000000001,37.85548],"type":"Point"}
}