{
  "type": "Feature",
  "properties": {
    "gn:admin1_code":"RR",
    "gn:asciiname":"Yangiabad",
    "gn:country_code":"TJ",
    "gn:dem":818,
    "gn:feature_class":"P",
    "gn:feature_code":"PPL",
    "gn:name":"Yangiabad",
    "gn:population":0,
    "gn:timezone":"Asia/Dushanbe",
    "iso:country":"TJ",
    "name:ceb_x_preferred":[
        "Yangiobod"
    ],
    "name:fas_x_preferred":[
        "\u06cc\u0627\u0646\u06af\u06cc\u200c\u0622\u0628\u0627\u062f"
    ],
    "name:hsb_x_preferred":[
        "Yangiobod"
    ],
    "name:kik_x_preferred":[
        "Yangiabad"
    ],
    "name:pol_x_preferred":[
        "Yangiobod"
    ],
    "name:rus_x_preferred":[
        "\u042f\u043d\u0433\u0438\u0430\u0431\u0430\u0434"
    ],
    "name:spa_x_preferred":[
        "Yangiabod"
    ],
    "name:tat_x_preferred":[
        "\u042f\u04a3\u044b\u0430\u0431\u0430\u0434"
    ],
    "name:tur_x_preferred":[
        "Yangiabad"
    ],
    "name:urd_x_preferred":[
        "\u06cc\u0626\u0646\u06af\u06cc \u0622\u0628\u0627\u062f"
    ],
    "name:uzb_x_preferred":[
        "Yangiobod"
    ],
    "wof:name":"Yangiabad",
    "wof:placetype":"locality"
},
  "geometry": {"coordinates":[68.52556,38.53158],"type":"Point"}
}