{
  "type": "Feature",
  "properties": {
    "gn:admin1_code":"RR",
    "gn:asciiname":"Yangiabad",
    "gn:country_code":"TJ",
    "gn:dem":818,
    "gn:feature_class":"P",
    "gn:feature_code":"PPL",
    "gn:name":"Yangiabad",
    "gn:population":0,
    "gn:timezone":"Asia/Dushanbe",
    "iso:country":"TJ",
    "wof:name":"Yangiabad",
    "wof:placetype":"locality"
},
  "geometry": {"coordinates":[68.52556,38.53158],"type":"Point"}
}