{
  "type": "Feature",
  "properties": {
    "gn:admin1_code":"03",
    "gn:asciiname":"Unji",
    "gn:country_code":"TJ",
    "gn:dem":345,
    "gn:feature_class":"P",
    "gn:feature_code":"PPL",
    "gn:name":"Unj\u00ed",
    "gn:population":0,
    "gn:timezone":"Asia/Dushanbe",
    "iso:country":"TJ",
    "name:ceb_x_preferred":[
        "Unj\u00ed"
    ],
    "name:fas_x_preferred":[
        "\u0627\u0648\u0646\u062c\u06cc"
    ],
    "name:kor_x_preferred":[
        "\uc6b4\uc9c0"
    ],
    "name:msa_x_preferred":[
        "Undzhi"
    ],
    "name:tgk_x_preferred":[
        "\u04b6\u0430\u043c\u043e\u0430\u0442\u0438 \u0423\u043d\u04b7\u04e3"
    ],
    "name:und_x_variant":[
        "Unzhi",
        "Undzhi",
        "Unj\u00ed",
        "\u0423\u043d\u04b7\u04e3"
    ],
    "name:urd_x_preferred":[
        "\u0627\u0648\u0646\u062c\u06cc"
    ],
    "wof:name":"Unji",
    "wof:placetype":"locality"
},
  "geometry": {"coordinates":[69.70022,40.28305],"type":"Point"}
}