{
  "type": "Feature",
  "properties": {
    "gn:admin1_code":"03",
    "gn:asciiname":"Unji",
    "gn:country_code":"TJ",
    "gn:dem":345,
    "gn:feature_class":"P",
    "gn:feature_code":"PPL",
    "gn:name":"Unj\u00ed",
    "gn:population":0,
    "gn:timezone":"Asia/Dushanbe",
    "iso:country":"TJ",
    "name:und_x_variant":[
        "Unzhi",
        "Undzhi",
        "Unj\u00ed",
        "\u0423\u043d\u04b7\u04e3"
    ],
    "wof:name":"Unji",
    "wof:placetype":"locality"
},
  "geometry": {"coordinates":[69.70022,40.28305],"type":"Point"}
}