{
  "type": "Feature",
  "properties": {
    "gn:admin1_code":"01",
    "gn:asciiname":"Sitvarg",
    "gn:country_code":"TJ",
    "gn:dem":1963,
    "gn:feature_class":"P",
    "gn:feature_code":"PPL",
    "gn:name":"Sitvarg",
    "gn:population":0,
    "gn:timezone":"Asia/Dushanbe",
    "iso:country":"TJ",
    "name:und_x_variant":[
        "\u0421\u0438\u0442\u0432\u0430\u0440\u0433"
    ],
    "wof:name":"Sitvarg",
    "wof:placetype":"locality"
},
  "geometry": {"coordinates":[71.60459,38.44956],"type":"Point"}
}