{
  "type": "Feature",
  "properties": {
    "gn:country":"TJ",
    "gn:fcode":"PPL",
    "gn:pop":8220,
    "iso:country":"TJ",
    "name:unk_x_variant":[
        "\u041f\u0430\u0445\u0442\u0430\u043a\u043e\u0440\u043e\u043d"
    ],
    "name:uzb_x_preferred":[
        "Paxtakoron"
    ],
    "qs:name":"Pakhtakoron",
    "qs:photos_9r":0,
    "qs:photos_sr":0,
    "qs:pop_sr":"5",
    "wof:name":"Pakhtakoron",
    "wof:placetype":"locality",
    "wof:population":8220
},
  "geometry": {"coordinates":[68.74659,40.15709],"type":"Point"}
}