{
  "type": "Feature",
  "properties": {
    "gn:admin1_code":"01",
    "gn:asciiname":"Amaler",
    "gn:country_code":"TJ",
    "gn:dem":2537,
    "gn:feature_class":"P",
    "gn:feature_code":"PPL",
    "gn:name":"Amaler",
    "gn:population":0,
    "gn:timezone":"Asia/Dushanbe",
    "iso:country":"TJ",
    "name:und_x_variant":[
        "Khamale",
        "Amaler"
    ],
    "wof:name":"Amaler",
    "wof:placetype":"locality"
},
  "geometry": {"coordinates":[71.56912,36.78802],"type":"Point"}
}