{
  "type": "Feature",
  "properties": {
    "gn:admin1_code":"RR",
    "gn:asciiname":"Chashmaiborozi",
    "gn:country_code":"TJ",
    "gn:dem":1227,
    "gn:feature_class":"P",
    "gn:feature_code":"PPL",
    "gn:name":"Chashmaiborozi",
    "gn:population":0,
    "gn:timezone":"Asia/Dushanbe",
    "iso:country":"TJ",
    "wof:name":"Chashmaiborozi",
    "wof:placetype":"locality"
},
  "geometry": {"coordinates":[68.54139000000001,38.64391],"type":"Point"}
}