{
  "type": "Feature",
  "properties": {
    "gn:admin1_code":"03",
    "gn:asciiname":"Ravot",
    "gn:country_code":"TJ",
    "gn:dem":463,
    "gn:feature_class":"P",
    "gn:feature_code":"PPL",
    "gn:name":"Ravot",
    "gn:population":0,
    "gn:timezone":"Asia/Dushanbe",
    "iso:country":"TJ",
    "name:und_x_variant":[
        "Robat",
        "Rabat",
        "Ravat",
        "Ravot",
        "\u0420\u0430\u0432\u043e\u0442"
    ],
    "name:uzb_x_preferred":[
        "Rabot"
    ],
    "wof:name":"Ravot",
    "wof:placetype":"locality"
},
  "geometry": {"coordinates":[70.36484,40.53749000000001],"type":"Point"}
}