{
  "type": "Feature",
  "properties": {
    "gn:admin1_code":"03",
    "gn:asciiname":"Mindona",
    "gn:country_code":"TJ",
    "gn:dem":1189,
    "gn:feature_class":"P",
    "gn:feature_code":"PPL",
    "gn:name":"Mindona",
    "gn:population":0,
    "gn:timezone":"Asia/Dushanbe",
    "iso:country":"TJ",
    "name:und_x_variant":[
        "Mindaka",
        "Mindona"
    ],
    "wof:name":"Mindona",
    "wof:placetype":"locality"
},
  "geometry": {"coordinates":[67.95268,39.48284],"type":"Point"}
}