{
  "type": "Feature",
  "properties": {
    "gn:admin1_code":"02",
    "gn:asciiname":"Shakardasht",
    "gn:country_code":"TJ",
    "gn:dem":382,
    "gn:feature_class":"P",
    "gn:feature_code":"PPL",
    "gn:name":"Shakardasht",
    "gn:population":0,
    "gn:timezone":"Asia/Dushanbe",
    "iso:country":"TJ",
    "name:und_x_variant":[
        "\u0428\u0430\u043a\u0430\u0440\u0434\u0430\u0448\u0442"
    ],
    "wof:name":"Shakardasht",
    "wof:placetype":"locality"
},
  "geometry": {"coordinates":[69.1953,37.18505],"type":"Point"}
}