{
  "type": "Feature",
  "properties": {
    "gn:country":"TJ",
    "gn:fcode":"PPLA2",
    "gn:pop":18122,
    "iso:country":"TJ",
    "name:bul_x_preferred":[
        "\u041d\u0443\u0440\u0435\u043a"
    ],
    "name:ceb_x_preferred":[
        "Norak"
    ],
    "name:deu_x_preferred":[
        "Norak"
    ],
    "name:eng_x_preferred":[
        "Nurak"
    ],
    "name:epo_x_preferred":[
        "Norak"
    ],
    "name:est_x_preferred":[
        "Norak"
    ],
    "name:fas_x_preferred":[
        "\u0646\u0627\u0631\u06a9"
    ],
    "name:fin_x_preferred":[
        "Norak"
    ],
    "name:fra_x_preferred":[
        "Nourek"
    ],
    "name:hsb_x_preferred":[
        "Norak"
    ],
    "name:ita_x_preferred":[
        "Norak"
    ],
    "name:jpn_x_preferred":[
        "\u30cc\u30ec\u30fc\u30af"
    ],
    "name:lit_x_preferred":[
        "Nurekas"
    ],
    "name:nld_x_preferred":[
        "Nurak"
    ],
    "name:pol_x_preferred":[
        "Norak"
    ],
    "name:pus_x_preferred":[
        "\u0646\u0648\u0631\u06a9"
    ],
    "name:rus_x_preferred":[
        "\u041d\u0443\u0440\u0435\u043a"
    ],
    "name:tat_x_preferred":[
        "\u041d\u0430\u0440\u04d9\u043a"
    ],
    "name:tgk_x_preferred":[
        "\u041d\u043e\u0440\u0430\u043a"
    ],
    "name:ukr_x_preferred":[
        "\u041d\u0443\u0440\u0435\u043a"
    ],
    "name:unk_x_variant":[
        "Nurek"
    ],
    "name:urd_x_preferred":[
        "\u0646\u0648\u0631\u06a9"
    ],
    "name:uzb_x_preferred":[
        "Norak"
    ],
    "name:zho_x_preferred":[
        "\u52aa\u96f7\u514b"
    ],
    "qs:name":"Norak",
    "qs:photos_9r":0,
    "qs:photos_sr":0,
    "qs:pop_sr":"6",
    "wd:wordcount":217,
    "wof:name":"Norak",
    "wof:placetype":"locality",
    "wof:population":18122
},
  "geometry": {"coordinates":[69.32272,38.38917],"type":"Point"}
}