{
  "type": "Feature",
  "properties": {
    "gn:admin1_code":"01",
    "gn:asciiname":"Shaymak",
    "gn:country_code":"TJ",
    "gn:dem":3844,
    "gn:feature_class":"P",
    "gn:feature_code":"PPL",
    "gn:name":"Shaymak",
    "gn:population":0,
    "gn:timezone":"Asia/Dushanbe",
    "iso:country":"TJ",
    "name:und_x_variant":[
        "Shayman",
        "\u0428\u0430\u0439\u043c\u0430\u043a"
    ],
    "wof:name":"Shaymak",
    "wof:placetype":"locality"
},
  "geometry": {"coordinates":[74.82564000000001,37.53724],"type":"Point"}
}