{
  "type": "Feature",
  "properties": {
    "gn:admin1_code":"01",
    "gn:asciiname":"Roshorv",
    "gn:country_code":"TJ",
    "gn:dem":3055,
    "gn:feature_class":"P",
    "gn:feature_code":"PPL",
    "gn:name":"Roshorv",
    "gn:population":0,
    "gn:timezone":"Asia/Dushanbe",
    "iso:country":"TJ",
    "name:und_x_variant":[
        "Oroshar",
        "Oroshor",
        "Roshorv",
        "\u0420\u043e\u0448\u043e\u0440\u0432"
    ],
    "wof:name":"Roshorv",
    "wof:placetype":"locality"
},
  "geometry": {"coordinates":[72.32467,38.31769],"type":"Point"}
}