{
  "type": "Feature",
  "properties": {
    "gn:admin1_code":"RR",
    "gn:asciiname":"Maykhura",
    "gn:country_code":"TJ",
    "gn:dem":3225,
    "gn:feature_class":"P",
    "gn:feature_code":"PPL",
    "gn:name":"Maykhura",
    "gn:population":0,
    "gn:timezone":"Asia/Dushanbe",
    "iso:country":"TJ",
    "wof:name":"Maykhura",
    "wof:placetype":"locality"
},
  "geometry": {"coordinates":[68.59241999999999,39.02155],"type":"Point"}
}