{
  "type": "Feature",
  "properties": {
    "gn:admin1_code":"02",
    "gn:asciiname":"Navobod",
    "gn:country_code":"TJ",
    "gn:dem":471,
    "gn:feature_class":"P",
    "gn:feature_code":"PPL",
    "gn:name":"Navobod",
    "gn:population":0,
    "gn:timezone":"Asia/Dushanbe",
    "iso:country":"TJ",
    "name:und_x_variant":[
        "Navabad",
        "Navobod",
        "\u041d\u0430\u0432\u043e\u0431\u043e\u0434"
    ],
    "wof:name":"Navobod",
    "wof:placetype":"locality"
},
  "geometry": {"coordinates":[68.88781999999999,37.50374],"type":"Point"}
}