{
  "type": "Feature",
  "properties": {
    "gn:admin1_code":"02",
    "gn:asciiname":"Chirakon",
    "gn:country_code":"TJ",
    "gn:dem":785,
    "gn:feature_class":"P",
    "gn:feature_code":"PPL",
    "gn:name":"Chirakon",
    "gn:population":0,
    "gn:timezone":"Asia/Dushanbe",
    "iso:country":"TJ",
    "wof:name":"Chirakon",
    "wof:placetype":"locality"
},
  "geometry": {"coordinates":[69.08333,38.36667],"type":"Point"}
}