{
  "type": "Feature",
  "properties": {
    "gn:admin1_code":"RR",
    "gn:asciiname":"Shuribolo",
    "gn:country_code":"TJ",
    "gn:dem":895,
    "gn:feature_class":"P",
    "gn:feature_code":"PPL",
    "gn:name":"Shuribolo",
    "gn:population":0,
    "gn:timezone":"Asia/Dushanbe",
    "iso:country":"TJ",
    "wof:name":"Shuribolo",
    "wof:placetype":"locality"
},
  "geometry": {"coordinates":[69.02538,38.48746],"type":"Point"}
}