{
  "type": "Feature",
  "properties": {
    "gn:admin1_code":"RR",
    "gn:asciiname":"Khokhu",
    "gn:country_code":"TJ",
    "gn:dem":1489,
    "gn:feature_class":"P",
    "gn:feature_code":"PPL",
    "gn:name":"Khokhu",
    "gn:population":0,
    "gn:timezone":"Asia/Dushanbe",
    "iso:country":"TJ",
    "wof:name":"Khokhu",
    "wof:placetype":"locality"
},
  "geometry": {"coordinates":[69.26666999999999,38.83333],"type":"Point"}
}